Workbook
Name __________a121: {"'ICo.'!$J$12:$K$20"}
Name _________a121: {"'ICo.'!$J$12:$K$20"}
Name ________a121: {"'ICo.'!$J$12:$K$20"}
Name _______a121: {"'ICo.'!$J$12:$K$20"}
Name _______DCF1: {#N/A,#N/A,FALSE,"DCF Summary";#N/A,#N/A,FALSE,"Casema";#N/A,#N/A,FALSE,"Casema NoTel";#N/A,#N/A,FALSE,"UK";#N/A,#N/A,FALSE,"RCF";#N/A,#N/A,FALSE,"Intercable CZ";#N/A,#N/A,FALSE,"Interkabel P"}
Name ______a121: {"'ICo.'!$J$12:$K$20"}
Name ______DCF1: {#N/A,#N/A,FALSE,"DCF Summary";#N/A,#N/A,FALSE,"Casema";#N/A,#N/A,FALSE,"Casema NoTel";#N/A,#N/A,FALSE,"UK";#N/A,#N/A,FALSE,"RCF";#N/A,#N/A,FALSE,"Intercable CZ";#N/A,#N/A,FALSE,"Interkabel P"}
Name ______fdv2: {"quarterly",#N/A,FALSE,"Income Statement";#N/A,#N/A,FALSE,"print segment";#N/A,#N/A,FALSE,"Balance Sheet";#N/A,#N/A,FALSE,"Annl Inc";#N/A,#N/A,FALSE,"Cash Flow"}
Name ______OCT334: #REF!
Name _____a121: {"'ICo.'!$J$12:$K$20"}
Name _____c: {#N/A,#N/A,FALSE,"Layout Cash Flow"}
Name _____DCF1: {#N/A,#N/A,FALSE,"DCF Summary";#N/A,#N/A,FALSE,"Casema";#N/A,#N/A,FALSE,"Casema NoTel";#N/A,#N/A,FALSE,"UK";#N/A,#N/A,FALSE,"RCF";#N/A,#N/A,FALSE,"Intercable CZ";#N/A,#N/A,FALSE,"Interkabel P"}
Name _____dcf2: {#N/A,#N/A,FALSE,"DCF Summary";#N/A,#N/A,FALSE,"Casema";#N/A,#N/A,FALSE,"Casema NoTel";#N/A,#N/A,FALSE,"UK";#N/A,#N/A,FALSE,"RCF";#N/A,#N/A,FALSE,"Intercable CZ";#N/A,#N/A,FALSE,"Interkabel P"}
Name _____fdv2: {"quarterly",#N/A,FALSE,"Income Statement";#N/A,#N/A,FALSE,"print segment";#N/A,#N/A,FALSE,"Balance Sheet";#N/A,#N/A,FALSE,"Annl Inc";#N/A,#N/A,FALSE,"Cash Flow"}
Name _____key2: #REF!
Name _____OCT334: #REF!
Name ____a121: {"'ICo.'!$J$12:$K$20"}
Name ____c: {#N/A,#N/A,FALSE,"Layout Cash Flow"}
Name ____cc1: {"'I-1 and I-2'!$A$1:$G$190"}
Name ____DAT1: #REF!
Name ____DAT2: #REF!
Name ____DAT3: #REF!
Name ____DAT4: #REF!
Name ____DAT5: #REF!
Name ____DAT6: #REF!
Name ____DAT7: #REF!
Name ____DCF1: {#N/A,#N/A,FALSE,"DCF Summary";#N/A,#N/A,FALSE,"Casema";#N/A,#N/A,FALSE,"Casema NoTel";#N/A,#N/A,FALSE,"UK";#N/A,#N/A,FALSE,"RCF";#N/A,#N/A,FALSE,"Intercable CZ";#N/A,#N/A,FALSE,"Interkabel P"}
Name ____dcf2: {#N/A,#N/A,FALSE,"DCF Summary";#N/A,#N/A,FALSE,"Casema";#N/A,#N/A,FALSE,"Casema NoTel";#N/A,#N/A,FALSE,"UK";#N/A,#N/A,FALSE,"RCF";#N/A,#N/A,FALSE,"Intercable CZ";#N/A,#N/A,FALSE,"Interkabel P"}
Name ____dd1: {"'I-1 and I-2'!$A$1:$G$190"}
Name ____fdv2: {"quarterly",#N/A,FALSE,"Income Statement";#N/A,#N/A,FALSE,"print segment";#N/A,#N/A,FALSE,"Balance Sheet";#N/A,#N/A,FALSE,"Annl Inc";#N/A,#N/A,FALSE,"Cash Flow"}
Name ____Grp16: {#N/A,#N/A,FALSE,"PMTABB";#N/A,#N/A,FALSE,"PMTABB"}
Name ____key1: '[1]#REF'!#REF!
Name ____key2: #REF!
Name ____OCT334: #REF!
Name ____raj1234: {"","","'Curves'!$V$3","'Curves'!$W$3","","","","","",""}
Name ____sm1: {"'I-1 and I-2'!$A$1:$G$190"}
Name ___a121: {"'ICo.'!$J$12:$K$20"}
Name ___c: {#N/A,#N/A,FALSE,"Layout Cash Flow"}
Name ___cc1: {"'I-1 and I-2'!$A$1:$G$190"}
Name ___DAT1: #REF!
Name ___DAT2: #REF!
Name ___DAT3: #REF!
Name ___DAT4: #REF!
Name ___DAT5: #REF!
Name ___DAT6: #REF!
Name ___DAT7: #REF!
Name ___DCF1: {#N/A,#N/A,FALSE,"DCF Summary";#N/A,#N/A,FALSE,"Casema";#N/A,#N/A,FALSE,"Casema NoTel";#N/A,#N/A,FALSE,"UK";#N/A,#N/A,FALSE,"RCF";#N/A,#N/A,FALSE,"Intercable CZ";#N/A,#N/A,FALSE,"Interkabel P"}
Name ___dcf2: {#N/A,#N/A,FALSE,"DCF Summary";#N/A,#N/A,FALSE,"Casema";#N/A,#N/A,FALSE,"Casema NoTel";#N/A,#N/A,FALSE,"UK";#N/A,#N/A,FALSE,"RCF";#N/A,#N/A,FALSE,"Intercable CZ";#N/A,#N/A,FALSE,"Interkabel P"}
Name ___dd1: {"'I-1 and I-2'!$A$1:$G$190"}
Name ___fdv2: {"quarterly",#N/A,FALSE,"Income Statement";#N/A,#N/A,FALSE,"print segment";#N/A,#N/A,FALSE,"Balance Sheet";#N/A,#N/A,FALSE,"Annl Inc";#N/A,#N/A,FALSE,"Cash Flow"}
Name ___fy97: {#N/A,#N/A,FALSE,"FY97";#N/A,#N/A,FALSE,"FY98";#N/A,#N/A,FALSE,"FY99";#N/A,#N/A,FALSE,"FY00";#N/A,#N/A,FALSE,"FY01"}
Name ___Grp16: {#N/A,#N/A,FALSE,"PMTABB";#N/A,#N/A,FALSE,"PMTABB"}
Name ___key1: '[1]#REF'!#REF!
Name ___key2: #REF!
Name ___OCT334: #REF!
Name ___r: {"consolidated",#N/A,FALSE,"Sheet1";"cms",#N/A,FALSE,"Sheet1";"fse",#N/A,FALSE,"Sheet1"}
Name ___raj1234: {"","","'Curves'!$V$3","'Curves'!$W$3","","","","","",""}
Name ___sm1: {"'I-1 and I-2'!$A$1:$G$190"}
Name ___thinkcell11wvTEL6W0W2zDrq5o.quA: #REF!
Name ___wrn1: {#N/A,#N/A,FALSE,"DCF";#N/A,#N/A,FALSE,"WACC";#N/A,#N/A,FALSE,"Sales_EBIT";#N/A,#N/A,FALSE,"Capex_Depreciation";#N/A,#N/A,FALSE,"WC";#N/A,#N/A,FALSE,"Interest";#N/A,#N/A,FALSE,"Assumptions"}

Sheet Charts
A1: SoftBank Group Corp.
A2: year end March ¥m
J4: SBG NAV mix vs. discount to NAV: | S4: Arm % upside/(downside) to March '26 | W4: 0.1 | AS4: % | AT4: %
AR5: 2030 | AS5: 2030 | AT5: 2050 | AV5: Today
J6: Today: | N6: June '24 net equity holdings | O6: % | P6: June '24 NAV | Q6: SBG market cap. today | S6: SBG 5-10yrs: | W6: '30E net equity holdings | X6: % | Y6: '30E NAV | Z6: SBG market cap. '30E | AO6: Arm + AI infrastructure | AR6: =W7 -> 198.35 | AS6: =MROUND(AR6/SUM($AR$6:$AR$11), 0.5%) -> #NUM! | AT6: 0.4 | AV6: =N7/SUM($N$7:$N$15) -> 0.54947368
J7: Arm | N7: =MROUND('Valuation & SBG NAV'!$BG$64, 0.05) -> 130.5 | O7: =N7/$N$20 -> 0.59602649 | P7: =$N$20 -> 218.95 | Q7: =$N$24 -> 149 | S7: Arm | W7: =MROUND(((N7+12)*(1-$W$4))*(1.1)^(3.75), 0.05)+15 -> 198.35 | X7: =W7/$W$20 -> #NUM! | Y7: =$W$20 -> #NUM! | Z7: =$W$24 -> #NUM! | AB7: = using 3.75yrs of Arm expected return on equity from March '26 share price + $15bn Arm accelerator investment. | AO7: Vision Funds | AR7: =SUM(W8:W10) -> 80.4 | AS7: =MROUND(AR7/SUM($AR$6:$AR$11), 0.5%) -> #NUM! | AT7: 0 | AV7: =SUM(N8:N10)/$N$17 -> 0.24168421
J8: SVF1 | N8: =MROUND('Valuation & SBG NAV'!$BG$56, 0.05) -> 24.1 | O8: =N8/$N$20 -> 0.11007079 | S8: SVF1 | W8: 0 | X8: =W8/$W$20 -> #NUM! | AB8: = initial fund life to November '29. | AO8: Domestic telcos + Japanese LLM | AR8: =W11 -> 26.65 | AS8: =MROUND(AR8/SUM($AR$6:$AR$11), 0.5%) -> #NUM! | AT8: 0.15 | AV8: =N11/$N$17 -> 0.083578947
J9: SVF2 | N9: =MROUND('Valuation & SBG NAV'!$BG$59, 0.05) -> 26.95 | O9: =N9/$N$20 -> 0.12308746 | S9: SVF2 | W9: =MROUND(N9*'SVF2'!$BX$11/'SVF2'!$AR$11, 0.05) -> 65.05 | X9: =W9/$W$20 -> #NUM! | AB9: = initial fund life to October '32. | AO9: International telcos | AR9: =SUM(W12:W13) -> 6.1 | AS9: =MROUND(AR9/SUM($AR$6:$AR$11), 0.5%) -> #NUM! | AT9: 0
J10: LatAm Funds | N10: =MROUND('Valuation & SBG NAV'!$BG$60, 0.05) -> 6.35 | O10: =N10/$N$20 -> 0.029002055 | S10: LatAm Funds | W10: =MROUND(N10*W9/N9, 0.05) -> 15.35 | X10: =W10/$W$20 -> #NUM! | AB10: = using SVF2 equivalent timeline. | AO10: Robotics | AR10: =W14 -> #NUM! | AS10: =MROUND(AR10/SUM($AR$6:$AR$11), 0.5%) -> #NUM! | AT10: 0.35
J11: SoftBank Corp. | N11: =MROUND('Valuation & SBG NAV'!$BG$55, 0.05) -> 19.85 | O11: =N11/$N$20 -> 0.090659968 | S11: SoftBank Corp. | W11: =MROUND(N11*(1+'Valuation & SBG NAV'!$BI$147)^(5.5), 0.05) -> 26.65 | X11: =W11/$W$20 -> #NUM! | AB11: = using 5.5yrs of SoftBank KK expected return on equity. | AO11: Others | AR11: =W15 -> 18 | AS11: =MROUND(AR11/SUM($AR$6:$AR$11), 0.5%) -> #NUM! | AT11: 0.1
J12: T-Mobile US | N12: =MROUND('Valuation & SBG NAV'!$BG$62, 0.05) -> 15 | O12: =N12/$N$20 -> 0.068508792 | S12: T-Mobile US | W12: =MROUND(N12*0.33, 0.05) -> 4.95 | X12: =W12/$W$20 -> #NUM! | AB12: = assume exposure more than halved by end of decade: non-core telcos assets.
J13: Deutsche Telekom | N13: =MROUND('Valuation & SBG NAV'!$BG$63, 0.05) -> 2.3 | O13: =N13/$N$20 -> 0.010504681 | S13: Deutsche Telekom | W13: =MROUND(N13*0.5, 0.05) -> 1.15 | X13: =W13/$W$20 -> #NUM! | AB13: = assume exposure more than halved by end of decade: non-core telcos assets.
J14: Alibaba | N14: =MROUND('Valuation & SBG NAV'!$BG$54, 0.05) -> 0.05 | O14: =N14/$N$20 -> 0.00022836264 | S14: Robotics + Japanese LLM | W14: =W35 -> #NUM! | X14: =W14/$W$20 -> #NUM! | AB14: = assumes SVF + non-core telcos sales reinvested in Robotics + Japanese LLM at 5% equity return: less $10bn capital returns and $10bn Arm accelerator investment.
J15: Others | N15: =MROUND('Valuation & SBG NAV'!$BG$65, 0.05) -> 12.4 | O15: =N15/$N$20 -> 0.056633935 | S15: Others | W15: =W36 -> 18 | X15: =W15/$W$20 -> #NUM! | AB15: = assumes 7% equity return on Other assets: less $10bn capital returns.
S16: Capital returns to shareholders | W16: =MROUND(W19-N19, 0.5) -> #NUM! | X16: =W16/$W$20 -> #NUM! | Z16: =W16 -> #NUM!
J17: SBG equity holdings net of asset-backed financing | N17: =SUM(N7:N15) -> 237.5 | S17: SBG equity holdings net of asset-backed financing | W17: =SUM(W7:W13)+SUM(W35:W36) -> #NUM!
J19: Less: SBG TopCo net debt | N19: =MROUND('Valuation & SBG NAV'!$BG$71, 0.05) -> 18.55 | S19: Less: SBG TopCo net debt | W19: =MROUND(W17*W22, 0.05) -> #NUM!
J20: SBG NAV as reported | N20: =N17-N19 -> 218.95 | S20: SBG NAV as reported | W20: =W17-W19 -> #NUM!
J22: LTV | N22: =N19/N17 -> 0.078105263 | S22: LTV | W22: 0.15 | AB22: = SBG calls out an average LTV of 14.5% over last 4-5yrs.
J24: vs. SBG market cap. $bn | N24: =MROUND(FP!$D$13/1000, 0.05) -> 149 | S24: vs. SBG market cap. $bn | W24: =MROUND(W20*(1-W25), 0.05) -> #NUM!
J25: % discount to NAV | N25: =1-(N24/N20) -> 0.31947933 | S25: % discount to NAV | W25: 0.25
S27: Assets monetised by end of decade: | X27: % equity return:
S28: SVF1 | W28: =N8-W8 -> 24.1 | X28: ='SVF1'!$AS$12 -> 0.035 | Z28: =X28*W28/$W$33 -> -0.071483051
S29: SVF2 | W29: =N9-W9 -> -38.1 | X29: ='SVF2'!$AS$14 -> 0.05 | Z29: =X29*W29/$W$33 -> 0.16144068
S30: LatAm Funds | W30: =N10-W10 -> -9 | X30: ='SVF Segment'!$AP$983 -> 0.09 | Z30: =X30*W30/$W$33 -> 0.068644068
S31: T-Mobile US | W31: =N12-W12 -> 10.05 | X31: ='Investment Business Of HoldCo'!$AS$138 -> 0.08 | Z31: =X31*W31/$W$33 -> -0.068135593
S32: Deutsche Telekom | W32: =N13-W13 -> 1.15 | X32: ='Investment Business Of HoldCo'!$AS$187 -> 0.08 | Z32: =X32*W32/$W$33 -> -0.0077966102
S33: Total | W33: =SUM(W28:W32) -> -11.8 | X33: =SUM(Z28:Z32) -> 0.082669492
S35: Total value of monetised assets at 2030 = | W35: =MROUND((SUM(N8:N10, N12:N14)-SUM(W8:W10, W12:W13))*(1+$X$33)^(5.5), 0.05) -> #NUM!
S36: Total value of Others at 2030 = | W36: =MROUND(N15*(1.07)^(5.5), 0.05) -> 18
J76: SBG TopCo de-grossing post-Covid:
N78: FY19 | O78: FY20 | P78: FY21 | Q78: FY22 | R78: FY23
N79: Mar. '20 | O79: Mar. '21 | P79: Mar. '22 | Q79: Mar. '23 | R79: Mar. '24
J81: Gross debt $bn | N81: ='Net debt & LTV'!BJ79/1000 -> 59.990205 | O81: ='Net debt & LTV'!BK79/1000 -> 55.62596 | P81: ='Net debt & LTV'!BL79/1000 -> 60.807558 | Q81: ='Net debt & LTV'!BM79/1000 -> 47.229761 | R81: ='Net debt & LTV'!BN79/1000 -> 44.887431
J82: Cash $bn | N82: ='Net debt & LTV'!BJ171/1000 -> 13.373013 | O82: ='Net debt & LTV'!BK171/1000 -> 17.597119 | P82: ='Net debt & LTV'!BL171/1000 -> 20.447961 | Q82: ='Net debt & LTV'!BM171/1000 -> 25.870396 | R82: ='Net debt & LTV'!BN171/1000 -> 14.522614
J83: Net debt $bn | N83: ='Net debt & LTV'!BJ245/1000 -> 46.617192 | O83: ='Net debt & LTV'!BK245/1000 -> 38.028841 | P83: ='Net debt & LTV'!BL245/1000 -> 40.359596 | Q83: ='Net debt & LTV'!BM245/1000 -> 21.359365 | R83: ='Net debt & LTV'!BN245/1000 -> 30.364817
J85: LTV % | N85: ='Valuation & SBG NAV'!BY37 -> 0.14183835 | O85: ='Valuation & SBG NAV'!BZ37 -> 0.12203947 | P85: ='Valuation & SBG NAV'!CA37 -> 0.20362381 | Q85: ='Valuation & SBG NAV'!CB37 -> 0.11027095 | R85: ='Valuation & SBG NAV'!CC37 -> 0.08437706
J106: SBG TopCo de-grossing post-Covid:
J108: TopCo gross cash | M108: =MROUND('Net debt & LTV'!$AP$171/1000, 0.1) -> 14.5
I109: Add: | J109: DT exercise of T-Mobile call options | M109: =MROUND(((28.2*FP!$G$8)+(6.7*103))/1000, 0.1) -> 6.8
I110: Add: | J110: 2yrs telcos divis | M110: 2.5 | N110: = based on current equity holdings adjusted for 35m T-Mobile shares being called away by DT in June '24.
I111: Add: | J111: SVF distributions | M111: =MROUND(('SVF Segment'!$AO$672*SUM('SVF1'!$AR$17:$AU$17, 'SVF1'!$AW$17:$AZ$17)+SUM('SVF2'!$AR$19:$AU$19, 'SVF2'!$AW$19:$AZ$19)+SUM('SVF Segment'!$AR$988:$AU$988, 'SVF Segment'!$AW$988:$AZ$988))/1000, 0.1) -> 7.5 | N111: = Arete SVF modelling.
I112: Less: | J112: Arm payment to SVF1 (net) | M112: =-MROUND(0.45*12, 0.1) -> -5.4 | N112: = third-party 45% ordinary equity share of remaining $12bn Arm distribution.
I113: Less: | J113: Bond maturities | M113: =-MROUND(1900/FP!$G$4, 0.1) -> -12.3 | N113: = 1,900bn yen debt maturities within 2yrs converted to US$bn.
I114: Less: | J114: Wayve investment | M114: -0.75 | N114: = per FT article May '24: see comment.
I115: Less: | J115: GreenBox JV commitment | M115: -3.2 | N115: = per IR commentary.
I116: Equals: | J116: TopCo firepower | M116: =MROUND(SUM(M108:M115), 0.1) -> 9.6
J137: SoftBank Vision Funds Cumulative Investment Return vs. Acquisition Cost:
J139: SVF1 AC | M139: ='SVF Segment'!$AO$730/1000 -> 89.6
J140: SVF1 IR | M140: ='SVF Segment'!$AO$731/1000 -> 106.3
J141: Adj. SV1 IR | M141: =M140-(16.1-8.2)-(('SVF1'!$AO$129-'SVF1'!$AO$145)/1000) -> 89.9
J142: SVF2 AC | M142: ='SVF Segment'!$AO$890/1000 -> 52.3
J143: SVF2 IR | M143: ='SVF Segment'!$AO$891/1000 -> 33.3
J144: LatAm AC | M144: ='SVF Segment'!$AO$992/1000 -> 7.4
J145: LatAm IR | M145: ='SVF Segment'!$AO$993/1000 -> 6.3
J166: SoftBank Vision Funds Fair Values vs. SoftBank Group Exposure:
J168: SVF1 FV | M168: ='SVF Segment'!$AR$726/1000 -> 41.8
J169: SVF1 SBG | M169: ='SVF Segment'!$AR$612/1000 -> 22.5
J170: SVF2 FV | M170: ='SVF Segment'!$AR$245/1000 -> 25.58
J171: SVF2 SBG | M171: ='SVF Segment'!$AR$251/1000 -> 25.58
J172: LatAm FV | M172: ='SVF Segment'!$AR$246/1000 -> 5.8
J173: LatAM SBG | M173: ='SVF Segment'!$AR$252/1000 -> 5.74
J195: SoftBank KK Revenue and EBITDA exposure:
M197: Revenue | N197: EBITDA
J198: Consumer | M198: ='Consolidated KK'!AM16 -> 0.4683906 | N198: ='Consolidated KK'!AM84 -> 0.53467305
J199: Enterprise | M199: ='Consolidated KK'!AM17 -> 0.12818976 | N199: ='Consolidated KK'!AM85 -> 0.1935556
J200: Distribution | M200: ='Consolidated KK'!AM18 -> 0.10379154 | N200: ='Consolidated KK'!AM86 -> 0.01899102
J201: Media & EC | M201: ='Consolidated KK'!AM20 -> 0.26175313 | N201: ='Consolidated KK'!AM88 -> 0.22688863
J202: Financial | M202: ='Consolidated KK'!AM21 -> 0.038129276 | N202: ='Consolidated KK'!AM89 -> 0.0069203669
J203: Other | M203: ='Consolidated KK'!AM22 -> 0.027941109 | N203: ='Consolidated KK'!AM90 -> 0.0058263233
J224: SVF1 capital structure evolution over time:
J245: SVF1 ordinary equity % of high watermark:
J266: SVF2 current vs. future MOIC vs. 1.3x hurdle rate for MgmtCo distributions:
J268: MOIC today | L268: 0.6 | M268: 1.3
J269: End of Fund life MOIC | L269: 0.9 | M269: 1.3
J270: MgmtCo hurdle rate | L270: 1.3
L272: MOIC today | M272: End of Fund life MOIC
L273: 0.6 | M273: 0.9
L274: 1.3 | M274: 1.3
J295: January '25 charts:
J297: $bn
J298: CY'24 cash | L298: =MROUND('TopCo Net debt waterfall'!$AT$83/1000, 1) -> 21
J299: OpenAI | L299: -20
J300: Stargate | L300: -15
J301: Arm | L301: -1.875
J302: Deficit | L302: =SUM(L298:L301) -> -15.875
J303: Northstar | L303: 3.5
J304: KK divi. | L304: 1
J305: SVF dist. | L305: 10
J306: Bonds | L306: 12.5
J307: ABF | L307: 5
J308: CY'25 cash | L308: =SUM(L302:L307) -> 16.125
J318: OpenAI revenues:
J320: $bn
J321: 2022 | K321: 0.028
J322: 2023 | K322: 2 | M322: =K322/K321-1 -> 70.428571
J323: 2024E | K323: 3.7 | M323: =K323/K322-1 -> 0.85
J324: 2025E | K324: 11.6 | L324: 3 | M324: =K324/K323-1 -> 2.1351351
J345: Software Co.'s comps.:
J347: $bn
...

Sheet New SBG Valuation
A1: SoftBank Group Corp.
A2: year end March ¥m
B4: * Arm position net of $13.5bn margin loan. | E4: = need to update all-in values "today" every time before publication..!
B6: Company | C6: Public vs. private | D6: % stake | E6: All-in value today $bn | F6: P.F. value today $bn | G6: % SBG market cap. today | H6: Valuation methodology today | I6: All-in value 2030 $bn | J6: SBG value 2030 $bn | K6: 2030 valuation methodology | L6: delta vs. previous
B7: Arm* | C7: Public | D7: 0.9 | E7: 132 | F7: =D7*E7-20 -> 98.8 | G7: =F7/(FP!$D$13/1000) -> 0.66303947 | H7: 90% of Arm's $xxxbn market cap. less $13.5bn margin loan. | I7: =MROUND($E$7*(265/FP!$L$5), 5) -> 280 | J7: =D7*I7-25 -> 227 | K7: 38x EV/EBIT in Mar. '31E less ABF. | L7: =J7-'[63]New SBG Valuation'!J7 -> -11.5 | M7: = uses Arm Valuation tab Method 4: 38x peer group EV/EBIT multiple -> $265 per Arm share in Mar. '31E.
B8: Ampere Computing | C8: Private | D8: 1 | E8: 6.5 | F8: =D8*E8 -> 6.5 | G8: =F8/(FP!$D$13/1000) -> 0.043621017 | H8: All-in $6.5bn acquisition value. | I8: 27.5 | J8: =D8*I8 -> 27.5 | K8: 30x P/E in Mar. '31E on "in-house" CPU chip unit. | L8: =J8-'[63]New SBG Valuation'!J8 -> 0
B9: Graphcore | C9: Private | D9: 1 | E9: 0.65 | F9: =D9*E9 -> 0.65 | G9: =F9/(FP!$D$13/1000) -> 0.0043621017 | H9: Est. all-in acquisition value. | I9: ??? | J9: ??? | K9: Optionality on "in-house" accelerator.
B10: SoftBank "in-house" semis franchise (A) | F10: =SUM(F7:F9) -> 105.95 | G10: =F10/(FP!$D$13/1000) -> 0.71102258 | J10: =SUM(J7:J8) -> 254.5 | L10: =J10-'[63]New SBG Valuation'!J10 -> -11.5
B11: OpenAI | C11: Private | D11: 0.1325 | E11: 730 | F11: ='Valuation & SBG NAV'!$BU$57 -> 109.425 | G11: =F11/(FP!$D$13/1000) -> 0.73434305 | H11: $730bn pre-money CY26 valuation. | I11: =MROUND(17.5*200, 5) -> 3500 | J11: =D11*I11-13.25%*76-'OpenAI Valuation table'!$L$79+3*(1.03)^(5) -> 409.95442 | K11: 12.5x EV/Sales in FY30E less MgmtCo 17.25%. | L11: =J11-'[63]New SBG Valuation'!J11 -> 73.75442 | M11: = adjusted for 13% P.F. share of capital contributions to cover remaining $76bn of $218bn '26E-'30E cash burn not covered by CY25 ($41bn) or CY26 ($110bn) funding rounds; less MgmtCo 17.25% share.
B12: DigitalBridge | C12: Public | D12: 1 | E12: 2.9 | F12: =D12*E12 -> 2.9 | G12: =F12/(FP!$D$13/1000) -> 0.019461685 | H12: $16/share transaction value. | I12: =E12*(1.1)^(5) -> 4.670479 | J12: =D12*I12 -> 4.670479 | K12: 10% p.a. from $2.9bn transaction value. | L12: =J12-'[63]New SBG Valuation'!J12 -> 0
B13: Stargate | C13: Private | D13: 0.5 | E13: 1 | F13: =D13*E13 -> 0.5 | G13: =F13/(FP!$D$13/1000) -> 0.0033554629 | H13: $1bn SoftBank & OpenAI equity to SB Energy. | I13: =85%*20*2*2500*85%/1000 -> 72.25 | J13: =D13*I13-P14-U14-3*2 -> 27.619321 | K13: 20x EV/EBIT in FY30E less debt, preferreds, etc. | L13: =J13-'[63]New SBG Valuation'!J13 -> -3.8806786 | M13: = shifted from "neocloud" to "colocation" valuation approach -> assume OpenAI PBC buys and owns chips at SB Energy data centers.
B14: SoftBank "core" AI assets (B) | F14: =SUM(F11:F13) -> 112.825 | G14: =F14/(FP!$D$13/1000) -> 0.7571602 | J14: =SUM(J11:J13) -> 442.24422 | L14: =J14-'[63]New SBG Valuation'!J14 -> 69.873741 | M14: Ares $800m "preferreds" in '30E -> | P14: =MROUND(0.8*(1.1)^(5), 0.5) -> 1.5 | R14: OpenAI PBC minority equity in '30E -> | U14: =0.5*(1.15)^(5) -> 1.0056786 | W14: + 3 years of $2bn p.a. equity contribution by SoftBank TopCo.
B15: SoftBank core semis + AI gross asset value = (A+B) | F15: =F10+F14 -> 218.775 | G15: =F15/(FP!$D$13/1000) -> 1.4681828 | J15: =J10+J14 -> 696.74422 | L15: =J15-'[63]New SBG Valuation'!J15 -> 58.373741
B16: Less: TopCo net debt | F16: =-MROUND('Valuation & SBG NAV'!$BU$71, 0.5) -> -77 | G16: =F16/(FP!$D$13/1000) -> -0.51674128 | J16: =($F$16)*(1.04)^(5) -> -93.682273 | L16: =J16-'[63]New SBG Valuation'!J16 -> -6.9217889
B17: SoftBank core semis + AI equity value (C) | F17: =SUM(F15:F16) -> 141.775 | G17: =F17/(FP!$D$13/1000) -> 0.9514415 | J17: =SUM(J15:J16) -> 603.06195 | L17: =J17-'[63]New SBG Valuation'!J17 -> 51.451952
B18: ABB Robotics | C18: Private | D18: 0 | E18: 5.4 | F18: =D18*E18 -> 0 | G18: =F18/(FP!$D$13/1000) -> 0 | H18: SoftBank transaction value. | I18: =E18*(1.2)^(5) -> 13.436928 | J18: =I18 -> 13.436928 | K18: 20% p.a. from $5.4bn transaction value. | L18: =J18-'[63]New SBG Valuation'!J18 -> 0
B19: Symbotic | C19: Public | D19: 0.068 | E19: 32.5 | F19: =D19*E19 -> 2.21 | G19: =F19/(FP!$D$13/1000) -> 0.014831146 | H19: Market value. | I19: =MROUND((70/54.5)*E19, 0.25) -> 41.75 | J19: =D19*I19 -> 2.839 | K19: Arete DCF. | L19: =J19-'[63]New SBG Valuation'!J19 -> -0.017
B20: GreenBox JV | C20: Private | D20: 0.65 | E20: 0 | F20: =D20*E20 -> 0 | G20: =F20/(FP!$D$13/1000) -> 0 | H20: n/a | I20: =2300*100/35/1000 -> 6.5714286 | J20: =D20*I20 -> 4.2714286 | K20: Arete DCF. | L20: =J20-'[63]New SBG Valuation'!J20 -> 0
B21: AutoStore | C21: Public | D21: 0.4 | E21: 3.65 | F21: =D21*E21 -> 1.46 | G21: =F21/(FP!$D$13/1000) -> 0.0097979516 | H21: Market value. | I21: =MROUND((20.5/10.5)*E21, 0.25) -> 7.25 | J21: =D21*I21 -> 2.9 | K21: Arete DCF. | L21: =J21-'[63]New SBG Valuation'!J21 -> 0.2
B22: Nuro | C22: Private | D22: =F22/E22 -> 0.18333333 | E22: 6 | F22: =MROUND(54%*2.1, 0.1) -> 1.1 | G22: =F22/(FP!$D$13/1000) -> 0.0073820183 | H22: $6bn Series E funding round valuation. | I22: =E22*(1.25)^(5) -> 18.310547 | J22: =D22*I22 -> 3.3569336 | K22: 25% p.a. from $6bn Aug. '25 valuation. | L22: =J22-'[63]New SBG Valuation'!J22 -> 3.3569336
B23: Wayve | C23: Private | D23: =F23/E23 -> 0.15116279 | E23: 8.6 | F23: 1.3 | G23: =F23/(FP!$D$13/1000) -> 0.0087242035 | H23: Arete ests. | I23: =E23*(1.25)^(5) -> 26.245117 | J23: =D23*I23 -> 3.9672852 | K23: 25% p.a. from $8bn Oct. '25 valuation. | L23: =J23-'[63]New SBG Valuation'!J23 -> 0
B24: Skild AI | C24: Private | D24: =F24/E24 -> 0.12857143 | E24: 14 | F24: 1.8 | G24: =F24/(FP!$D$13/1000) -> 0.012079666 | H24: Arete ests. | I24: =E24*(1.125)^(5) -> 25.228455 | J24: =D24*I24 -> 3.2436584 | K24: 12.5% p.a. from $8bn Oct. '25 valuation.
B25: Boston Dynamics | C25: Private | D25: 0.125 | E25: 1.1 | F25: =D25*E25 -> 0.1375 | G25: =F25/(FP!$D$13/1000) -> 0.00092275229 | H25: Hyundai Motor Group Dec. '20 transaction value. | I25: =0.5*39 -> 19.5 | J25: =D25*I25 -> 2.4375 | K25: 50% discount on Figure AI $39bn mark. | L25: =J25-'[63]New SBG Valuation'!J24 -> 0
B26: Autonomous and Robotics (D) | F26: =SUM(F18:F25) -> 8.0075 | G26: =F26/(FP!$D$13/1000) -> 0.053737738 | J26: =SUM(J18:J25) -> 36.452734 | L26: =J26-'[63]New SBG Valuation'!J25 -> 6.783592
B27: NVIDIA | C27: Public | D27: ='SoftBank Other (13F)'!$AX$50 -> 0.0013214179 | E27: 4600 | F27: 0 | G27: 0 | H27: Market value. | I27: =MROUND(E27*(1.1)^(5), 5) -> 7410 | J27: 0 | K27: Fully exited. | L27: =J27-'[63]New SBG Valuation'!J26 -> 0
B28: Intel | C28: Public | D28: =F28/E28 -> 0.013391304 | E28: 225 | F28: =2*34.65/23 -> 3.0130435 | G28: =F28/(FP!$D$13/1000) -> 0.020220311 | H28: Market value. | I28: =MROUND(E28*(1.05)^(5), 5) -> 285 | J28: =D28*I28 -> 3.8165217 | K28: 5% p.a. growth. | L28: =J28-'[63]New SBG Valuation'!J27 -> -0.031461498
B29: TSMC | C29: Public | D29: n/m | E29: 1650 | F29: ='SoftBank Other (13F)'!$BA$8/1000 -> 0.743581 | G29: =F29/(FP!$D$13/1000) -> 0.0049901169 | H29: Market value. | I29: =MROUND(E29*(1.08)^(5), 5) -> 2425 | J29: =MROUND(F29*(1.08)^(5), 0.1) -> 1.1 | K29: 8% p.a. growth. | L29: =J29-'[63]New SBG Valuation'!J28 -> 0.4674202
B30: Oracle | C30: Public | D30: n/m | E30: 695 | F30: 0 | G30: 0 | H30: Market value. | I30: =E30 -> 695 | J30: =F30 -> 0 | K30: Fully exited. | L30: =J30-'[63]New SBG Valuation'!J29 -> 0
B31: Publicly-listed semis + AI stakes (E) | F31: =SUM(F27:F30) -> 3.7566245 | G31: =F31/(FP!$D$13/1000) -> 0.025210428 | J31: =SUM(J27:J30) -> 4.9165217 | L31: =J31-'[63]New SBG Valuation'!J30 -> 0.4359587
B32: ByteDance | C32: Private | D32: =MROUND(54%*3.25%, 0.05%) -> 0.0175 | E32: =MROUND('SVF1'!$AX$129/0.0325/1000, 5) -> 505 | F32: =D32*E32 -> 8.8375 | G32: =F32/(FP!$D$13/1000) -> 0.059307806 | H32: SVF1 mark which excl. TikTok U.S. value. | I32: =MROUND(8*50%*((95*1.08^(7))+(0.65*1.5*30)), 5) -> 770 | J32: =D32*I32 -> 13.475 | K32: 8x FY30E EBITDA on 50% EBITDA margin. | L32: =J32-'[63]New SBG Valuation'!J31 -> 0 | M32: = TikTok International revenue assumption based on 35% discount to Facebook/Instagram $30 ARPU and 1.5bn ex. China users.
B33: Revolut | C33: Private | D33: =F33/E33 -> 0.017923077 | E33: 65 | F33: ='SVF2'!$AX$147/1000 -> 1.165 | G33: =F33/(FP!$D$13/1000) -> 0.0078182285 | H33: FT reported $65bn funding round. | I33: =120*(1.1)^(5) -> 193.2612 | J33: =D33*I33 -> 3.4638354 | K33: Grey market IPO value (IG) + 10% p.a. | L33: =J33-'[63]New SBG Valuation'!J32 -> -1.9474782
B34: Perplexity | C34: Private | D34: =F34/E34 -> 0.0045282738 | E34: 20 | F34: =(20/18)*'SVF2'!$AX$146/1000 -> 0.090565476 | G34: =F34/(FP!$D$13/1000) -> 0.00060777819 | H34: $20bn funding round. | I34: =MROUND(0.5*E34*I11/E11, 5) -> 50 | J34: =I34*F34/E34 -> 0.22641369 | K34: Half value creation of OpenAI. | L34: =J34-'[63]New SBG Valuation'!J33 -> -0.090565476
B35: Other AI stakes (F) | F35: =SUM(F32:F34) -> 10.093065 | G35: =F35/(FP!$D$13/1000) -> 0.067733813 | J35: =SUM(J32:J34) -> 17.165249 | L35: =J35-'[63]New SBG Valuation'!J34 -> -2.0380437
B36: SoftBank Corp. (G) | C36: Public | D36: 0.4025 | E36: =F36/D36 -> 45.722225 | F36: ='Valuation & SBG NAV'!$BP$55 -> 18.403196 | G36: =F36/(FP!$D$13/1000) -> 0.12350248 | H36: Market value of 40% less $5bn+ K.K. margin loan. | I36: =MROUND(E36*(1.1)^(5), 5) -> 75 | J36: =D36*I36-7.75 -> 22.4375 | K36: 10% p.a. less K.K. ABF. | L36: =J36-'[63]New SBG Valuation'!J35 -> -6.775 | M36: = additional margin loan.
B37: Total SoftBank "core" equity (C+D+E+F) | F37: =F17+F26+F31+F35+F36 -> 182.03539 | G37: =F37/(FP!$D$13/1000) -> 1.221626 | J37: =J17+J26+J31+J35+J36 -> 684.03395 | L37: =J37-'[63]New SBG Valuation'!J36 -> 49.858459
B38: SoftBank "non-core"
B39: International telcos | F39: =SUM('P.F. NAV Table'!$E$16:$E$17) -> 5.8124681 | G39: =F39/(FP!$D$13/1000) -> 0.039007042 | H39: Market value net of ABF. | J39: 0 | L39: =J39-'[63]New SBG Valuation'!J38 -> -13.679841
B40: Publicly-listed SVF assets | F40: ='Alt. SoftBank Valuation'!$H$11 -> 13.505 | G40: =F40/(FP!$D$13/1000) -> 0.090631052 | H40: Market value. | J40: =F40*(1.125)^(5) -> 24.336449 | L40: =J40-'[63]New SBG Valuation'!J39 -> 3.3690822 | M40: = upgrade est. returns on lower Coupang starting price.
B41: Privately held SVF assets** | F41: ='Alt. SoftBank Valuation'!$H$21-SUM(F22:F23) -> 16.92417 | G41: =F41/(FP!$D$13/1000) -> 0.11357685 | H41: Private marks. | J41: =F41*(1.1)^(5) -> 27.256546 | L41: =J41-'[63]New SBG Valuation'!J40 -> -21.500723 | M41: = faster pace of PayPay monetisation to fund OpenAI PBC transaction.
B42: Other non-core publicly listed stakes | F42: ='Alt. SoftBank Valuation'!$H$12 -> 2.2121829 | G42: =F42/(FP!$D$13/1000) -> 0.014845795 | H42: Market value. | J42: =F42*(1.05)^(5) -> 2.8233683 | L42: =J42-'[63]New SBG Valuation'!J41 -> 0.061547392
B43: Other "non-core" | F43: =F45-F37-SUM(F39:F42) -> 7.7263502 | G43: =F43/(FP!$D$13/1000) -> 0.051850963 | J43: =F43*(1.05)^(5) -> 9.8609984 | L43: =J43-'[63]New SBG Valuation'!J42 -> 12.974524
B44: Total SoftBank "non-core" equity | F44: =SUM(F39:F43) -> 46.180172 | G44: =F44/(FP!$D$13/1000) -> 0.3099117 | J44: =SUM(J39:J43) -> 64.277361 | K44: 5% p.a. growth for "non-core". | L44: =J44-'[63]New SBG Valuation'!J43 -> -21.888936
B45: Total SoftBank "core" + "non-core" equity | F45: ='Valuation & SBG NAV'!$BU$73 -> 228.21556 | G45: =F45/(FP!$D$13/1000) -> 1.5315377 | J45: =J37+J44 -> 748.31131 | L45: =J45-'[63]New SBG Valuation'!J44 -> 27.969523
B46: Discount-to-NAV | F46: =MROUND(1-FP!$D$13/1000/F45, 0.5%) -> 0.345 | J46: 0.1
B47: Target 2030 equity value | J47: =J45*(1-J46) -> 673.48018
B48: 2030 target price | J48: =MROUND(1000*FP!$G$4*J47/'Valuation & SBG NAV'!$BU$44, 250) -> 18250
B49: % total return | J49: =J48/FP!$D$9-1 -> 3.5106278
B50: % equity return p.a. | J50: =(J48/FP!$D$9)^(1/5)-1 -> 0.35159756
B52: Mar. '27E target price -> | I52: % CAGR | J52: Mar. '27E
I53: 0.1 | J53: =MROUND($J$48/(1+I53)^(4), 100) -> 12500
I54: =I53+2.5% -> 0.125 | J54: =MROUND($J$48/(1+I54)^(4), 100) -> 11400
I55: =I54+2.5% -> 0.15 | J55: =MROUND($J$48/(1+I55)^(4), 100) -> 10400
I56: =I55+2.5% -> 0.175 | J56: =MROUND($J$48/(1+I56)^(4), 100) -> 9600
I57: =I56+2.5% -> 0.2 | J57: =MROUND($J$48/(1+I57)^(4), 100) -> 8800
I58: =I57+2.5% -> 0.225 | J58: =MROUND($J$48/(1+I58)^(4), 100) -> 8100
I59: =I58+2.5% -> 0.25 | J59: =MROUND($J$48/(1+I59)^(4), 100) -> 7500

Sheet Alt. SoftBank Valuation
A1: SoftBank Group Corp.
A2: year end March ¥m
B4: SoftBank March '26 valuation -> | H4: = must update formula at each note/publication.
G5: $m | H5: $bn
B6: SoftBank market cap. | G6: =MROUND(FP!$D$5*'Valuation & SBG NAV'!$BP$39/FP!$G$4, 5) -> 149010 | H6: =G6/1000 -> 149.01
B7: Less: International telcos net of ABF | G7: =MROUND(1000*H7, 5) -> 0 | H7: ='Valuation & SBG NAV'!$BU$62+'Valuation & SBG NAV'!$BU$63 -> 0
B8: SVF1 = 55% | G8: =MROUND('SVF1'!$AZ$39*'SVF1'!$AZ$74, 5) -> 7975 | H8: =G8/1000 -> 7.975
B9: SVF2 = 100% | G9: ='SVF2'!$AZ$68 -> 4505 | H9: =G9/1000 -> 4.505
B10: LatAm = 100% | G10: ='LatAm Funds'!$AZ$7 -> 1025 | H10: =G10/1000 -> 1.025
B11: Less: publicly listed SVF stakes | G11: =SUM(G8:G10) -> 13505 | H11: =SUM(H8:H10) -> 13.505
B12: Less: other publicly listed stakes | G12: =SUM('SoftBank Other (13F)'!BA10:BA15) -> 2212.1829 | H12: =G12/1000 -> 2.2121829
B13: Less: SVF privately held at $50c on the $1 | G13: =MROUND(G21*50%, 5) -> 9665 | H13: =G13/1000 -> 9.665
B14: SoftBank net market cap. | G14: =G6-G7-SUM(G11:G13) -> 123627.82 | H14: =H6-H7-SUM(H11:H13) -> 123.62782
B15: Add: TopCo net debt | G15: =MROUND(1000*H15, 5) -> 77000 | H15: =MROUND('Valuation & SBG NAV'!$BU$71, 0.5) -> 77
B16: SoftBank net enterprise value | G16: =SUM(G14:G15) -> 200627.82 | H16: =SUM(H14:H15) -> 200.62782 | I16: =100*H16/F52 -> 85.186965
B17: Enterprise value with SVF private fully-valued | G17: =G16-G13 -> 190962.82 | H17: =H16-H13 -> 190.96282 | I17: =100*H17/F52 -> 81.083187
G19: $m | H19: $bn
B20: Total SVF excl. OpenAI, ByteDance and Revolut | G20: =MROUND(1000*H20, 5) -> 32830 | H20: ='Valuation & SBG NAV'!$BU$61-'Valuation & SBG NAV'!$BU$57-(('SVF1'!$AZ$39*'SVF1'!$AZ$129+'SVF2'!$AZ$147)/1000) -> 32.82917
B21: Privately held assets by Vision Funds | G21: =G20-G11 -> 19325 | H21: =H20-H11 -> 19.32417
G23: $m | H23: $bn
B24: NVIDIA | G24: ='SoftBank Other (13F)'!BA6 -> 0 | H24: =G24/1000 -> 0
B25: TSMC | G25: ='SoftBank Other (13F)'!BA8 -> 743.581 | H25: =G25/1000 -> 0.743581
B26: Oracle | G26: ='SoftBank Other (13F)'!BA9 -> 0 | H26: =G26/1000 -> 0
B27: Total large cap. AI stocks | G27: =SUM(G24:G26) -> 743.581 | H27: =SUM(H24:H26) -> 0.743581
B29: * Arm position net of $13.5bn margin loan.
B30: Company | C30: Public vs. private | D30: % stake | E30: All-in value $bn | F30: SBG value $bn | G30: % SBG market cap. today | H30: Valuation methodology today
B31: Arm* | C31: Public | D31: 0.9 | E31: 162 | F31: =D31*E31-8.5 -> 137.3 | G31: =F31/$H$6 -> 0.92141467 | H31: SoftBank's 90% share of Arm's $162bn market cap. less $13.5bn margin loan.
B32: Ampere Computing | C32: Private | D32: 1 | E32: 6.5 | F32: =D32*E32 -> 6.5 | G32: =F32/$H$6 -> 0.043621233 | H32: All-in SoftBank acquisition value.
B33: Graphcore | C33: Private | D33: 1 | E33: 0.65 | F33: =D33*E33 -> 0.65 | G33: =F33/$H$6 -> 0.0043621233 | H33: Est. all-in SoftBank acquisition value.
B34: SoftBank "in-house" semis franchise | F34: =SUM(F31:F33) -> 144.45 | G34: =F34/$H$6 -> 0.96939803
B35: OpenAI | C35: Private | D35: ='SoftBank Other (13F)'!$BA$31/1000/FP!$Q$11 -> 0.1088 | E35: =FP!$Q$11 -> 500 | F35: =D35*E35 -> 54.4 | G35: =F35/$H$6 -> 0.36507617 | H35: $500bn Sep. '25 employee share sale valuation.
B36: SoftBank Corp. | C36: Public | D36: 0.4025 | E36: 71.25 | F36: ='Valuation & SBG NAV'!$BP$55 -> 18.403196 | G36: =F36/$H$6 -> 0.12350309 | H36: Market value of 40.25% less $5bn+ K.K. margin loan.
B37: Stargate | C37: Private | D37: 0.5 | E37: 0 | F37: =D37*E37 -> 0 | G37: =F37/$H$6 -> 0 | H37: n/a
B38: NVIDIA | C38: Public | D38: ='SoftBank Other (13F)'!$AX$50 -> 0.0013214179 | E38: =MROUND(F38/D38, 5) -> 0 | F38: ='SoftBank Other (13F)'!$BA$6/1000 -> 0 | G38: =F38/$H$6 -> 0 | H38: Market value.
B39: Intel | C39: Public | D39: =F39/E39 -> 0.018629929 | E39: 172 | F39: =2*36.85/23 -> 3.2043478 | G39: =F39/$H$6 -> 0.021504247 | H39: Market value.
B40: TSMC | C40: Public | D40: n/m | E40: 1000 | F40: ='SoftBank Other (13F)'!$BA$8/1000 -> 0.743581 | G40: =F40/$H$6 -> 0.0049901416 | H40: Market value.
B41: Oracle | C41: Public | D41: n/m | E41: 705 | F41: ='SoftBank Other (13F)'!$BA$9/1000 -> 0 | G41: =F41/$H$6 -> 0 | H41: Market value.
B42: "Other" semis holdings | F42: =SUM(F38:F41) -> 3.9479288
B43: ByteDance | C43: Private | D43: =MROUND(54%*3.25%, 0.05%) -> 0.0175 | E43: =MROUND('SVF1'!$AX$129/0.0325/1000, 5) -> 505 | F43: =D43*E43 -> 8.8375 | G43: =F43/$H$6 -> 0.0593081 | H43: SVF1 private mark which excludes potential TikTok US value.
B44: Symbotic | C44: Public | D44: 0.068 | E44: 37.25 | F44: =D44*E44 -> 2.533 | G44: =F44/$H$6 -> 0.016998859 | H44: Market value.
B45: GreenBox JV | C45: Private | D45: 0.65 | E45: 0 | F45: =D45*E45 -> 0 | G45: =F45/$H$6 -> 0 | H45: n/a
B46: AutoStore | C46: Public | D46: 0.4 | E46: 3.25 | F46: =D46*E46 -> 1.3 | G46: =F46/$H$6 -> 0.0087242467 | H46: Market value.
B47: Autonomous Warehouses | F47: =SUM(F44:F46) -> 3.833 | G47: =F47/$H$6 -> 0.025723106
B48: Revolut | C48: Private | D48: =F48/E48 -> 0.017923077 | E48: 65 | F48: ='SVF2'!$AX$147/1000 -> 1.165 | G48: =F48/$H$6 -> 0.0078182672 | H48: FT reported $65bn funding round.
B49: Wayve | C49: Private | D49: =F49/E49 -> 0.13689836 | E49: =1.27*41.7/0.029/1000 -> 1.8261724 | F49: 0.25 | G49: =F49/$H$6 -> 0.0016777397 | H49: Arete est. of SoftBank's contribution (est. $250m) to $1.05bn Series C funding round vs. Ocado Group reported Wayve mark.
B50: Boston Dynamics | C50: Private | D50: 0.125 | E50: 1.1 | F50: =D50*E50 -> 0.1375 | G50: =F50/$H$6 -> 0.00092275686 | H50: Dec. '20 agreed transaction value of 80% of Boston Dynamics Inc. to Hyundai Motor Group.
B51: Perplexity | C51: Private | D51: =F51/E51 -> 0.0045282738 | E51: 20 | F51: =(20/18)*'SVF2'!$AX$146/1000 -> 0.090565476 | G51: =F51/$H$6 -> 0.0006077812 | H51: $18bn funding round.
B52: Total AI "winners" | F52: =SUM(F34:F37)+SUM(F42:F43)+SUM(F47:F51) -> 235.51469 | G52: =F52/$H$6 -> 1.5805294
B53: cents on the $ | F53: =MROUND(100*H16/F52, 5) -> 85
B55: SoftBank March '31 or "end of decade" valuation ->
B57: * Arm position net of $13.5bn margin loan.
B58: Company | C58: Public vs. private | D58: % stake | E58: All-in value $bn | F58: SBG value $bn | G58: 2030 valuation methodology
B59: Arm* | C59: Public | D59: 0.9 | E59: 250 | F59: =D59*E59-13.5 -> 211.5 | G59: Arete 2030 estimated value (40x $Y.Y adjusted Mar. '31 EPS) less $13.5bn margin loan.
B60: Ampere Computing | C60: Private | D60: 1 | E60: 27.5 | F60: =D60*E60 -> 27.5 | G60: Arete 2030 estimated value of SoftBank/Arm "in-house" CPU chip business.
B61: Graphcore | C61: Private | D61: 1 | G61: Too early at this stage to ascribe value to SoftBank's "in-house" accelerator chip efforts.
B62: SoftBank "in-house" semis franchise | F62: =SUM(F59:F61) -> 239
B63: OpenAI | C63: Private | D63: =D35 -> 0.1088 | E63: =MROUND(17.5*200, 5) -> 3500 | F63: =D63*E63 -> 380.8 | G63: 17.5x OpenAI's est. FY30E sales based on large-cap. Software comps adj. for $xxbn SoftBank anti-dilution commitments.
B64: SoftBank Corp. | C64: Public | D64: 0.4025 | E64: =MROUND(E36*(1.1)^(5), 5) -> 115 | F64: =D64*E64-5 -> 41.2875 | G64: 10% p.a. share price growth less $5bn+ K.K. margin loan.
B65: Stargate | C65: Private | D65: =D37 -> 0.5 | E65: 15 | F65: =D65*E65 -> 7.5 | G65: ???
B66: NVIDIA | C66: Public | D66: =D38 -> 0.0013214179 | E66: =MROUND(E38*(1.1)^(5), 5) -> 0 | F66: =D66*E66 -> 0 | G66: 10% p.a. growth.
B67: Intel | C67: Public | D67: =D39 -> 0.018629929 | E67: =E39 -> 172 | F67: =D67*E67 -> 3.2043478 | G67: 0% p.a. growth.
B68: TSMC | C68: Public | D68: =D40 -> n/m | E68: =MROUND(E40*(1.1)^(5), 5) -> 1610 | F68: =F40 -> 0.743581 | G68: 10% p.a. growth.
B69: Oracle | C69: Public | D69: =D41 -> n/m | E69: =MROUND(E41*(1.1)^(5), 5) -> 1135 | F69: =F41 -> 0 | G69: 10% p.a. growth.
B70: "Other" semis holdings | F70: =SUM(F66:F69) -> 3.9479288
B71: ByteDance | C71: Private | D71: =D43 -> 0.0175 | E71: =MROUND(8*50%*((95*1.08^(7))+(0.65*1.5*30)), 5) -> 770 | F71: =D71*E71 -> 13.475 | G71: 8x FY30E ByteDance EBITDA assuming 50% EBITDA margin vs. Meta >60% EBITDA margin today. | U71: TikTok International (incl. US) based on Facebook/Instagram MAUs and ARPU comp., Douyin at 8% p.a. revenue growth to FY30E, 40% EBITDA margin.
B72: Symbotic | C72: Public | D72: =D44 -> 0.068 | E72: =MROUND((70/63.1)*E44, 0.25) -> 41.25 | F72: =D72*E72 -> 2.805 | G72: Arete Research est. FY30E valuation based on DCF (WACC x%, PGR y%).
B73: GreenBox JV | C73: Private | D73: =D45 -> 0.65 | E73: =2300*100/35/1000 -> 6.5714286 | F73: =D73*E73 -> 4.2714286 | G73: Arete Research est. FY30E valuation based on DCF (WACC x%, PGR y%).
B74: AutoStore | C74: Public | D74: =D46 -> 0.4 | E74: =MROUND((17.5/9.6)*E46, 0.25) -> 6 | F74: =D74*E74 -> 2.4 | G74: Arete Research est. FY30E valuation based on DCF (WACC x%, PGR y%).
B75: Autonomous Warehouses | F75: =SUM(F72:F74) -> 9.4764286
B76: Revolut | C76: Private | D76: =D48 -> 0.017923077 | E76: =115*(1.1)^(5) -> 185.20865 | F76: =D76*E76 -> 3.3195089 | G76: Largest European bank market cap. + 10% p.a. return for Revolut through 2030.
B77: Wayve | C77: Private | D77: =D49*(1-(0.5/(E49*1.5))) -> 0.11191014 | E77: 10 | F77: =D77*E77 -> 1.1191014 | G77: 25% p.a. return less dilution from $500m NVIDIA investment.
B78: Boston Dynamics | C78: Private | D78: 0.125 | E78: =0.5*39 -> 19.5 | F78: =D78*E78 -> 2.4375 | G78: 50% of Figure AI's Sep. '25 Series C funding round valuation.
B79: Perplexity | C79: Private | D79: =D51 -> 0.0045282738 | E79: =MROUND(0.5*E51*E63/E35, 5) -> 70 | F79: =E79*F51/E51 -> 0.31697917 | G79: Assumes half the value creation growth vs. OpenAI from Perplexity's Sep. '25 $20bn valuation.
B80: Total AI "winners" | F80: =SUM(F62:F65)+SUM(F70:F71)+SUM(F75:F79) -> 702.67995
B81: % discount | F81: 0.1
B82: SoftBank AI "winners" | F82: =F80*(1-F81) -> 632.41195
B83: multiple vs. net market cap. today | F83: =F82/H14 -> 5.1154503
B85: 2030 AI assets | F85: =F80 -> 702.67995
B86: 10% discount | F86: =F87-F85 -> -70.267995
B87: Market value | F87: =F82 -> 632.41195
B88: TopCo net debt | F88: =-MROUND('Valuation & SBG NAV'!$BP$71, 0.5) -> -51
B89: 2030 market cap. $bn | F89: =SUM(F87:F88) -> 581.41195
B90: Target share price | F90: =MROUND(1000*FP!$G$4*F89/'Valuation & SBG NAV'!$BP$39, 500) -> 63000
B91: % p.a. compound return | F91: =(F90/FP!$D$5)^(1/5)-1 -> 0.31233759
B92: Mar. '26E = discounted at 12.5% cost of equity | F92: =MROUND(F90/(1.125)^(4), 100) -> 39300
B93: % upside/(downside) | F93: =F92/FP!D5-1 -> 1.4281742

Sheet Valuation table summary
A1: SoftBank Group Corp.
A2: year end March ¥m
D3: = excludes variable Prepaid forward contracts where both asset and liability move in tandem i.e., "net" equity remains fixed.
C4: A | D4: B | E4: A + B = C | F4: D | H4: E = C x (1 - D) | I4: F = E - B
C5: SBG reported NAV $bn | D5: Asset-backed financing $bn | E5: Gross exposure $bn | F5: Arete % gross discount | G5: Comments | H5: Arete Gross exposure $bn | I5: Arete est. NAV $bn
B6: Alibaba | C6: ='Valuation & SBG NAV'!BP54 -> 0 | E6: ='Valuation & SBG NAV'!BP149 -> 0 | F6: ='Valuation & SBG NAV'!C175 -> 0 | G6: ='Valuation & SBG NAV'!D175 -> = minimal exposure (due to variable prepaid forward contracts) and subject to near-term monetisation. | H6: ='Valuation & SBG NAV'!BP194 -> 0 | I6: ='Valuation & SBG NAV'!BP239 -> 0 | K6: SBG-reported NAV $bn | N6: =$C$21 -> 212.48849 | S6: SBG gross exposure $bn | V6: =$N$9 -> 296.46022
B7: SoftBank Corp. | C7: ='Valuation & SBG NAV'!BP55 -> 18.403196 | D7: ='Valuation & SBG NAV'!BP97 -> 7.7111541 | E7: ='Valuation & SBG NAV'!BP150 -> 26.11435 | F7: ='Valuation & SBG NAV'!C176 -> 0.15 | G7: ='Valuation & SBG NAV'!D176 -> = seen as SBG's core telcos asset i.e., no further monetisation of 40.5% holding. | H7: ='Valuation & SBG NAV'!BP195 -> 22.197197 | I7: ='Valuation & SBG NAV'!BP240 -> 14.486043 | K7: TopCo net debt $bn | N7: =$C$20 -> 51.124113 | S7: Arete discount $bn | V7: =-($E$18-$H$18) -> -33.052159
B8: SVF1 | C8: ='Valuation & SBG NAV'!BP56 -> 23.15 | E8: ='Valuation & SBG NAV'!BP151 -> 23.15 | F8: =1-MROUND(H8/E8, 5%) -> 0 | H8: ='Valuation & SBG NAV'!BP196 -> 23.414681 | I8: ='Valuation & SBG NAV'!BP241 -> 23.414681 | K8: ABF $bn | N8: =$D$18 -> 32.847618 | S8: Arete gross exposure $bn | V8: =SUM(V6:V7) -> 263.40807
B9: OpenAI | C9: ='Valuation & SBG NAV'!BP57 -> 54.4 | E9: ='Valuation & SBG NAV'!BP152 -> 54.4 | F9: =1-MROUND(H9/E9, 5%) -> 0 | H9: ='Valuation & SBG NAV'!BP197 -> 54.4 | I9: ='Valuation & SBG NAV'!BP242 -> 54.4 | K9: SBG gross exposure $bn | N9: =SUM(N6:N8) -> 296.46022 | S9: ABF $bn | V9: =-$N$8 -> -32.847618
B10: SVF2 excl. OpenAI | C10: ='Valuation & SBG NAV'!BP58 -> 28.99 | D10: ='Valuation & SBG NAV'!BP100 -> 5.33 | E10: ='Valuation & SBG NAV'!BP153 -> 34.32 | F10: =1-MROUND(H10/E10, 5%) -> 0.6 | H10: ='Valuation & SBG NAV'!BP198 -> 14.15128 | I10: ='Valuation & SBG NAV'!BP243 -> 8.82128 | S10: TopCo net debt $bn | V10: =-$N$7 -> -51.124113
B11: SVF2 | C11: ='Valuation & SBG NAV'!BP59 -> 83.39 | D11: ='Valuation & SBG NAV'!BP101 -> 5.33 | E11: ='Valuation & SBG NAV'!BP154 -> 88.72 | F11: =1-MROUND(H11/E11, 5%) -> 0.25 | H11: ='Valuation & SBG NAV'!BP199 -> 68.55128 | I11: ='Valuation & SBG NAV'!BP244 -> 63.22128 | S11: Arete est. NAV $bn | V11: =SUM(V8:V10) -> 179.43633
B12: LatAm Funds | C12: ='Valuation & SBG NAV'!BP60 -> 6.773 | E12: ='Valuation & SBG NAV'!BP155 -> 6.773 | F12: =1-MROUND(H12/E12, 5%) -> 0.5 | H12: ='Valuation & SBG NAV'!BP200 -> 3.3865 | I12: ='Valuation & SBG NAV'!BP245 -> 3.3865
B13: SBG's equity in Vision Funds | C13: ='Valuation & SBG NAV'!BP61 -> 113.313 | D13: ='Valuation & SBG NAV'!BP103 -> 5.33 | E13: ='Valuation & SBG NAV'!BP156 -> 118.643 | F13: =1-MROUND(H13/E13, 5%) -> 0.2 | H13: ='Valuation & SBG NAV'!BP201 -> 95.352461 | I13: ='Valuation & SBG NAV'!BP246 -> 90.022461
B14: T-Mobile US | C14: ='Valuation & SBG NAV'!BP62 -> 3.45776 | D14: ='Valuation & SBG NAV'!BP104 -> 0 | E14: ='Valuation & SBG NAV'!BP157 -> 3.45776 | F14: ='Valuation & SBG NAV'!C183 -> 0 | G14: ='Valuation & SBG NAV'!D183 -> = Arete have xx% upside on T-Mobile US and non-core + easily monetisable e.g., buyback participation. | H14: ='Valuation & SBG NAV'!BP202 -> 3.45776 | I14: ='Valuation & SBG NAV'!BP247 -> 3.45776
B15: Deutsche Telekom | C15: ='Valuation & SBG NAV'!BP63 -> 0 | D15: ='Valuation & SBG NAV'!BP105 -> 0 | E15: ='Valuation & SBG NAV'!BP158 -> 0 | F15: ='Valuation & SBG NAV'!C184 -> 0 | G15: ='Valuation & SBG NAV'!D184 -> = Arete have xx% upside on DT and non-core + easily monetisable e.g., buyback participation. | H15: ='Valuation & SBG NAV'!BP203 -> 0 | I15: ='Valuation & SBG NAV'!BP248 -> 0
B16: Arm | C16: ='Valuation & SBG NAV'!BP64 -> 97.598771 | D16: ='Valuation & SBG NAV'!BP106 -> 19.806464 | E16: ='Valuation & SBG NAV'!BP159 -> 117.40524 | F16: ='Valuation & SBG NAV'!C185 -> 0.1 | G16: = uses Arete FYXX $xx target price for 90% Arm gross exposure and applies 10% holding discount. | H16: ='Valuation & SBG NAV'!BP204 -> 117.24476 | I16: ='Valuation & SBG NAV'!BP249 -> 97.438291
B17: Others (incl. OpenAI + Stargate + Ampere + Graphcore) | C17: ='Valuation & SBG NAV'!BP65 -> 30.839879 | E17: ='Valuation & SBG NAV'!BP160 -> 30.839879 | F17: =1-MROUND(H17/E17, 5%) -> 0.2 | G17: ='Valuation & SBG NAV'!D188 -> = 15% discount for other assets (e.g., NVIDIA, TSMC, Oracle equity stakes). | H17: ='Valuation & SBG NAV'!BP205 -> 25.155891 | I17: ='Valuation & SBG NAV'!BP250 -> 25.155891
B18: Total | C18: ='Valuation & SBG NAV'!BP66 -> 263.61261 | D18: ='Valuation & SBG NAV'!BP108 -> 32.847618 | E18: ='Valuation & SBG NAV'!BP161 -> 296.46022 | F18: =1-MROUND(H18/E18, 5%) -> 0.1 | H18: ='Valuation & SBG NAV'!BP206 -> 263.40807 | I18: ='Valuation & SBG NAV'!BP251 -> 230.56045
B20: Less: TopCo standalone net interest-bearing debt | C20: ='Valuation & SBG NAV'!BP71 -> 51.124113 | I20: =C20 -> 51.124113
B21: SBG NAV $bn | C21: =C18-C20 -> 212.48849 | F21: =1-MROUND(I21/C21, 2.5%) -> 0.15 | I21: =I18-I20 -> 179.43633
B22: FX | C22: =FP!$G$4 -> 155.1 | I22: =FP!$G$4 -> 155.1
B23: SBG NAV ¥tn | C23: =C21*C22/1000 -> 32.956965 | I23: =I21*I22/1000 -> 27.830575
B24: Outstanding shares (millions) | I24: ='Valuation & SBG NAV'!$BO$39 -> 1427.962
B25: Target price ¥ | I25: =MROUND(1000000*I23/I24, 100) -> 19500
B26: % upside/(downside) | I26: =I25/FP!$D$5-1 -> 0.20481928
C28: A | D28: B | E28: A + B = C | F28: D | H28: E = C x (1 - D) | I28: F = E - B
B29: SoftBank Vision Funds | C29: SBG reported NAV $bn | D29: Asset-backed financing $bn | E29: Gross exposure $bn | F29: Arete % gross discount | G29: Comments | H29: Arete Gross exposure $bn | I29: Arete est. NAV $bn
B30: SVF1 Publicly listed | C30: =E30 -> 10.701359 | E30: ='Valuation & SBG NAV'!BK216 -> 10.701359 | F30: ='Valuation & SBG NAV'!C177 -> 0 | G30: ='Valuation & SBG NAV'!D177 -> = to be monetised in near future & already marked-to-market by SBG. | H30: =E30*(1-F30) -> 10.701359
B31: SVF1 Privately held ex. ByteDance | C31: =E31 -> 6.2863331 | E31: ='Valuation & SBG NAV'!BK217 -> 6.2863331 | F31: ='Valuation & SBG NAV'!C178 -> 0.25 | G31: ='Valuation & SBG NAV'!D178 -> = highly skeptical of under the bonnet SVF valuations given investment track record. | H31: =E31*(1-F31) -> 4.7147498
B32: ByteDance | C32: =E32 -> 7.6244 | E32: ='Valuation & SBG NAV'!BK218 -> 7.6244 | F32: ='Valuation & SBG NAV'!C179 -> 0 | G32: ='Valuation & SBG NAV'!D179 -> = value separately: think SBG carrying value conservative and already marked down 20% for potential US ban. | H32: =E32*(1-F32) -> 7.6244
B33: SVF1 | C33: =C8 -> 23.15 | E33: =E8 -> 23.15 | F33: =1-MROUND(H33/E33, 5%) -> 0 | H33: =H8 -> 23.414681 | I33: =I8 -> 23.414681
B34: SVF2 Publicly listed | C34: ='SVF2'!$AR$4*'Valuation table summary'!$C$11 -> 8.6989568 | E34: ='Valuation & SBG NAV'!BK229 -> 3.6361146 | F34: ='Valuation & SBG NAV'!C180 -> 0.15 | G34: ='Valuation & SBG NAV'!D180 -> = monetisation timeline less obvious albeit marked-to-market by SBG. | H34: =E34*(1-F34) -> 3.0906974
B35: SVF2 Privately held | C35: =C36-C34 -> 74.691043 | E35: ='Valuation & SBG NAV'!BK230 -> 28.325339 | F35: ='Valuation & SBG NAV'!C181 -> 0.67 | G35: ='Valuation & SBG NAV'!D181 -> = see SVF1 explanation: additional discount due to peak tech valuation "vintage". | H35: =E35*(1-F35) -> 9.347362
B36: SVF2 | C36: =C11 -> 83.39 | D36: =D11 -> 5.33 | E36: =E11 -> 88.72 | F36: =1-MROUND(H36/E36, 5%) -> 0.25 | H36: =H11 -> 68.55128 | I36: =I11 -> 63.22128
B37: LatAm Funds | C37: =C12 -> 6.773 | D37: =D12 -> 0 | E37: =E12 -> 6.773 | F37: =1-MROUND(H37/E37, 5%) -> 0.5 | G37: ='Valuation & SBG NAV'!D182 -> = poor visibility on investments plus significant EM risk etc etc. | H37: =H12 -> 3.3865 | I37: =I12 -> 3.3865
B39: Check
B40: Alibaba | E40: =E6-(C6+D6) -> 0 | H40: =H6-(E6*(1-F6)) -> 0
B41: SoftBank Corp. | E41: =E7-(C7+D7) -> 0 | H41: =H7-(E7*(1-F7)) -> 0
B42: SVF1 | E42: =E8-(C8+D8) -> 0
B43: SVF2 | E43: =E11-(C11+D11) -> 0
B44: LatAm Funds | E44: =E12-(C12+D12) -> 0
B45: SBG's equity in Vision Funds | E45: =E13-(C13+D13) -> 0
B46: T-Mobile US | E46: =E14-(C14+D14) -> 0 | H46: =H14-(E14*(1-F14)) -> 0
B47: Deutsche Telekom | E47: =E15-(C15+D15) -> 0 | H47: =H15-(E15*(1-F15)) -> 0
B48: Arm | E48: =E16-(C16+D16) -> 0 | H48: =H16-(E16*(1-F16)) -> 11.580044
B49: Others | E49: =E17-(C17+D17) -> 0
B50: Total | E50: =E18-(C18+D18) -> 0

Sheet FP
A1: SoftBank Group Corp.
A2: year end March ¥m
N3: = 10-for-1 stock split to SoftBank KK shares executed on 30th September -> need to adjust model. | Z3: = update from T-Mobile US and DT models.
F4: JPY/USD | G4: 155.1 | I4: Prior Q Arm share price $ | L4: 109.31 | N4: Prior Q SoftBank Corp. share price ¥ | Q4: =10*214.8 -> 2148 | S4: SoftBank Corp. % ownership | V4: 0.4025 | X4: SoftBank Corp. net debt ¥bn | Z4: ='Financial statements KK'!$AK$292 -> 3731.1 | AB4: SoftBank Corp. net debt $bn | AE4: =MROUND(Z4/$G$4, 0.05) -> 24.05
B5: Share price ¥ | D5: =MROUND(D9*4, 5) -> 16185 | F5: JPY/EUR | G5: 183.25 | I5: Arm share price $ | L5: 124.37 | N5: SoftBank Corp. share price ¥ | Q5: =10*212.7 -> 2127 | X5: SoftBank Corp. towers liabs. ¥bn | Z5: ='Financial statements KK'!$AK$252 -> 490.9 | AB5: SoftBank Corp. towers liabs. $bn | AE5: =MROUND(Z5/$G$4, 0.05) -> 3.15
B6: Shares outstanding (m) | D6: 1427.962 | F6: JPY/GBP | G6: 209.15 | I6: Arm shares outstanding (m) | L6: ='[64]P&L'!$FO$69 -> 1048.8885 | N6: SoftBank Corp. shares outstanding (m) | Q6: ='Financial statements KK'!$AL$58 -> 4731.0511 | S6: SoftBank Corp. stake. ¥bn | X6: T-Mobile US net debt $bn | Z6: 74.65 | AB6: T-Mobile US net debt $bn | AE6: =MROUND(Z6, 0.05) -> 74.65
B7: Market cap. ¥bn | D7: =D5*D6/1000 -> 23111.565 | I7: Arm market cap. $bn | L7: =L5*L6/1000 -> 130.45026 | N7: SoftBank Corp. market cap. ¥bn | Q7: =Q5*Q6/1000 -> 10062.946 | X7: DT net debt €m | Z7: 93.746 | AB7: DT net debt $bn | AE7: =MROUND(Z7*$G$5/$G$4, 0.05) -> 110.75
F8: T-Mobile US $ | G8: 216.11 | S8: SoftBank Corp. stake. $m | X8: = T-Mobile/DT taken from reports or Arete model.
B9: Share price ¥ | D9: 4046 | F9: DT € | G9: 33.21 | I9: Arm target price $ FY27E | L9: 138 | N9: Market cap. $m | Q9: =1000*Q7/$G$4 -> 64880.372
B10: Shares outstanding (m) | D10: =4*D6 -> 5711.8481 | I10: Arm target price $ = discounted. | L10: =L9/1.075 -> 128.37209
B11: Market cap. ¥bn | D11: =D9*D10/1000 -> 23110.137 | F11: Thomson | G11: 20500 | I11: Arm target market cap. $bn | L11: =L9*L6/1000 -> 144.74661 | N11: OpenAI all-in valuation $bn | Q11: 500 | S11: OpenAI "discount" carried by SVF2 | V11: 0.05
F12: Reuters VC | N12: #2 Dec. '25 investment tranche SBG $bn | Q12: 22.5 | S12: OpenAI all-in valuation within SVF2 $bn | V12: =Q11*(1-V11) -> 475
B13: Market cap. $m | D13: =1000*D7/$G$4 -> 149010.74 | I13: Arm % ownership | L13: 0.9 | N13: #2 Dec. '25 syndicate $bn | Q13: 7.5
B14: vs. PF SBG reported NAV $m | D14: =1000*'Valuation table summary'!$C$21 -> 212488.49 | N14: Total #2 syndicate $bn | Q14: =SUM(Q12:Q13) -> 30 | T14: $35bn F-O
B15: % discount/(premium) | D15: =1-D13/D14 -> 0.29873502 | Q15: Tranche 1 = $15bn Amazon + $10bn SoftBank + $10bn NVIDIA but excludes $10bn Middle East & Venture Capital.
N16: OpenAI CY26 funding round assumptions -> | Q16: =(110-35)/(Q17+110-35) -> 0.093167702 | R16: =(110-35)/(R17+110-35) -> 0.093167702 | S16: =(110-35)/(S17+110-35) -> 0.093167702 | T16: =(110)/(T17+110) -> 0.13095238 | U16: = total dilution to existing OpenAI shareholders incl. full Amazon $50bn investment.
B17: March '31E target price | D17: ='New SBG Valuation'!$J$48 -> 18250 | N17: Pre-money valuation $bn | Q17: 730 | R17: 730 | S17: 730 | T17: 730
B18: Arete target market cap. $bn | D18: ='New SBG Valuation'!$J$47 -> 673.48018 | N18: + Funding round amount $bn | Q18: =10+10+15 -> 35 | R18: =10+10 -> 20 | S18: =10+10 -> 20 | T18: 35 | U18: -> assumptions = Amazon $15bn (+$35bn "when certain conditions are met"), NVIDIA $30bn, SoftBank Group $30bn, Middle East + VCs $10bn.
B19: % upside/(downside) | D19: =D17/D9-1 -> 3.5106278 | N19: Post-money valuation $bn | Q19: =SUM(Q17:Q18) -> 765 | R19: =Q19+R18 -> 785 | S19: =R19+S18 -> 805 | T19: =S19+T18 -> 840 | U19: https://www.theinformation.com/articles/openai-finalizing-first-commitments-100-billion-mega-round?rc=oyp3ga
N20: % SVF2 stake in OpenAI pre-funding round | Q20: 0.115 | R20: Tranche #2 | S20: Tranche #3
B21: = using OLD share count (pre- 4-for-1 share split on 31 Dec. '25). | G21: = using NEW share count (pre- 4-for-1 share split on 31 Dec. '25). | N21: SVF2 tranche #1 $bn | Q21: 10 | R21: 10 | S21: 10 | U21: = we assume two additional $10bn tranches by SoftBank of which 25% syndicated.
C22: NAV/share ¥ | D22: % discount to NAV | E22: % LTV | H22: NAV/share ¥ | I22: % discount to NAV | J22: % LTV
B23: F1Q23 | C23: ='Valuation & SBG NAV'!$BB$41 -> 10610 | D23: ='SVF Indexes'!I28 -> 0.36270096 | E23: ='Valuation & SBG NAV'!$BB$37 -> 0.079881657 | G23: F1Q23 | H23: =C23/4 -> 2652.5 | I23: =D23 -> 0.36270096 | J23: =E23 -> 0.079881657
B24: F2Q23 | C24: ='Valuation & SBG NAV'!$BC$41 -> 11190 | D24: ='SVF Indexes'!I29 -> 0.43479586 | E24: ='Valuation & SBG NAV'!$BC$37 -> 0.10620915 | G24: F2Q23 | H24: =C24/4 -> 2797.5 | I24: =D24 -> 0.43479586 | J24: =E24 -> 0.10620915
B25: F3Q23 | C25: ='Valuation & SBG NAV'!$BD$41 -> 13120 | D25: ='SVF Indexes'!I30 -> 0.52053015 | E25: ='Valuation & SBG NAV'!$BD$37 -> 0.11418048 | G25: F3Q23 | H25: =C25/4 -> 3280 | I25: =D25 -> 0.52053015 | J25: =E25 -> 0.11418048
B26: F4Q23 | C26: ='Valuation & SBG NAV'!$BE$41 -> 18950 | D26: ='SVF Indexes'!I31 -> 0.52717783 | E26: ='Valuation & SBG NAV'!$BE$37 -> 0.08437706 | G26: F4Q23 | H26: =C26/4 -> 4737.5 | I26: =D26 -> 0.52717783 | J26: =E26 -> 0.08437706
B27: F1Q24 | C27: ='Valuation & SBG NAV'!$BG$41 -> 24060 | D27: ='SVF Indexes'!I32 -> 0.56691239 | E27: ='Valuation & SBG NAV'!$BG$37 -> 0.078149503 | G27: F1Q24 | H27: =C27/4 -> 6015 | I27: =D27 -> 0.56691239 | J27: =E27 -> 0.078149503
B28: F2Q24 | C28: ='Valuation & SBG NAV'!$BH$41 -> 20050 | D28: ='SVF Indexes'!I33 -> 0.57876594 | E28: ='Valuation & SBG NAV'!$BH$37 -> 0.12462281 | G28: F2Q24 | H28: =C28/4 -> 5012.5 | I28: =D28 -> 0.57876594 | J28: =E28 -> 0.12462281
B29: F3Q24 | C29: ='Valuation & SBG NAV'!$BI$41 -> 20360 | D29: ='SVF Indexes'!I34 -> 0.54856851 | E29: ='Valuation & SBG NAV'!$BI$37 -> 0.12860113 | G29: F3Q24 | H29: =C29/4 -> 5090 | I29: =D29 -> 0.54856851 | J29: =E29 -> 0.12860113
B30: F4Q24 | C30: ='Valuation & SBG NAV'!$BJ$41 -> 17880 | D30: ='SVF Indexes'!I35 -> 0.58093385 | E30: ='Valuation & SBG NAV'!$BJ$37 -> 0.18074594 | G30: F4Q24 | H30: =C30/4 -> 4470 | I30: =D30 -> 0.58093385 | J30: =E30 -> 0.18074594
B31: F1Q25 | C31: ='Valuation & SBG NAV'!$BL$41 -> 22750 | D31: ='SVF Indexes'!I36 -> 0.5367284 | E31: ='Valuation & SBG NAV'!$BL$37 -> 0.17008197 | G31: F1Q25 | H31: =C31/4 -> 5687.5 | I31: =D31 -> 0.5367284 | J31: =E31 -> 0.17008197
B32: F2Q25 | C32: ='Valuation & SBG NAV'!$BM$41 -> 23380 | D32: ='SVF Indexes'!I37 -> 0.20075075 | E32: ='Valuation & SBG NAV'!$BM$37 -> 0.16457602 | G32: F2Q25 | H32: =C32/4 -> 5845 | I32: =D32 -> 0.20075075 | J32: =E32 -> 0.16457602
B33: F3Q25 | C33: ='Valuation & SBG NAV'!$BN$41 -> 21670 | D33: ='Valuation & SBG NAV'!$BN$42 -> 0.25311491 | E33: ='Valuation & SBG NAV'!$BN$37 -> 0.20625962 | G33: F3Q25 | H33: ='Valuation & SBG NAV'!$BN$46 -> 5420 | I33: ='Valuation & SBG NAV'!$BN$47 -> 0.25350554 | J33: ='Valuation & SBG NAV'!$BN$37 -> 0.20625962
B34: F4Q25E | C34: ='Valuation & SBG NAV'!$BO$41 -> 23080 | D34: ='Valuation & SBG NAV'!$BO$42 -> 0.2987435 | E34: ='Valuation & SBG NAV'!$BO$37 -> 0.19393653 | G34: F4Q25E | H34: ='Valuation & SBG NAV'!$BO$46 -> 5770 | I34: ='Valuation & SBG NAV'!$BO$47 -> 0.29878683 | J34: ='Valuation & SBG NAV'!$BO$37 -> 0.19393653
G35: F1Q26E | H35: ='Valuation & SBG NAV'!$BQ$46 -> 6290 | I35: ='Valuation & SBG NAV'!$BQ$47 -> 0.35675676 | J35: ='Valuation & SBG NAV'!$BQ$37 -> 0.19402876
G36: F2Q26E | H36: ='Valuation & SBG NAV'!$BR$46 -> 6280 | I36: ='Valuation & SBG NAV'!$BR$47 -> 0.35573248 | J36: ='Valuation & SBG NAV'!$BR$37 -> 0.22402141
G37: F3Q26E | H37: ='Valuation & SBG NAV'!$BS$46 -> 6220 | I37: ='Valuation & SBG NAV'!$BS$47 -> 0.34951768 | J37: ='Valuation & SBG NAV'!$BS$37 -> 0.25264093
G38: F4Q26E | H38: ='Valuation & SBG NAV'!$BT$46 -> 6130 | I38: ='Valuation & SBG NAV'!$BT$47 -> 0.33996737 | J38: ='Valuation & SBG NAV'!$BT$37 -> 0.25267031

Sheet P.F. NAV Table
A1: SoftBank Group Corp.
A2: year end March ¥tn | I2: Annual
A4: Net asset value & LTV ¥tn = as reported by SBG.
B5: = update quarterly figures by adjusting column refs from Valuation & SBG NAV and delta columns update automatically.
B6: F2Q25E | D6: Pro Forma | F6: delta
B7: ¥tn | C7: $bn | D7: ¥tn | E7: $bn | F7: ¥tn | G7: $bn | I7: = impact on SoftBank NAV per share.
A8: Alibaba | B8: ='Quarterly NAV Table'!D8 -> 0 | C8: ='Quarterly NAV Table'!E8 -> 0 | D8: ='Valuation & SBG NAV'!BN10 -> 0 | E8: ='Valuation & SBG NAV'!BN54 -> 0 | F8: =D8-B8 -> 0 | G8: =E8-C8 -> 0 | I8: =1000000*F8/FP!$D$6 -> 0
A9: SoftBank Corp. | B9: ='Quarterly NAV Table'!D9 -> 2.92 | C9: ='Quarterly NAV Table'!E9 -> 18.650996 | D9: ='Valuation & SBG NAV'!BN11 -> 2.92 | E9: ='Valuation & SBG NAV'!BN55 -> 18.650996 | F9: =D9-B9 -> 0 | G9: =E9-C9 -> 0 | I9: =1000000*F9/FP!$D$6 -> 0
A10: SVF1 | B10: ='Quarterly NAV Table'!D10 -> 3.79 | C10: ='Quarterly NAV Table'!E10 -> 24.207971 | D10: ='Valuation & SBG NAV'!BN12 -> 3.79 | E10: ='Valuation & SBG NAV'!BN56 -> 24.207971 | F10: =D10-B10 -> 0 | G10: =E10-C10 -> 0 | I10: =1000000*F10/FP!$D$6 -> 0
A11: OpenAI | B11: ='Quarterly NAV Table'!D11 -> 8.516864 | C11: ='Quarterly NAV Table'!E11 -> 54.4 | D11: ='Valuation & SBG NAV'!BN13 -> 8.516864 | E11: ='Valuation & SBG NAV'!BN57 -> 54.4 | F11: =D11-B11 -> 0 | G11: =E11-C11 -> 0 | I11: =1000000*F11/FP!$D$6 -> 0
A12: SVF2 excl. OpenAI | B12: ='Quarterly NAV Table'!D12 -> 4.653136 | C12: ='Quarterly NAV Table'!E12 -> 29.721104 | D12: ='Valuation & SBG NAV'!BN14 -> 4.653136 | E12: ='Valuation & SBG NAV'!BN58 -> 29.721104 | F12: =D12-B12 -> 0 | G12: =E12-C12 -> 0 | I12: =1000000*F12/FP!$D$6 -> 0
A13: SVF2 | B13: ='Quarterly NAV Table'!D13 -> 13.17 | C13: ='Quarterly NAV Table'!E13 -> 84.121104 | D13: ='Valuation & SBG NAV'!BN15 -> 13.17 | E13: ='Valuation & SBG NAV'!BN59 -> 84.121104 | F13: =D13-B13 -> 0 | G13: =E13-C13 -> 0 | I13: =1000000*F13/FP!$D$6 -> 0
A14: LatAm Funds | B14: ='Quarterly NAV Table'!D14 -> 1.04 | C14: ='Quarterly NAV Table'!E14 -> 6.6428206 | D14: ='Valuation & SBG NAV'!BN16 -> 1.04 | E14: ='Valuation & SBG NAV'!BN60 -> 6.6428206 | F14: =D14-B14 -> 0 | G14: =E14-C14 -> 0 | I14: =1000000*F14/FP!$D$6 -> 0
A15: SBG's equity in Vision Funds | B15: ='Quarterly NAV Table'!D15 -> 18 | C15: ='Quarterly NAV Table'!E15 -> 114.9719 | D15: ='Valuation & SBG NAV'!BN17 -> 18 | E15: ='Valuation & SBG NAV'!BN61 -> 114.9719 | F15: =D15-B15 -> 0 | G15: =E15-C15 -> 0 | I15: =1000000*F15/FP!$D$6 -> 0
A16: T-Mobile US | B16: ='Quarterly NAV Table'!D16 -> 0.91 | C16: ='Quarterly NAV Table'!E16 -> 5.8124681 | D16: ='Valuation & SBG NAV'!BN18 -> 0.91 | E16: ='Valuation & SBG NAV'!BN62 -> 5.8124681 | F16: =D16-B16 -> 0 | G16: =E16-C16 -> 0 | I16: =1000000*F16/FP!$D$6 -> 0
A17: Deutsche Telekom | B17: ='Quarterly NAV Table'!D17 -> 0 | C17: ='Quarterly NAV Table'!E17 -> 0 | D17: ='Valuation & SBG NAV'!BN19 -> 0 | E17: ='Valuation & SBG NAV'!BN63 -> 0 | F17: =D17-B17 -> 0 | G17: =E17-C17 -> 0 | I17: =1000000*F17/FP!$D$6 -> 0
A18: Arm | B18: ='Quarterly NAV Table'!D18 -> 12.69 | C18: ='Quarterly NAV Table'!E18 -> 81.055187 | D18: ='Valuation & SBG NAV'!BN20 -> 12.69 | E18: ='Valuation & SBG NAV'!BN64 -> 81.055187 | F18: =D18-B18 -> 0 | G18: =E18-C18 -> 0 | I18: =1000000*F18/FP!$D$6 -> 0
A19: Others | B19: ='Quarterly NAV Table'!D19 -> 4.46 | C19: ='Quarterly NAV Table'!E19 -> 28.487481 | D19: ='Valuation & SBG NAV'!BN21 -> 4.46 | E19: ='Valuation & SBG NAV'!BN65 -> 28.487481 | F19: =D19-B19 -> 0 | G19: =E19-C19 -> 0 | I19: =1000000*F19/FP!$D$6 -> 0
A20: SBG total value of equity holdings net of asset-backed finance = A | B20: ='Quarterly NAV Table'!D20 -> 38.98 | C20: ='Quarterly NAV Table'!E20 -> 248.97803 | D20: ='Valuation & SBG NAV'!BN22 -> 38.98 | E20: ='Valuation & SBG NAV'!BN66 -> 248.97803 | F20: =D20-B20 -> 0 | G20: =E20-C20 -> 0 | I20: =1000000*F20/FP!$D$6 -> 0
A21: Less: SBG TopCo standalone net interest-bearing debt = B | B21: ='Quarterly NAV Table'!D21 -> 8.04 | C21: ='Quarterly NAV Table'!E21 -> 51.354113 | D21: ='Valuation & SBG NAV'!BN31 -> 8.04 | E21: ='Valuation & SBG NAV'!BN71 -> 51.354113 | F21: =D21-B21 -> 0 | G21: =E21-C21 -> 0 | I21: =1000000*F21/FP!$D$6 -> 0
A22: Net asset value = A - B | B22: ='Quarterly NAV Table'!D22 -> 30.94 | C22: ='Quarterly NAV Table'!E22 -> 197.62391 | D22: =D20-D21 -> 30.94 | E22: =E20-E21 -> 197.62391 | F22: =D22-B22 -> 0 | G22: =E22-C22 -> 0 | I22: =1000000*F22/FP!$D$6 -> 0
A23: per share ¥ | D23: =MROUND(1000000*D22/FP!$D$10, 10) -> 5420
A24: % qoq increase/(decrease) | D24: =D22/B22-1 -> 0 | E24: =E22/C22-1 -> 0
A26: Loan-to-value = B/A | B26: =C21/C20 -> 0.20625962 | D26: =E21/E20 -> 0.20625962
A27: EoP FX | B27: ='Valuation & SBG NAV'!BM79 -> 148.88 | D27: ='Valuation & SBG NAV'!BN79 -> 156.56
A28: % qoq change | D28: =D27/B27-1 -> 0.051585169

Sheet Quarterly NAV Table
A1: SoftBank Group Corp.
A2: year end March ¥tn | I2: Annual
A4: Net asset value & LTV ¥tn = as reported by SBG.
B5: = update quarterly figures by adjusting column refs from Valuation & SBG NAV and delta columns update automatically.
B6: F2Q25 | D6: F3Q25E | F6: delta
B7: ¥tn | C7: $bn | D7: ¥tn | E7: $bn | F7: ¥tn | G7: $bn
A8: Alibaba | B8: ='Valuation & SBG NAV'!BM10 -> 0 | C8: ='Valuation & SBG NAV'!BM54 -> 0 | D8: ='Valuation & SBG NAV'!BN10 -> 0 | E8: ='Valuation & SBG NAV'!BN54 -> 0 | F8: =D8-B8 -> 0 | G8: =E8-C8 -> 0
A9: SoftBank Corp. | B9: ='Valuation & SBG NAV'!BM11 -> 3.37 | C9: ='Valuation & SBG NAV'!BM55 -> 22.63568 | D9: ='Valuation & SBG NAV'!BN11 -> 2.92 | E9: ='Valuation & SBG NAV'!BN55 -> 18.650996 | F9: =D9-B9 -> -0.45 | G9: =E9-C9 -> -3.9846833
A10: SVF1 | B10: ='Valuation & SBG NAV'!BM12 -> 3.96 | C10: ='Valuation & SBG NAV'!BM56 -> 26.598603 | D10: ='Valuation & SBG NAV'!BN12 -> 3.79 | E10: ='Valuation & SBG NAV'!BN56 -> 24.207971 | F10: =D10-B10 -> -0.17 | G10: =E10-C10 -> -2.3906315
A11: OpenAI | B11: ='Valuation & SBG NAV'!BM13 -> 3.677336 | C11: ='Valuation & SBG NAV'!BM57 -> 24.7 | D11: ='Valuation & SBG NAV'!BN13 -> 8.516864 | E11: ='Valuation & SBG NAV'!BN57 -> 54.4 | F11: =D11-B11 -> 4.839528 | G11: =E11-C11 -> 29.7
A12: SVF2 excl. OpenAI | B12: ='Valuation & SBG NAV'!BM14 -> 4.582664 | C12: ='Valuation & SBG NAV'!BM58 -> 30.780924 | D12: ='Valuation & SBG NAV'!BN14 -> 4.653136 | E12: ='Valuation & SBG NAV'!BN58 -> 29.721104 | F12: =D12-B12 -> 0.070472 | G12: =E12-C12 -> -1.0598205
A13: SVF2 | B13: ='Valuation & SBG NAV'!BM15 -> 8.26 | C13: ='Valuation & SBG NAV'!BM59 -> 55.480924 | D13: ='Valuation & SBG NAV'!BN15 -> 13.17 | E13: ='Valuation & SBG NAV'!BN59 -> 84.121104 | F13: =D13-B13 -> 4.91 | G13: =E13-C13 -> 28.640179
A14: LatAm Funds | B14: ='Valuation & SBG NAV'!BM16 -> 1.04 | C14: ='Valuation & SBG NAV'!BM60 -> 6.9854917 | D14: ='Valuation & SBG NAV'!BN16 -> 1.04 | E14: ='Valuation & SBG NAV'!BN60 -> 6.6428206 | F14: =D14-B14 -> 0 | G14: =E14-C14 -> -0.34267103
A15: SBG's equity in Vision Funds | B15: ='Valuation & SBG NAV'!BM17 -> 13.26 | C15: ='Valuation & SBG NAV'!BM61 -> 89.065019 | D15: ='Valuation & SBG NAV'!BN17 -> 18 | E15: ='Valuation & SBG NAV'!BN61 -> 114.9719 | F15: =D15-B15 -> 4.74 | G15: =E15-C15 -> 25.906877
A16: T-Mobile US | B16: ='Valuation & SBG NAV'!BM18 -> 1.61 | C16: ='Valuation & SBG NAV'!BM62 -> 10.814078 | D16: ='Valuation & SBG NAV'!BN18 -> 0.91 | E16: ='Valuation & SBG NAV'!BN62 -> 5.8124681 | F16: =D16-B16 -> -0.7 | G16: =E16-C16 -> -5.0016104
A17: Deutsche Telekom | B17: ='Valuation & SBG NAV'!BM19 -> 0.05 | C17: ='Valuation & SBG NAV'!BM63 -> 0.33584095 | D17: ='Valuation & SBG NAV'!BN19 -> 0 | E17: ='Valuation & SBG NAV'!BN63 -> 0 | F17: =D17-B17 -> -0.05 | G17: =E17-C17 -> -0.33584095
A18: Arm | B18: ='Valuation & SBG NAV'!BM20 -> 18.18 | C18: ='Valuation & SBG NAV'!BM64 -> 122.11177 | D18: ='Valuation & SBG NAV'!BN20 -> 12.69 | E18: ='Valuation & SBG NAV'!BN64 -> 81.055187 | F18: =D18-B18 -> -5.49 | G18: =E18-C18 -> -41.056581
A19: Others | B19: ='Valuation & SBG NAV'!BM21 -> 3.39 | C19: ='Valuation & SBG NAV'!BM65 -> 22.770016 | D19: ='Valuation & SBG NAV'!BN21 -> 4.46 | E19: ='Valuation & SBG NAV'!BN65 -> 28.487481 | F19: =D19-B19 -> 1.07 | G19: =E19-C19 -> 5.7174647
A20: SBG total value of equity holdings net of asset-backed finance = A | B20: ='Valuation & SBG NAV'!BM22 -> 39.86 | C20: ='Valuation & SBG NAV'!BM66 -> 267.7324 | D20: ='Valuation & SBG NAV'!BN22 -> 38.98 | E20: ='Valuation & SBG NAV'!BN66 -> 248.97803 | F20: =D20-B20 -> -0.88 | G20: =E20-C20 -> -18.754374
A21: Less: SBG TopCo standalone net interest-bearing debt = B | B21: ='Valuation & SBG NAV'!BM31 -> 6.56 | C21: ='Valuation & SBG NAV'!BM71 -> 44.062332 | D21: ='Valuation & SBG NAV'!BN31 -> 8.04 | E21: ='Valuation & SBG NAV'!BN71 -> 51.354113 | F21: =D21-B21 -> 1.48 | G21: =E21-C21 -> 7.2917814
A22: Net asset value = A - B | B22: =B20-B21 -> 33.3 | C22: =C20-C21 -> 223.67007 | D22: =D20-D21 -> 30.94 | E22: =E20-E21 -> 197.62391 | F22: =D22-B22 -> -2.36 | G22: =E22-C22 -> -26.046156
A23: per share ¥ | D23: =MROUND(1000000*D22/FP!$D$10, 10) -> 5420
A24: % qoq increase/(decrease) | D24: =D22/B22-1 -> -0.070870871 | E24: =E22/C22-1 -> -0.116449
A26: Loan-to-value = B/A | B26: =C21/C20 -> 0.16457602 | D26: =E21/E20 -> 0.20625962
A27: EoP FX | B27: ='Valuation & SBG NAV'!BM79 -> 148.88 | D27: ='Valuation & SBG NAV'!BN79 -> 156.56
A28: % qoq change | D28: =D27/B27-1 -> 0.051585169

Sheet OpenAI SBG "rough"
B1: Cost $bn | C1: Pre-money $bn | D1: All-in valuation $bn | E1: % | F1: Post-dilution % | G1: Quarter $bn
G3: F2Q $bn
A4: Autumn '24 | B4: 0.5 | C4: =D4-6.6 -> 150.4 | D4: 157 | E4: =100*B4/D4 -> 0.31847134 | F4: =E4*(1-10/300) -> 0.30785563 | G4: =F4*$G$11/100 -> 1.3468684
A5: C1Q | B5: 1.7 | C5: =D5 -> 157 | D5: 157 | E5: =100*B5/D5 -> 1.0828025 | F5: =E5*(1-10/300) -> 1.0467091 | G5: =F5*$G$11/100 -> 4.5793524
A6: #1 tranche | B6: 7.5 | C6: =D6-40 -> 260 | D6: 300 | E6: =100*B6/D6 -> 2.5 | F6: =E6 -> 2.5 | G6: =F6*$G$11/100 -> 10.9375
A7: August | B7: 1.1 | C7: =D7 -> 300 | D7: 300 | E7: =100*B7/D7 -> 0.36666667 | F7: =E7 -> 0.36666667 | G7: =F7*$G$11/100 -> 1.6041667
A8: Total | B8: =SUM(B4:B7) -> 10.8 | C8: =(C4*B4/$B$8)+(C5*B5/$B$8)+(C6*B6/$B$8)+(C7*B7/$B$8) -> 242.78704 | D8: =(D4*B4/$B$8)+(D5*B5/$B$8)+(D6*B6/$B$8)+(D7*B7/$B$8) -> 270.87037 | E8: =SUM(E4:E7) -> 4.2679406 | F8: =SUM(F4:F7) -> 4.2212314 | G8: =SUM(G4:G7) -> 18.467887
A9: "net profit" on OpenAI investment $bn | G9: =G8-B8 -> 7.6678875
A11: OpenAI all-in valuation at F2Q $bn | G11: 437.5 | H11: 500 | I11: = $6.6bn Oct. '25 employee share sale -> $1.45bn participation by SVF2.
A12: % uplift vs. prior $300bn all-in mark | G12: =G11/G20-1 -> 0.86170213 | H12: =1-G11/H11 -> 0.125 | I12: = % discount to publicly reported "mark-to-market".
G14: FY24 $bn
A15: Autumn '24 | B15: 0.5 | C15: =D15-6.6 -> 150.4 | D15: 157 | E15: =100*B15/D15 -> 0.31847134 | F15: =E15 -> 0.31847134 | G15: =F15*$G$20/100 -> 0.74840764
A16: C1Q | B16: 1.7 | C16: =D16 -> 157 | D16: 157 | E16: =100*B16/D16 -> 1.0828025 | F16: =E16 -> 1.0828025 | G16: =F16*$G$20/100 -> 2.544586
A17: Total | B17: =SUM(B15:B16) -> 2.2 | C17: =(C15*B15/$B$17)+(C16*B16/$B$17) -> 155.5 | D17: =(D15*B15/$B$17)+(D16*B16/$B$17) -> 157 | E17: =SUM(E15:E16) -> 1.4012739 | F17: =SUM(F15:F16) -> 1.4012739 | G17: =SUM(G15:G16) -> 3.2929936
A18: "net profit" on OpenAI investment $bn | G18: =G17-B17 -> 1.0929936
A20: OpenAI all-in valuation at FY24 $bn | G20: 235 | H20: 300 | I20: = $40bn CY25 funding round.
A21: % uplift vs. prior $300bn all-in mark | G21: =G20/$D$17-1 -> 0.49681529 | H21: =1-G20/H20 -> 0.21666667 | I21: = % discount to publicly reported "mark-to-market".
G23: F3Q $bn
A24: Autumn '24 | B24: 0.5 | C24: =D24-6.6 -> 150.4 | D24: 157 | E24: =100*B24/D24 -> 0.31847134 | F24: =E24*(1-41/300) -> 0.27494692 | G24: =F24*$G$32/100 -> 1.2372611
A25: C1Q | B25: 1.7 | C25: =D25 -> 157 | D25: 157 | E25: =100*B25/D25 -> 1.0828025 | F25: =E25*(1-41/300) -> 0.93481953 | G25: =F25*$G$32/100 -> 4.2066879
A26: #1 tranche | B26: 7.5 | C26: =D26-40 -> 260 | D26: 300 | E26: =100*B26/D26 -> 2.5 | F26: =E26 -> 2.5 | G26: =F26*$G$32/100 -> 11.25
A27: August | B27: 1.1 | C27: =D27 -> 300 | D27: 300 | E27: =100*B27/D27 -> 0.36666667 | F27: =E27*(1-30/300) -> 0.33 | G27: =F27*$G$32/100 -> 1.485
A28: October | B28: 1.45 | C28: =D28 -> 500 | D28: 500 | E28: =100*B28/D28 -> 0.29 | F28: =E28*(1-30/300) -> 0.261 | G28: =F28*$G$32/100 -> 1.1745
A29: #2 tranche | B29: 22.5 | C29: =D29-40 -> 260 | D29: 300 | E29: =100*B29/D29 -> 7.5 | F29: =E29 -> 7.5 | G29: =F29*$G$32/100 -> 33.75
A30: Total | B30: =SUM(B24:B29) -> 34.75 | C30: =(C24*B24/$B$30)+(C25*B25/$B$30)+(C26*B26/$B$30)+(C27*B27/$B$30)+(C28*B28/$B$30)+(C29*B29/$B$30) -> 264.66475 | D30: =(D24*B24/$B$30)+(D25*B25/$B$30)+(D26*B26/$B$30)+(D27*B27/$B$30)+(D28*B28/$B$30)+(D29*B29/$B$30) -> 299.29209 | E30: =SUM(E24:E29) -> 12.057941 | F30: =SUM(F24:F29) -> 11.800766 | G30: =SUM(G24:G29) -> 53.103449
A32: OpenAI all-in valuation at F3Q $bn | G32: 450
A33: % uplift vs. prior $300bn all-in mark | G33: =G32/G11-1 -> 0.028571429
A35: * $437.5bn estimate of OpenAI all-in valuation for existing stakes at F2Q (i.e., $10.8bn cumulative investments up to August '25) differs from valuation implied by "OpenAI Forward Contract" -> $8bn net profit on $22.5bn "notional" for #2 tranche = 35.5% implied uplift to $406.7bn -> IR guidance is that there is some level of "uncertainty" over $22.5bn Dec. '25 tranche (e.g., via options pricing) written into 30 Sep./F2Q mark, hence the implied all-in mark is different to existing investments.
A37: SVF2 "gain" on OpenAI investment in F3QE ->
A39: SVF2 existing investments | G39: =1000*G8*(G32/G11-1) -> 527.65393
A40: $22.5bn Dec. '25 investment | G40: =1000*(22.5*(G32/300-1)-8) -> 3250 | H40: -> $8bn net profit already recognised = $6.2bn at SVF2 and $1.8bn at "TopCo" or "SBG".
A41: Total SVF2 gain on OpenAI investment in F3Q $m | G41: =SUM(G39:G40) -> 3777.6539
A42: Gain/(loss) on publicly-listed assets | G42: ='SVF2'!AY68-'SVF2'!AX68 -> 1400
A43: Gain/(loss) on OpenAI private assets | G43: 0
A44: Effective SVF2 gain/(loss) in F3Q $m | G44: =SUM(G41:G43) -> 5177.6539
A45: % effective gain/(loss) | G45: =G44/AVERAGE('SVF2'!$AX$10:$AY$10) -> 0.072566979
A47: SVF2 "gain" on OpenAI investment in F3QE assuming OpenAI to $500bn all-in valuation ->
A49: SVF2 existing investments | G49: =1000*G8*(500/G11-1) -> 2638.2696
A50: $22.5bn Dec. '25 investment | G50: =1000*(22.5*(500/300-1)-8) -> 7000
A51: Total SVF2 gain on OpenAI investment in F3Q $m | G51: =SUM(G49:G50) -> 9638.2696
A52: Gain/(loss) on publicly-listed assets | G52: =G42 -> 1400
A53: Gain/(loss) on OpenAI private assets | G53: =G43 -> 0
A54: Effective SVF2 gain/(loss) in F3Q $m | G54: =SUM(G51:G53) -> 11038.27
A55: % effective gain/(loss) | G55: =G54/AVERAGE('SVF2'!$AX$10:$AY$10) -> 0.15470595
A57: NAV implication of taking OpenAI valuation from $450bn -> $500bn all-in (1) | G57: =G51-G44 -> 4460.6157
A58: -> check | G58: =G57-'SVF2'!$AY$143*(500/$G$32-1) -> -1583.8287
A60: NAV implication of taking OpenAI valuation from $450bn -> $500bn all-in (2) ->
A62: OpenAI PBC % equity | G62: =$F$30/100 -> 0.11800766
A63: $100bn incremental equity value $bn | G63: =G62*100 -> 11.800766
A64: JPY vs. USD | G64: =FP!$G$4 -> 155.1
A65: # of SoftBank Group shares | G65: =FP!$D$10 -> 5711.8481
A66: NAV/share impact | G66: =MROUND((1000*G63/G65)*G64, 5) -> 320
A67: PF impact % | G67: =G66/FP!$H$34 -> 0.055459272
A68: impact on PF % NAV discount | G68: =1-((100*(1-FP!$I$34))/(100*(1+G67))) -> 0.33563218
A69: delta | G69: =G68-FP!$I$34 -> 0.036845355
A71: Increase in OpenAI valuation -> | G71: 50
A72: = scaled to $100bn. | G72: =G71/100 -> 0.5
A73: NAV/share impact | G73: =MROUND(G72*G66, 5) -> 160
A74: PF impact % | G74: =G73/FP!$H$34 -> 0.027729636
A76: SoftBank $100bn Funding participation..?
A77: SoftBank PF NAV/share ¥ | D77: =FP!$H$34 -> 5770
A78: # of SoftBank shares (millions) | D78: =$G$65 -> 5711.8481
A79: ¥ vs. US$ | D79: =$G$64 -> 155.1
A80: 11.8% OpenAI @ $450bn | D80: =11.8%*450 -> 53.1
A81: OpenAI NAV/share ¥ | D81: =MROUND(1000*D80*$D$79/$D$78, 5) -> 1440
A82: % of SoftBank NAV | D82: =D81/D77 -> 0.24956672
A83: 11.8% OpenAI @ $830bn | D83: =11.8%*830 -> 97.94
A84: Less: 10% haircut on SBG "mark" | D84: =-10%*D83 -> -9.794
A85: OpenAI stake carrying value $bn | D85: =SUM(D83:D84) -> 88.146
A86: OpenAI NAV/share ¥ | D86: =MROUND(1000*D85*$D$79/$D$78, 5) -> 2395
A87: Increase in carrying value | D87: =D85-D80 -> 35.046
A88: Less: 11.8% share of $100bn commit. | D88: =-11.8%*100 -> -11.8
A89: Increase in SoftBank NAV | D89: =SUM(D87:D88) -> 23.246
A90: Increase in PF NAV/share ¥ | D90: =MROUND(1000*D89*$D$79/$D$78, 5) -> 630
A91: SoftBank PF NAV/share ¥ | D91: =D77+D90 -> 6400
A92: vs. SoftBank share price today ¥ | D92: =FP!$D$9 -> 4046

Sheet OpenAI Valuation table
B1: Cost $bn | C1: Pre-money $bn | D1: Post-money $bn | E1: % | F1: Diluted % | G1: F2Q $bn | H1: F3QE $bn | K1: 11.8 | L1: 11.5 | M1: 11 | O1: OpenAI PBC dilution from all-equity acquisitions + third-party investments (e.g., Disney) ->
A2: Autumn '24 | B2: ='OpenAI SBG "rough"'!B24 -> 0.5 | C2: ='OpenAI SBG "rough"'!C24 -> 150.4 | D2: ='OpenAI SBG "rough"'!D24 -> 157 | E2: ='OpenAI SBG "rough"'!E24 -> 0.31847134 | F2: ='OpenAI SBG "rough"'!F24 -> 0.27494692 | G2: ='OpenAI SBG "rough"'!G4 -> 1.3468684 | H2: ='OpenAI SBG "rough"'!G24 -> 1.2372611 | K2: =H2*$K$15/$H$15 -> 1.2785032 | L2: =($L$1/$F$14)*H2*$L$15/$H$15 -> 1.2727119 | M2: =($M$1/$F$14)*H2*$M$15/$H$15 -> 1.281449 | O2: Company | P2: Date | Q2: Transaction | R2: Valuation | S2: OAI all-in | T2: % dilution | V2: Comments ->
A3: C1Q | B3: ='OpenAI SBG "rough"'!B25 -> 1.7 | C3: ='OpenAI SBG "rough"'!C25 -> 157 | D3: ='OpenAI SBG "rough"'!D25 -> 157 | E3: ='OpenAI SBG "rough"'!E25 -> 1.0828025 | F3: ='OpenAI SBG "rough"'!F25 -> 0.93481953 | G3: ='OpenAI SBG "rough"'!G5 -> 4.5793524 | H3: ='OpenAI SBG "rough"'!G25 -> 4.2066879 | K3: =H3*$K$15/$H$15 -> 4.3469108 | L3: =($L$1/$F$14)*H3*$L$15/$H$15 -> 4.3272204 | M3: =($M$1/$F$14)*H3*$M$15/$H$15 -> 4.3569267 | O3: io | P3: May '25 | Q3: Acquired | R3: 6.5 | S3: 300 | T3: =R3/S3 -> 0.021666667
A4: #1 tranche | B4: ='OpenAI SBG "rough"'!B26 -> 7.5 | C4: ='OpenAI SBG "rough"'!C26 -> 260 | D4: ='OpenAI SBG "rough"'!D26 -> 300 | E4: ='OpenAI SBG "rough"'!E26 -> 2.5 | F4: ='OpenAI SBG "rough"'!F26 -> 2.5 | G4: ='OpenAI SBG "rough"'!G6 -> 10.9375 | H4: ='OpenAI SBG "rough"'!G26 -> 11.25 | K4: =H4*$K$15/$H$15 -> 11.625 | L4: =($L$1/$F$14)*H4*$L$15/$H$15 -> 11.572342 | M4: =($M$1/$F$14)*H4*$M$15/$H$15 -> 11.651786 | O4: Statsig | P4: Sep. '25 | Q4: Acquired | R4: 1.1 | S4: 300 | T4: =R4/S4 -> 0.0036666667
A5: August | B5: ='OpenAI SBG "rough"'!B27 -> 1.1 | C5: ='OpenAI SBG "rough"'!C27 -> 300 | D5: ='OpenAI SBG "rough"'!D27 -> 300 | E5: ='OpenAI SBG "rough"'!E27 -> 0.36666667 | F5: ='OpenAI SBG "rough"'!F27 -> 0.33 | G5: ='OpenAI SBG "rough"'!G7 -> 1.6041667 | H5: ='OpenAI SBG "rough"'!G27 -> 1.485 | K5: =H5*$K$15/$H$15 -> 1.5345 | L5: =($L$1/$F$14)*H5*$L$15/$H$15 -> 1.5275491 | M5: =($M$1/$F$14)*H5*$M$15/$H$15 -> 1.5380357 | O5: Neptune.ai | P5: Dec. '25 | Q5: Acquired | R5: 0.4 | S5: 300 | T5: =R5/S5 -> 0.0013333333
A6: Total | B6: =SUM(B2:B5) -> 10.8 | C6: ='OpenAI SBG "rough"'!$C$8 -> 242.78704 | D6: ='OpenAI SBG "rough"'!$D$8 -> 270.87037 | E6: =SUM(E2:E5) -> 4.2679406 | F6: =SUM(F2:F5) -> 4.0397665 | G6: =SUM(G2:G5) -> 18.467887 | H6: =SUM(H2:H5) -> 18.178949 | K6: =SUM(K2:K5) -> 18.784914 | L6: =SUM(L2:L5) -> 18.699823 | M6: =SUM(M2:M5) -> 18.828197 | O6: Disney | P6: Dec. '25 | Q6: Investor | R6: 1 | S6: 300 | T6: =R6/S6 -> 0.0033333333
A7: OpenAI "all-in" | G7: ='OpenAI SBG "rough"'!$G$11 -> 437.5 | H7: ='OpenAI SBG "rough"'!$G$32 -> 450 | O7: SBC | P7: 2025 | Q7: SBC | R7: 6 | S7: 300 | T7: =R7/S7 -> 0.02 | V7: = Wall Street Journal reported OpenAI paying $1.5m SBC per employee -> given 4k employees in '25 this implies $6bn in SBC.
A8: Forward contract | C8: 260 | D8: 300 | E8: 7.5 | F8: 7.5 | G8: 8 | H8: 0 | O8: Total dilution | R8: =SUM(R3:R7) -> 15 | S8: =R8/T8 -> 300 | T8: =SUM(T3:T7) -> 0.05
A9: = implied "all-in" valuation for Forward contract | G9: =300*(22.5+G8)/22.5 -> 406.66667 | H9: n/a
A10: Total P.F. | C10: =C6*F6/F10+C8*F8/F10 -> 253.9742 | D10: =D6*F6/F10+D8*F8/F10 -> 289.80249 | E10: =E6+E8 -> 11.767941 | F10: =F6+F8 -> 11.539766 | G10: =G6+G8 -> 26.467887
A11: OpenAI "all-in" | G11: =G7*F6/F10+G9*F8/F10 -> 417.4606
A12: October | B12: ='OpenAI SBG "rough"'!B28 -> 1.45 | C12: ='OpenAI SBG "rough"'!C28 -> 500 | D12: ='OpenAI SBG "rough"'!D28 -> 500 | E12: ='OpenAI SBG "rough"'!E28 -> 0.29 | F12: ='OpenAI SBG "rough"'!F28 -> 0.261 | H12: ='OpenAI SBG "rough"'!G28 -> 1.1745 | K12: =H12*$K$15/$H$15 -> 1.21365 | L12: =($L$1/$F$14)*H12*$L$15/$H$15 -> 1.2081525 | M12: =($M$1/$F$14)*H12*$M$15/$H$15 -> 1.2164464
A13: #2 tranche | B13: ='OpenAI SBG "rough"'!B29 -> 22.5 | C13: ='OpenAI SBG "rough"'!C29 -> 260 | D13: ='OpenAI SBG "rough"'!D29 -> 300 | E13: ='OpenAI SBG "rough"'!E29 -> 7.5 | F13: ='OpenAI SBG "rough"'!F29 -> 7.5 | H13: ='OpenAI SBG "rough"'!G29 -> 33.75 | K13: =H13*$K$15/$H$15 -> 34.875 | L13: =($L$1/$F$14)*H13*$L$15/$H$15 -> 34.717025 | M13: =($M$1/$F$14)*H13*$M$15/$H$15 -> 34.955357
A14: Total | B14: =B6+SUM(B12:B13) -> 34.75 | C14: =C6*F6/F14+C12*F12/F14+C13*F13/F14 -> 259.4156 | D14: =D6*F6/F14+D12*F12/F14+D13*F13/F14 -> 294.45147 | E14: =E6+SUM(E12:E13) -> 12.057941 | F14: =F6+SUM(F12:F13) -> 11.800766 | H14: =H6+SUM(H12:H13) -> 53.103449 | K14: =K6+SUM(K12:K13) -> 54.873564 | L14: =L6+SUM(L12:L13) -> 54.625 | M14: =M6+SUM(M12:M13) -> 55
A15: OpenAI "all-in" | H15: ='OpenAI SBG "rough"'!$G$32 -> 450 | K15: 465 | L15: 475 | M15: 500
A16: Net gain | H16: =H14-B14 -> 18.353449
A17: MOIC | H17: =H15/$D$14 -> 1.5282654
A19: OpenAI $500bn all-in valuation
A20: Total | H20: =H14*H21/H15 -> 59.003832
A21: OpenAI "all-in" | H21: 500
A22: Net gain | H22: =H20-$B$14 -> 24.253832
A23: MOIC | H23: =H21/$D$14 -> 1.6980727
A25: SVF2 OpenAI distribution waterfall ->
A27: OpenAI all-in valuation at Mar. '31E ("2030 Vision") $tn | E27: =F27-0.25 -> 0.5 | F27: =G27-0.25 -> 0.75 | G27: =H27-0.5 -> 1 | H27: =I27-0.5 -> 1.5 | I27: =J27-0.5 -> 2 | J27: =K27-0.5 -> 2.5 | K27: =L27-0.5 -> 3 | L27: 3.5
A28: OpenAI investment cost | E28: =$B$14 -> 34.75 | F28: =$B$14 -> 34.75 | G28: =$B$14 -> 34.75 | H28: =$B$14 -> 34.75 | I28: =$B$14 -> 34.75 | J28: =$B$14 -> 34.75 | K28: =$B$14 -> 34.75 | L28: =$B$14 -> 34.75
A29: Add: $1.8bn paid to TopCo for "OpenAI Forward Contract" | E29: 1.8 | F29: 1.8 | G29: 1.8 | H29: 1.8 | I29: 1.8 | J29: 1.8 | K29: 1.8 | L29: 1.8
A30: Add: 11.8% contribution to $100bn raise | E30: =11.8%*100 -> 11.8 | F30: =11.8%*100 -> 11.8 | G30: =11.8%*100 -> 11.8 | H30: =11.8%*100 -> 11.8 | I30: =11.8%*100 -> 11.8 | J30: =11.8%*100 -> 11.8 | K30: =11.8%*100 -> 11.8 | L30: =11.8%*100 -> 11.8
A31: Total invested capital in OpenAI Global LLC | E31: =SUM(E28:E30) -> 48.35 | F31: =SUM(F28:F30) -> 48.35 | G31: =SUM(G28:G30) -> 48.35 | H31: =SUM(H28:H30) -> 48.35 | I31: =SUM(I28:I30) -> 48.35 | J31: =SUM(J28:J30) -> 48.35 | K31: =SUM(K28:K30) -> 48.35 | L31: =SUM(L28:L30) -> 48.35
A32: Preferred equity invested (= 80%) | E32: =$F$54*E31 -> 38.68 | F32: =$F$54*F31 -> 38.68 | G32: =$F$54*G31 -> 38.68 | H32: =$F$54*H31 -> 38.68 | I32: =$F$54*I31 -> 38.68 | J32: =$F$54*J31 -> 38.68 | K32: =$F$54*K31 -> 38.68 | L32: =$F$54*L31 -> 38.68
A33: Ordinary equity invested (= 20%) | E33: =E31-E32 -> 9.67 | F33: =F31-F32 -> 9.67 | G33: =G31-G32 -> 9.67 | H33: =H31-H32 -> 9.67 | I33: =I31-I32 -> 9.67 | J33: =J31-J32 -> 9.67 | K33: =K31-K32 -> 9.67 | L33: =L31-L32 -> 9.67
A34: 11.8% OpenAI Global LLC @ Mar. '31E | E34: =E27/$L$27*$L$34 -> 59 | F34: =F27/$L$27*$L$34 -> 88.5 | G34: =G27/$L$27*$L$34 -> 118 | H34: =H27/$L$27*$L$34 -> 177 | I34: =I27/$L$27*$L$34 -> 236 | J34: =J27/$L$27*$L$34 -> 295 | K34: =K27/$L$27*$L$34 -> 354 | L34: =11.8%*L27*1000 -> 413
A35: Less: $7.5bn intercompany loan @4% | E35: =-7.5*(1+4%)^(5) -> -9.1248968 | F35: =-7.5*(1+4%)^(5) -> -9.1248968 | G35: =-7.5*(1+4%)^(5) -> -9.1248968 | H35: =-7.5*(1+4%)^(5) -> -9.1248968 | I35: =-7.5*(1+4%)^(5) -> -9.1248968 | J35: =-7.5*(1+4%)^(5) -> -9.1248968 | K35: =-7.5*(1+4%)^(5) -> -9.1248968 | L35: =-7.5*(1+4%)^(5) -> -9.1248968
A36: Less: 5 years CAGR on Preferred equity @ 8% | E36: =-E32*(1+8%)^(5) -> -56.83361 | F36: =-F32*(1+8%)^(5) -> -56.83361 | G36: =-G32*(1+8%)^(5) -> -56.83361 | H36: =-H32*(1+8%)^(5) -> -56.83361 | I36: =-I32*(1+8%)^(5) -> -56.83361 | J36: =-J32*(1+8%)^(5) -> -56.83361 | K36: =-K32*(1+8%)^(5) -> -56.83361 | L36: =-L32*(1+8%)^(5) -> -56.83361
A37: SVF2 LLC Ordinary equity OpenAI | E37: =IF(SUM(E34:E36)>0, SUM(E34:E36), 0) -> 0 | F37: =IF(SUM(F34:F36)>0, SUM(F34:F36), 0) -> 22.541493 | G37: =IF(SUM(G34:G36)>0, SUM(G34:G36), 0) -> 52.041493 | H37: =IF(SUM(H34:H36)>0, SUM(H34:H36), 0) -> 111.04149 | I37: =IF(SUM(I34:I36)>0, SUM(I34:I36), 0) -> 170.04149 | J37: =IF(SUM(J34:J36)>0, SUM(J34:J36), 0) -> 229.04149 | K37: =IF(SUM(K34:K36)>0, SUM(K34:K36), 0) -> 288.04149 | L37: =IF(SUM(L34:L36)>0, SUM(L34:L36), 0) -> 347.04149
A38: Less: 12.5% p.a. "hurdle rate" | E38: =E33*(1+12.5%)^(5) -> 17.425654 | F38: =F33*(1+12.5%)^(5) -> 17.425654 | G38: =G33*(1+12.5%)^(5) -> 17.425654 | H38: =H33*(1+12.5%)^(5) -> 17.425654 | I38: =I33*(1+12.5%)^(5) -> 17.425654 | J38: =J33*(1+12.5%)^(5) -> 17.425654 | K38: =K33*(1+12.5%)^(5) -> 17.425654 | L38: =L33*(1+12.5%)^(5) -> 17.425654
A39: Equity returns above "hurdle rate" | E39: =IF(E37-E38>0, E37-E38, 0) -> 0 | F39: =IF(F37-F38>0, F37-F38, 0) -> 5.1158392 | G39: =IF(G37-G38>0, G37-G38, 0) -> 34.615839 | H39: =IF(H37-H38>0, H37-H38, 0) -> 93.615839 | I39: =IF(I37-I38>0, I37-I38, 0) -> 152.61584 | J39: =IF(J37-J38>0, J37-J38, 0) -> 211.61584 | K39: =IF(K37-K38>0, K37-K38, 0) -> 270.61584 | L39: =IF(L37-L38>0, L37-L38, 0) -> 329.61584
A40: SoftBank Group @ Mar. '31E
A41: $7.5bn intercompany loan | E41: =-E35 -> 9.1248968 | F41: =-F35 -> 9.1248968 | G41: =-G35 -> 9.1248968 | H41: =-H35 -> 9.1248968 | I41: =-I35 -> 9.1248968 | J41: =-J35 -> 9.1248968 | K41: =-K35 -> 9.1248968 | L41: =-L35 -> 9.1248968
A42: Preferred equity | E42: =IF(-SUM(E35:E36)>E34, E34+E35, -E36) -> 49.875103 | F42: =IF(-SUM(F35:F36)>F34, F34+F35, -F36) -> 56.83361 | G42: =IF(-SUM(G35:G36)>G34, G34+G35, -G36) -> 56.83361 | H42: =IF(-SUM(H35:H36)>H34, H34+H35, -H36) -> 56.83361 | I42: =IF(-SUM(I35:I36)>I34, I34+I35, -I36) -> 56.83361 | J42: =IF(-SUM(J35:J36)>J34, J34+J35, -J36) -> 56.83361 | K42: =IF(-SUM(K35:K36)>K34, K34+K35, -K36) -> 56.83361 | L42: =IF(-SUM(L35:L36)>L34, L34+L35, -L36) -> 56.83361
A43: 25% management performance fee | E43: =IF(E39>0, 25%*E39, 0) -> 0 | F43: =IF(F39>0, 25%*F39, 0) -> 1.2789598 | G43: =IF(G39>0, 25%*G39, 0) -> 8.6539598 | H43: =IF(H39>0, 25%*H39, 0) -> 23.40396 | I43: =IF(I39>0, 25%*I39, 0) -> 38.15396 | J43: =IF(J39>0, 25%*J39, 0) -> 52.90396 | K43: =IF(K39>0, 25%*K39, 0) -> 67.65396 | L43: =IF(L39>0, 25%*L39, 0) -> 82.40396
A44: 82.75% SoftBank Group equity | E44: =IF(E39>0, 82.75%*(E37-E43), 82.75%*E37) -> 0 | F44: =IF(F39>0, 82.75%*(F37-F43), 82.75%*F37) -> 17.594746 | G44: =IF(G39>0, 82.75%*(G37-G43), 82.75%*G37) -> 35.903184 | H44: =IF(H39>0, 82.75%*(H37-H43), 82.75%*H37) -> 72.520059 | I44: =IF(I39>0, 82.75%*(I37-I43), 82.75%*I37) -> 109.13693 | J44: =IF(J39>0, 82.75%*(J37-J43), 82.75%*J37) -> 145.75381 | K44: =IF(K39>0, 82.75%*(K37-K43), 82.75%*K37) -> 182.37068 | L44: =IF(L39>0, 82.75%*(L37-L43), 82.75%*L37) -> 218.98756
A45: SoftBank Group @ Mar. '31E | E45: =SUM(E41:E44) -> 59 | F45: =SUM(F41:F44) -> 84.832213 | G45: =SUM(G41:G44) -> 110.51565 | H45: =SUM(H41:H44) -> 161.88253 | I45: =SUM(I41:I44) -> 213.2494 | J45: =SUM(J41:J44) -> 264.61628 | K45: =SUM(K41:K44) -> 315.98315 | L45: =SUM(L41:L44) -> 367.35003
A46: % share of 11.8% OpenAI | E46: =E45/E34 -> 1 | F46: =F45/F34 -> 0.95855608 | G46: =G45/G34 -> 0.93657331 | H46: =H45/H34 -> 0.91459054 | I46: =I45/I34 -> 0.90359915 | J46: =J45/J34 -> 0.89700432 | K46: =K45/K34 -> 0.89260777 | L46: =L45/L34 -> 0.88946737
A47: % share of SVF2 LLC ordinary equity | F47: =SUM(F43:F44)/F37 -> 0.83728731 | G47: =SUM(G43:G44)/G37 -> 0.85618496 | H47: =SUM(H43:H44)/H37 -> 0.86385743 | I47: =SUM(I43:I44)/I37 -> 0.8662056 | J47: =SUM(J43:J44)/J37 -> 0.86734402 | K47: =SUM(K43:K44)/K37 -> 0.86801607 | L47: =SUM(L43:L44)/L37 -> 0.86845961
A48: Masayoshi Son @ Mar. '31E | E48: =IF(E37>0, E37-E43-E44, 0) -> 0 | F48: =IF(F37>0, F37-F43-F44, 0) -> 3.667787 | G48: =IF(G37>0, G37-G43-G44, 0) -> 7.4843495 | H48: =IF(H37>0, H37-H43-H44, 0) -> 15.117475 | I48: =IF(I37>0, I37-I43-I44, 0) -> 22.7506 | J48: =IF(J37>0, J37-J43-J44, 0) -> 30.383725 | K48: =IF(K37>0, K37-K43-K44, 0) -> 38.01685 | L48: =IF(L37>0, L37-L43-L44, 0) -> 45.649975
A49: % share of 11.8% OpenAI | E49: =E48/E34 -> 0 | F49: =F48/F34 -> 0.041443921 | G49: =G48/G34 -> 0.063426691 | H49: =H48/H34 -> 0.085409461 | I49: =I48/I34 -> 0.096400845 | J49: =J48/J34 -> 0.10299568 | K49: =K48/K34 -> 0.10739223 | L49: =L48/L34 -> 0.11053263
A50: % share of SVF2 LLC ordinary equity | F50: =F48/F37 -> 0.16271269 | G50: =G48/G37 -> 0.14381504 | H50: =H48/H37 -> 0.13614257 | I50: =I48/I37 -> 0.1337944 | J50: =J48/J37 -> 0.13265598 | K50: =K48/K37 -> 0.13198393 | L50: =L48/L37 -> 0.13154039
A52: SVF2 LLC "joint investments" capital structure ->
G53: = reset for additional SVF2 capital contributions in form of Preferred equity to cover further investments in OpenAI PBC.
A54: Preferred equity | E54: ='SVF Segment'!$AY$787/1000 -> 66.9 | F54: =MROUND(E54/E56, 5%) -> 0.8 | G54: 0.9 | H54: = see SVF2 % of Preferred equity excl. "outside scope of co-investment".
A55: Ordinary equity | E55: =SUM('SVF Segment'!$AY$788:$AY$789)/1000 -> 15 | F55: =1-F54 -> 0.2 | G55: 0.1
A56: Total | E56: =SUM(E54:E55) -> 81.9
A58: SVF2 OpenAI distribution waterfall ->
A60: OpenAI all-in valuation at Mar. '31E ("2030 Vision") $tn | E60: =F60-0.25 -> 0.5 | F60: =G60-0.25 -> 0.75 | G60: =H60-0.5 -> 1 | H60: =I60-0.5 -> 1.5 | I60: =J60-0.5 -> 2 | J60: =K60-0.5 -> 2.5 | K60: =L60-0.5 -> 3 | L60: 3.5
A61: OpenAI investment cost | E61: 64.6 | F61: 64.6 | G61: 64.6 | H61: 64.6 | I61: 64.6 | J61: 64.6 | K61: 64.6 | L61: 64.6
A62: Add: $1.8bn paid to TopCo for "OpenAI Forward Contract" | E62: 1.8 | F62: 1.8 | G62: 1.8 | H62: 1.8 | I62: 1.8 | J62: 1.8 | K62: 1.8 | L62: 1.8
A63: Add: 13.25% contribution to remaining $76bn cash burn | E63: =13.25%*76 -> 10.07 | F63: =13.25%*76 -> 10.07 | G63: =13.25%*76 -> 10.07 | H63: =13.25%*76 -> 10.07 | I63: =13.25%*76 -> 10.07 | J63: =13.25%*76 -> 10.07 | K63: =13.25%*76 -> 10.07 | L63: =13.25%*76 -> 10.07
A64: Total invested capital in OpenAI Global LLC | E64: =SUM(E61:E63) -> 76.47 | F64: =SUM(F61:F63) -> 76.47 | G64: =SUM(G61:G63) -> 76.47 | H64: =SUM(H61:H63) -> 76.47 | I64: =SUM(I61:I63) -> 76.47 | J64: =SUM(J61:J63) -> 76.47 | K64: =SUM(K61:K63) -> 76.47 | L64: =SUM(L61:L63) -> 76.47
A65: Preferred equity invested (= 90%) | E65: =$G$54*E64 -> 68.823 | F65: =$G$54*F64 -> 68.823 | G65: =$G$54*G64 -> 68.823 | H65: =$G$54*H64 -> 68.823 | I65: =$G$54*I64 -> 68.823 | J65: =$G$54*J64 -> 68.823 | K65: =$G$54*K64 -> 68.823 | L65: =$G$54*L64 -> 68.823
A66: Ordinary equity invested (= 10%) | E66: =E64-E65 -> 7.647 | F66: =F64-F65 -> 7.647 | G66: =G64-G65 -> 7.647 | H66: =H64-H65 -> 7.647 | I66: =I64-I65 -> 7.647 | J66: =J64-J65 -> 7.647 | K66: =K64-K65 -> 7.647 | L66: =L64-L65 -> 7.647
A67: 13.25% OpenAI Global LLC @ Mar. '31E | E67: =E60/$L$60*$L$67 -> 66.25 | F67: =F60/$L$60*$L$67 -> 99.375 | G67: =G60/$L$60*$L$67 -> 132.5 | H67: =H60/$L$60*$L$67 -> 198.75 | I67: =I60/$L$60*$L$67 -> 265 | J67: =J60/$L$60*$L$67 -> 331.25 | K67: =K60/$L$60*$L$67 -> 397.5 | L67: =13.25%*L60*1000 -> 463.75
A68: Less: 5 years CAGR on Preferred equity @ 8-9% | E68: =-E65*(1+8.5%)^(5) -> -103.48616 | F68: =-F65*(1+8.5%)^(5) -> -103.48616 | G68: =-G65*(1+8.5%)^(5) -> -103.48616 | H68: =-H65*(1+8.5%)^(5) -> -103.48616 | I68: =-I65*(1+8.5%)^(5) -> -103.48616 | J68: =-J65*(1+8.5%)^(5) -> -103.48616 | K68: =-K65*(1+8.5%)^(5) -> -103.48616 | L68: =-L65*(1+8.5%)^(5) -> -103.48616 | M68: = n.b., new SVF2 "Preferred equity" issued to TopCo is being issued @ 9%.
A69: SVF2 LLC Ordinary equity OpenAI | E69: =IF(SUM(E67:E68)>0, SUM(E67:E68), 0) -> 0 | F69: =IF(SUM(F67:F68)>0, SUM(F67:F68), 0) -> 0 | G69: =IF(SUM(G67:G68)>0, SUM(G67:G68), 0) -> 29.013836 | H69: =IF(SUM(H67:H68)>0, SUM(H67:H68), 0) -> 95.263836 | I69: =IF(SUM(I67:I68)>0, SUM(I67:I68), 0) -> 161.51384 | J69: =IF(SUM(J67:J68)>0, SUM(J67:J68), 0) -> 227.76384 | K69: =IF(SUM(K67:K68)>0, SUM(K67:K68), 0) -> 294.01384 | L69: =IF(SUM(L67:L68)>0, SUM(L67:L68), 0) -> 360.26384
A70: Less: 15% p.a. "hurdle rate" | E70: =E66*(1+12.5%)^(5) -> 13.780142 | F70: =F66*(1+12.5%)^(5) -> 13.780142 | G70: =G66*(1+12.5%)^(5) -> 13.780142 | H70: =H66*(1+12.5%)^(5) -> 13.780142 | I70: =I66*(1+12.5%)^(5) -> 13.780142 | J70: =J66*(1+12.5%)^(5) -> 13.780142 | K70: =K66*(1+12.5%)^(5) -> 13.780142 | L70: =L66*(1+12.5%)^(5) -> 13.780142
A71: Equity returns above "hurdle rate" | E71: =IF(E69-E70>0, E69-E70, 0) -> 0 | F71: =IF(F69-F70>0, F69-F70, 0) -> 0 | G71: =IF(G69-G70>0, G69-G70, 0) -> 15.233693 | H71: =IF(H69-H70>0, H69-H70, 0) -> 81.483693 | I71: =IF(I69-I70>0, I69-I70, 0) -> 147.73369 | J71: =IF(J69-J70>0, J69-J70, 0) -> 213.98369 | K71: =IF(K69-K70>0, K69-K70, 0) -> 280.23369 | L71: =IF(L69-L70>0, L69-L70, 0) -> 346.48369
A72: SoftBank Group @ Mar. '31E
A73: Preferred equity | E73: =IF(-E68>E67, E67, -E68) -> 66.25 | F73: =IF(-F68>F67, F67, -F68) -> 99.375 | G73: =IF(-G68>G67, G67, -G68) -> 103.48616 | H73: =IF(-H68>H67, H67, -H68) -> 103.48616 | I73: =IF(-I68>I67, I67, -I68) -> 103.48616 | J73: =IF(-J68>J67, J67, -J68) -> 103.48616 | K73: =IF(-K68>K67, K67, -K68) -> 103.48616 | L73: =IF(-L68>L67, L67, -L68) -> 103.48616
A74: 25% management performance fee | E74: =IF(E71>0, 25%*E71, 0) -> 0 | F74: =IF(F71>0, 25%*F71, 0) -> 0 | G74: =IF(G71>0, 25%*G71, 0) -> 3.8084233 | H74: =IF(H71>0, 25%*H71, 0) -> 20.370923 | I74: =IF(I71>0, 25%*I71, 0) -> 36.933423 | J74: =IF(J71>0, 25%*J71, 0) -> 53.495923 | K74: =IF(K71>0, 25%*K71, 0) -> 70.058423 | L74: =IF(L71>0, 25%*L71, 0) -> 86.620923
A75: 82.75% SoftBank Group equity | E75: =IF(E71>0, 82.75%*(E69-E74), 82.75%*E69) -> 0 | F75: =IF(F71>0, 82.75%*(F69-F74), 82.75%*F69) -> 0 | G75: =IF(G71>0, 82.75%*(G69-G74), 82.75%*G69) -> 20.857479 | H75: =IF(H71>0, 82.75%*(H69-H74), 82.75%*H69) -> 61.973885 | I75: =IF(I71>0, 82.75%*(I69-I74), 82.75%*I69) -> 103.09029 | J75: =IF(J71>0, 82.75%*(J69-J74), 82.75%*J69) -> 144.2067 | K75: =IF(K71>0, 82.75%*(K69-K74), 82.75%*K69) -> 185.3231 | L75: =IF(L71>0, 82.75%*(L69-L74), 82.75%*L69) -> 226.43951
A76: SoftBank Group @ Mar. '31E | E76: =SUM(E72:E75) -> 66.25 | F76: =SUM(F72:F75) -> 99.375 | G76: =SUM(G72:G75) -> 128.15207 | H76: =SUM(H72:H75) -> 185.83097 | I76: =SUM(I72:I75) -> 243.50988 | J76: =SUM(J72:J75) -> 301.18879 | K76: =SUM(K72:K75) -> 358.86769 | L76: =SUM(L72:L75) -> 416.5466
A77: % share of 11.8% OpenAI | E77: =E76/E67 -> 1 | F77: =F76/F67 -> 1 | G77: =G76/G67 -> 0.96718541 | H77: =H76/H67 -> 0.9349986 | I77: =I76/I67 -> 0.9189052 | J77: =J76/J67 -> 0.90924916 | K77: =K76/K67 -> 0.9028118 | L77: =L76/L67 -> 0.89821369
A78: % share of SVF2 LLC ordinary equity | F78: =SUM(F74:F75)/F69 -> #DIV/0! | G78: =SUM(G74:G75)/G69 -> 0.85014275 | H78: =SUM(H74:H75)/H69 -> 0.86438687 | I78: =SUM(I74:I75)/I69 -> 0.86694563 | J78: =SUM(J74:J75)/J69 -> 0.86801586 | K78: =SUM(K74:K75)/K69 -> 0.86860377 | L78: =SUM(L74:L75)/L69 -> 0.86897546
A79: Masayoshi Son @ Mar. '31E | E79: =IF(E69>0, E69-E74-E75, 0) -> 0 | F79: =IF(F69>0, F69-F74-F75, 0) -> 0 | G79: =IF(G69>0, G69-G74-G75, 0) -> 4.3479336 | H79: =IF(H69>0, H69-H74-H75, 0) -> 12.919027 | I79: =IF(I69>0, I69-I74-I75, 0) -> 21.490121 | J79: =IF(J69>0, J69-J74-J75, 0) -> 30.061215 | K79: =IF(K69>0, K69-K74-K75, 0) -> 38.632309 | L79: =IF(L69>0, L69-L74-L75, 0) -> 47.203402
A80: % share of 11.8% OpenAI | E80: =E79/E67 -> 0 | F80: =F79/F67 -> 0 | G80: =G79/G67 -> 0.032814593 | H80: =H79/H67 -> 0.065001396 | I80: =I79/I67 -> 0.081094797 | J80: =J79/J67 -> 0.090750837 | K80: =K79/K67 -> 0.097188198 | L80: =L79/L67 -> 0.10178631
A81: % share of SVF2 LLC ordinary equity | F81: =F79/F69 -> #DIV/0! | G81: =G79/G69 -> 0.14985725 | H81: =H79/H69 -> 0.13561313 | I81: =I79/I69 -> 0.13305437 | J81: =J79/J69 -> 0.13198414 | K81: =K79/K69 -> 0.13139623 | L81: =L79/L69 -> 0.13102454

Sheet Valuation & SBG NAV
AE1: 3Q18 | AF1: 4Q18 | AG1: FY18 | AH1: 1Q19 | AI1: 2Q19 | AJ1: 3Q19 | AK1: 4Q19 | AL1: FY19 | AM1: 1Q20 | AN1: 2Q20 | AO1: 3Q20 | AP1: 4Q20 | AQ1: FY20 | AR1: 1Q21 | AS1: 2Q21 | AT1: 3Q21 | AU1: 4Q21 | AV1: FY21 | AW1: 1Q22 | AX1: 2Q22 | AY1: 3Q22 | AZ1: 4Q22 | BA1: FY22 | BB1: 1Q23 | BC1: 2Q23 | BD1: 3Q23 | BE1: 4Q23 | BF1: FY23 | BG1: 1Q24 | BH1: 2Q24 | BI1: 3Q24 | BJ1: 4Q24 | BK1: FY24 | BL1: 1Q25 | BM1: 2Q25 | BN1: 3Q25 | BO1: 4Q25E | BP1: FY25E | BQ1: 1Q26E | BR1: 2Q26E | BS1: 3Q26E | BT1: 4Q26E | BU1: FY26E
A2: SoftBank Group Corp. | I2: Jun. '14 | J2: Sep. '14 | K2: Dec. '14 | M2: = year ending 31 March '15. | N2: Jun. '15 | O2: Sep. '15 | P2: Dec. '15 | R2: = year ending 31 March '16. | S2: Jun. '16 | T2: Sep. '16 | U2: Dec. '16 | W2: = year ending 31 March '17. | X2: Jun. '17 | Y2: Sep. '17 | Z2: Dec. '17 | AB2: = year ending 31 March '18. | AC2: Jun. '18 | AD2: Sep. '18 | AE2: Dec. '18 | AG2: = year ending 31 March '19. | AH2: Jun. '19 | AI2: Sep. '19 | AJ2: Dec. '19 | AL2: = year ending 31 March '20. | AM2: Jun. '20 | AN2: Sep. '20 | AO2: Dec. '20 | AQ2: = year ending 31 March '21. | AR2: Jun. '21 | AS2: Sep. '21 | AT2: Dec. '21 | AV2: = year ending 31 March '22. | AW2: Jun. '22 | AX2: Sep. '22 | AY2: Dec. '22 | BA2: = year ending 31 March '23. | BB2: Jun. '23 | BC2: Sep. '23 | BD2: Dec. '23 | BF2: = year ending 31 March '24. | BG2: Jun. '24 | BH2: Sep. '24 | BI2: Dec. '24 | BK2: = year ending 31 March '25. | BL2: Jun. '25 | BM2: Sep. '25 | BN2: Dec. '25 | BP2: = year ending 31 March '26. | BQ2: Jun. '26 | BR2: Sep. '26 | BS2: Dec. '26 | BU2: = year ending 31 March '27.
A3: year end March ¥tn | I3: 1Q14 | J3: 2Q14 | K3: 3Q14 | L3: 4Q14 | M3: FY14 | N3: 1Q15 | O3: 2Q15 | P3: 3Q15 | Q3: 4Q15 | R3: FY15 | S3: 1Q16 | T3: 2Q16 | U3: 3Q16 | V3: 4Q16 | W3: FY16 | X3: 1Q17 | Y3: 2Q17 | Z3: 3Q17 | AA3: 4Q17 | AB3: FY17 | AC3: 1Q18 | AD3: 2Q18 | AE3: 3Q18 | AF3: 4Q18 | AG3: FY18 | AH3: 1Q19 | AI3: 2Q19 | AJ3: 3Q19 | AK3: 4Q19 | AL3: FY19 | AM3: 1Q20 | AN3: 2Q20 | AO3: 3Q20 | AP3: 4Q20 | AQ3: FY20 | AR3: 1Q21 | AS3: 2Q21 | AT3: 3Q21 | AU3: 4Q21 | AV3: FY21 | AW3: 1Q22 | AX3: 2Q22 | AY3: 3Q22 | AZ3: 4Q22 | BA3: FY22 | BB3: 1Q23 | BC3: 2Q23 | BD3: 3Q23 | BE3: 4Q23 | BF3: FY23 | BG3: 1Q24 | BH3: 2Q24 | BI3: 3Q24 | BJ3: 4Q24 | BK3: FY24 | BL3: 1Q25 | BM3: 2Q25 | BN3: 3Q25 | BO3: 4Q25 | BP3: FY25 | BQ3: 1Q26 | BR3: 2Q26 | BS3: 3Q26 | BT3: 4Q26 | BU3: FY26 | BW3: Annual | BY3: FY19 | BZ3: FY20 | CA3: FY21 | CB3: FY22 | CC3: FY23 | CD3: FY24 | CE3: FY25 | CF3: FY26 | CG3: FY27 | CH3: FY28 | CI3: FY29 | CJ3: FY30
A5: Net asset value & LTV ¥tn = as reported by SBG.
A7: ¥tn
AE8: = SBG started reporting NAV and LTV after IPO'ing SoftBank Corp. in December '18.
A9: SoftBank Group equity value of holdings = as reported by SBG in quarterly Data sheets. | AK9: = up to end FY19 Alibaba equity holding reported gross of margin loans, prepaid forward contract liabilities etc etc.
A10: Alibaba | AE10: 12.11 | AF10: 13.06 | AG10: =AF10 -> 13.06 | AH10: 11.28 | AI10: =13.35-0.95 -> 12.4 | AJ10: =16.08-1.23 -> 14.85 | AK10: =14.68-1.72-1.49 -> 11.47 | AL10: =AK10 -> 11.47 | AM10: 12.63 | AN10: 18.55 | AO10: 13.13 | AP10: 12.75 | AQ10: =AP10 -> 12.75 | AR10: 12.38 | AS10: 7.27 | AT10: 5.97 | AU10: 5.23 | AV10: =AU10 -> 5.23 | AW10: 4.48 | AX10: 3.03 | AY10: 2.05 | AZ10: 0.71 | BA10: =AZ10 -> 0.71 | BB10: 0.02 | BC10: 0.01 | BD10: 0.01 | BE10: 0.01 | BF10: =BE10 -> 0.01 | BG10: 0.01 | BH10: 0.01 | BI10: 0.01 | BJ10: 0.01 | BK10: =BJ10 -> 0.01 | BL10: 0.01 | BM10: 0 | BN10: 0 | BO10: =BO54*BO$79/1000 -> 0 | BP10: =BO10 -> 0 | BQ10: =BQ54*BQ$79/1000 -> 0 | BR10: =BR54*BR$79/1000 -> 0 | BS10: =BS54*BS$79/1000 -> 0 | BT10: =BT54*BT$79/1000 -> 0 | BU10: =BT10 -> 0
A11: SoftBank Corp. = includes Yahoo Japan up to 4Q18. | AE11: =4.33+0.59 -> 4.92 | AF11: =4.46+0.62 -> 5.08 | AG11: =AF11 -> 5.08 | AH11: 4.7 | AI11: 4.79 | AJ11: 4.79 | AK11: 4.48 | AL11: =AK11 -> 4.48 | AM11: 3.55 | AN11: 1.76 | AO11: 1.98 | AP11: 2.26 | AQ11: =AP11 -> 2.26 | AR11: 2.28 | AS11: 2.4 | AT11: 2.29 | AU11: 2.24 | AV11: =AU11 -> 2.24 | AW11: 2.39 | AX11: 2.21 | AY11: 2.29 | AZ11: 2.37 | BA11: =AZ11 -> 2.37 | BB11: 2.39 | BC11: 2.67 | BD11: 2.8 | BE11: 3.16 | BF11: =BE11 -> 3.16 | BG11: 3.2 | BH11: 3.06 | BI11: 3.31 | BJ11: 3.19 | BK11: =BJ11 -> 3.19 | BL11: 3.47 | BM11: 3.37 | BN11: 2.92 | BO11: =BO55*BO$79/1000 -> 2.8543357 | BP11: =BO11 -> 2.8543357 | BQ11: =BQ55*BQ$79/1000 -> 2.8543357 | BR11: =BR55*BR$79/1000 -> 2.8543357 | BS11: =BS55*BS$79/1000 -> 2.8543357 | BT11: =BT55*BT$79/1000 -> 2.8543357 | BU11: =BT11 -> 2.8543357
A12: SVF1 | AM12: 2.74 | AN12: 2.85 | AO12: 4.23 | AP12: 6.2 | AQ12: =AP12 -> 6.2 | AR12: 6.19 | AS12: 5.12 | AT12: 5.19 | AU12: 3.99 | AV12: =AU12 -> 3.99 | AW12: 3.41 | AX12: 3.27 | AY12: 2.79 | AZ12: 2.8 | BA12: =AZ12 -> 2.8 | BB12: 3.03 | BC12: 3.29 | BD12: 3.25 | BE12: 3.44 | BF12: =BE12 -> 3.44 | BG12: 3.88 | BH12: 3.65 | BI12: 3.95 | BJ12: 3.68 | BK12: =BJ12 -> 3.68 | BL12: 3.8 | BM12: 3.96 | BN12: 3.79 | BO12: =BO56*BO$79/1000 -> 3.590565 | BP12: =BO12 -> 3.590565 | BQ12: =BQ56*BQ$79/1000 -> 3.3283705 | BR12: =BR56*BR$79/1000 -> 3.072113 | BS12: =BS56*BS$79/1000 -> 2.8202175 | BT12: =BT56*BT$79/1000 -> 2.5688225 | BU12: =BT12 -> 2.5688225
A13: OpenAI Global LLC | BG13: =BG57*BG$79/1000 -> 0 | BH13: =BH57*BH$79/1000 -> 0.071365 | BI13: =BI57*BI$79/1000 -> 0.07909 | BJ13: =BJ57*BJ$79/1000 -> 0.49236841 | BK13: =BJ13 -> 0.49236841 | BL13: =BL57*BL$79/1000 -> 1.5629334 | BM13: =BM57*BM$79/1000 -> 3.677336 | BN13: =BN57*BN$79/1000 -> 8.516864 | BO13: =BO57*BO$79/1000 -> 8.43744 | BP13: =BO13 -> 8.43744 | BQ13: =BQ57*BQ$79/1000 -> 13.222983 | BR13: =BR57*BR$79/1000 -> 15.036535 | BS13: =BS57*BS$79/1000 -> 16.840508 | BT13: =BT57*BT$79/1000 -> 16.796737 | BU13: =BT13 -> 16.796737
A14: SVF2 excl. OpenAI | BG14: =BG58*BG$79/1000 -> 4.34 | BH14: =BH58*BH$79/1000 -> 3.968635 | BI14: =BI58*BI$79/1000 -> 4.44091 | BJ14: =BJ58*BJ$79/1000 -> 4.2776316 | BK14: =BJ14 -> 4.2776316 | BL14: =BL58*BL$79/1000 -> 4.2970666 | BM14: =BM58*BM$79/1000 -> 4.582664 | BN14: =BN58*BN$79/1000 -> 4.653136 | BO14: =BO58*BO$79/1000 -> 4.496349 | BP14: =BO14 -> 4.496349 | BQ14: =BQ58*BQ$79/1000 -> 4.138225 | BR14: =BR58*BR$79/1000 -> 3.797323 | BS14: =BS58*BS$79/1000 -> 3.4804485 | BT14: =BT58*BT$79/1000 -> 3.0815125 | BU14: =BT14 -> 3.0815125
A15: SVF2 | AM15: 0.22 | AN15: 0.82 | AO15: 0.96 | AP15: 1.31 | AQ15: =AP15 -> 1.31 | AR15: 2.85 | AS15: 4.04 | AT15: 4.83 | AU15: 4.96 | AV15: =AU15 -> 4.96 | AW15: 4.5 | AX15: 4.19 | AY15: 3.71 | AZ15: 3.52 | BA15: =AZ15 -> 3.52 | BB15: 4.04 | BC15: 3.89 | BD15: 4.14 | BE15: 4.42 | BF15: =BE15 -> 4.42 | BG15: 4.34 | BH15: 4.04 | BI15: 4.52 | BJ15: 4.77 | BK15: =BJ15 -> 4.77 | BL15: 5.86 | BM15: 8.26 | BN15: 13.17 | BO15: =BO59*BO$79/1000 -> 12.933789 | BP15: =BO15 -> 12.933789 | BQ15: =BQ59*BQ$79/1000 -> 17.361208 | BR15: =BR59*BR$79/1000 -> 18.833858 | BS15: =BS59*BS$79/1000 -> 20.320956 | BT15: =BT59*BT$79/1000 -> 19.87825 | BU15: =BT15 -> 19.87825
A16: LatAm Funds | AM16: 0.15 | AN16: 0.22 | AO16: 0.32 | AP16: 0.44 | AQ16: =AP16 -> 0.44 | AR16: 0.77 | AS16: 0.85 | AT16: 0.94 | AU16: 1.13 | AV16: =AU16 -> 1.13 | AW16: 0.96 | AX16: 0.99 | AY16: 0.86 | AZ16: 0.79 | BA16: =AZ16 -> 0.79 | BB16: 0.91 | BC16: 0.94 | BD16: 0.91 | BE16: 0.97 | BF16: =BE16 -> 0.97 | BG16: 1.02 | BH16: 0.94 | BI16: 1.03 | BJ16: 0.95 | BK16: =BJ16 -> 0.95 | BL16: 0.99 | BM16: 1.04 | BN16: 1.04 | BO16: =BO60*BO$79/1000 -> 1.0504923 | BP16: =BO16 -> 1.0504923 | BQ16: =BQ60*BQ$79/1000 -> 1.0539711 | BR16: =BR60*BR$79/1000 -> 1.0535604 | BS16: =BS60*BS$79/1000 -> 1.0529838 | BT16: =BT60*BT$79/1000 -> 1.044721 | BU16: =BT16 -> 1.044721
A17: SBG's equity in Vision Funds | AE17: 2.7 | AF17: 3.15 | AG17: =AF17 -> 3.15 | AH17: 3.45 | AI17: 3.17 | AJ17: 3.15 | AK17: 2.61 | AL17: =AK17 -> 2.61 | AM17: =AM12+AM15+AM16 -> 3.11 | AN17: =AN12+AN15+AN16 -> 3.89 | AO17: =AO12+AO15+AO16 -> 5.51 | AP17: =AP12+AP15+AP16 -> 7.95 | AQ17: =AQ12+AQ15+AQ16 -> 7.95 | AR17: =AR12+AR15+AR16 -> 9.81 | AS17: =AS12+AS15+AS16 -> 10.01 | AT17: =AT12+AT15+AT16 -> 10.96 | ... BU17: =BU12+BU15+BU16 -> 23.491793
A18: T-Mobile US = Sprint US up to end 3Q19. | AE18: 2.69 | AF18: 2.82 | AG18: =AF18 -> 2.82 | AH18: 2.9 | AI18: 3.13 | AJ18: 3.23 | AK18: 3.17 | AL18: =AK18 -> 3.17 | AM18: 1.36 | AN18: 1.27 | AO18: 1.57 | AP18: 1.51 | AQ18: =AP18 -> 1.51 | AR18: 1.88 | AS18: 0.78 | AT18: 0.74 | AU18: 0.96 | AV18: =AU18 -> 0.96 | AW18: 1 | AX18: 1.15 | AY18: 1.15 | AZ18: 1.23 | BA18: =AZ18 -> 1.23 | BB18: 1.2 | BC18: 1.27 | BD18: 1.62 | BE18: 1.76 | BF18: =BE18 -> 1.76 | BG18: 2.42 | BH18: 2.51 | BI18: 2.98 | BJ18: 3.4 | BK18: =BJ18 -> 3.4 | BL18: 2.2 | BM18: 1.61 | BN18: 0.91 | BO18: =BO62*BO$79/1000 -> 0.53629858 | BP18: =BO18 -> 0.53629858 | BQ18: =BQ62*BQ$79/1000 -> 0 | BR18: =BR62*BR$79/1000 -> 0 | BS18: =BS62*BS$79/1000 -> 0 | BT18: =BT62*BT$79/1000 -> 0 | BU18: =BT18 -> 0
A19: Deutsche Telekom | AS19: 0.51 | AT19: 0.08 | AU19: 0.1 | AV19: =AU19 -> 0.1 | AW19: 0.17 | AX19: 0.13 | AY19: 0.16 | AZ19: 0.28 | BA19: =AZ19 -> 0.28 | BB19: 0.23 | BC19: 0.23 | BD19: 0.29 | BE19: 0.33 | BF19: =BE19 -> 0.33 | BG19: 0.37 | BH19: 0.37 | BI19: 0.38 | BJ19: 0.41 | BK19: =BJ19 -> 0.41 | BL19: 0.35 | BM19: 0.05 | BN19: 0 | BO19: =BO63*BO$79/1000 -> 0 | BP19: =BO19 -> 0 | BQ19: =BQ63*BQ$79/1000 -> 0 | BR19: =BR63*BR$79/1000 -> 0 | BS19: =BS63*BS$79/1000 -> 0 | BT19: =BT63*BT$79/1000 -> 0 | BU19: =BT19 -> 0
A20: Arm | AE20: 2.7 | AF20: 2.71 | AG20: =AF20 -> 2.71 | AH20: 2.62 | AI20: 2.68 | AJ20: 2.7 | AK20: 2.63 | AL20: =AK20 -> 2.63 | AM20: 2.65 | AN20: 2.6 | AO20: 2.55 | AP20: 2.72 | AQ20: =AP20 -> 2.72 | AR20: 2.72 | AS20: 2.75 | AT20: 2.83 | AU20: 2.71 | AV20: =AU20 -> 2.71 | AW20: 2.96 | AX20: 3.13 | AY20: 2.63 | AZ20: 2.87 | BA20: =AZ20 -> 2.87 | BB20: 3.66 | BC20: 4.33 | BD20: 6.93 | BE20: 14.36 | BF20: =BE20 -> 14.36 | BG20: 21.02 | BH20: 16.5 | BI20: 15.42 | BJ20: 12.9 | BK20: =BJ20 -> 12.9 | BL20: 19.83 | BM20: 18.18 | BN20: 12.69 | BO20: =BO64*BO$79/1000 -> 15.137569 | BP20: =BO20 -> 15.137569 | BQ20: =BQ64*BQ$79/1000 -> 15.09853 | BR20: =BR64*BR$79/1000 -> 14.67374 | BS20: =BS64*BS$79/1000 -> 14.250951 | BT20: =BT64*BT$79/1000 -> 14.213911 | BU20: =BT20 -> 14.213911
A21: Others | AE21: 0.27 | AF21: 0.47 | AG21: =AF21 -> 0.47 | AH21: 0.9 | AI21: 0.76 | AJ21: 1.14 | AK21: 0.88 | AL21: =AK21 -> 0.88 | AM21: =AM26 -> 1.54 | AN21: =AN26 -> 3.46 | AO21: =AO26 -> 3.35 | AP21: =AP26 -> 3.21 | AQ21: =AP21 -> 3.21 | AR21: =AR26 -> 3.04 | AS21: =AS26 -> 1.98 | AT21: =AT26 -> 1.8 | AU21: =AU26 -> 1.86 | AV21: =AU21 -> 1.86 | AW21: 1.79 | AX21: 1.59 | AY21: 1.29 | AZ21: 1.3 | BA21: =AZ21 -> 1.3 | BB21: 1.42 | BC21: 1.73 | BD21: 1.77 | BE21: 1.89 | BF21: =BE21 -> 1.89 | BG21: 2 | BH21: 2.06 | BI21: 2.07 | BJ21: 2.06 | BK21: =BJ21 -> 2.06 | BL21: 2.53 | BM21: 3.39 | BN21: 4.46 | BO21: =BO65*BO$79/1000 -> 4.7832652 | BP21: =BO21 -> 4.7832652 | BQ21: =BQ65*BQ$79/1000 -> 4.8482793 | BR21: =BR65*BR$79/1000 -> 5.7422558 | BS21: =BS65*BS$79/1000 -> 6.2544774 | BT21: =BT65*BT$79/1000 -> 6.3149714 | BU21: =BT21 -> 6.3149714
A22: SBG total value of equity holdings net of asset-backed finance | AE22: =SUM(AE10:AE11)+AE17+SUM(AE18:AE21) -> 25.39 | AF22: =SUM(AF10:AF11)+AF17+SUM(AF18:AF21) -> 27.29 | AG22: =SUM(AG10:AG11)+AG17+SUM(AG18:AG21) -> 27.29 | AH22: =SUM(AH10:AH11)+AH17+SUM(AH18:AH21) -> 25.85 | AI22: =SUM(AI10:AI11)+AI17+SUM(AI18:AI21) -> 26.93 | AJ22: =SUM(AJ10:AJ11)+AJ17+SUM(AJ18:AJ21) -> 29.86 | AK22: =SUM(AK10:AK11)+AK17+SUM(AK18:AK21) -> 25.24 | AL22: =SUM(AL10:AL11)+AL17+SUM(AL18:AL21) -> 25.24 | ... BU22: =SUM(BU10:BU11)+BU17+SUM(BU18:BU21) -> 46.875012
A24: SB Northstar | AM24: 0.35 | AN24: 2.25 | AO24: 2.11 | AP24: 1.66 | AQ24: =AP24 -> 1.66 | AR24: 1.47 | AS24: 0.73 | AT24: 0.76 | AU24: 0.58 | AV24: =AU24 -> 0.58
A25: Others | AM25: 1.19 | AN25: 1.21 | AO25: 1.24 | AP25: 1.55 | AQ25: =AP25 -> 1.55 | AR25: 1.57 | AS25: 1.25 | AT25: 1.04 | AU25: 1.28 | AV25: =AU25 -> 1.28
A26: Total others = pre-FY22 SB Northstar reported separately to Others. | AM26: =SUM(AM24:AM25) -> 1.54 | AN26: =SUM(AN24:AN25) -> 3.46 | AO26: =SUM(AO24:AO25) -> 3.35 | AP26: =SUM(AP24:AP25) -> 3.21 | AQ26: =SUM(AQ24:AQ25) -> 3.21 | AR26: =SUM(AR24:AR25) -> 3.04 | AS26: =SUM(AS24:AS25) -> 1.98 | AT26: =SUM(AT24:AT25) -> 1.8 | ... AV26: =SUM(AV24:AV25) -> 1.86
A28: Consolidated net interest-bearing debt | AE28: 11.14 | AF28: 12.06 | AG28: =AF28 -> 12.06 | AH28: 14.6 | AI28: 14.08 | AJ28: 15.7 | AK28: 11.03 | AL28: =AK28 -> 11.03 | AM28: 9.95 | AN28: 9.07 | AO28: 12.39 | AP28: 14.02 | AQ28: =AP28 -> 14.02 | AR28: 15.87 | AS28: 16.07 | AT28: 16.75 | AU28: 17.1 | AV28: =AU28 -> 17.1 | AW28: 17.92 | AX28: 14.13 | AY28: 13.48 | AZ28: 13.59 | BA28: =AZ28 -> 13.59 | BB28: 14.7 | BC28: 14.68 | BD28: 14.76 | BE28: 14.89 | BF28: =BE28 -> 14.89 | BG28: 15.62 | BH28: 15.43 | BI28: 14.63 | BJ28: 14.41 | BK28: =BJ28 -> 14.41 | BL28: 14.75 | BM28: 14.41 | BN28: 18.56
A29: Less: net interest-bearing debt at self-financing entities | AE29: 7.52 | AF29: 6.98 | AG29: =AF29 -> 6.98 | AH29: 8.39 | AI29: 8.56 | AJ29: 9.47 | AK29: 4.57 | AL29: =AK29 -> 4.57 | AM29: 4.3 | AN29: 2.54 | AO29: 4.74 | AP29: 5.46 | AQ29: =AP29 -> 5.46 | AR29: 5.36 | AS29: 5.15 | AT29: 5.26 | AU29: 4.97 | AV29: =AU29 -> 4.97 | AW29: 5.9 | AX29: 5.63 | AY29: 5.37 | AZ29: 5.38 | BA29: =AZ29 -> 5.38 | BB29: 5.76 | BC29: 4.7 | BD29: 4.74 | BE29: 4.52 | BF29: =BE29 -> 4.52 | BG29: 5.1 | BH29: 5.16 | BI29: 4.97 | BJ29: 4.89 | BK29: =BJ29 -> 4.89 | BL29: 5.36 | BM29: 5.31 | BN29: 5.51
A30: Other adjustments = 50% equity component of hybrid bonds plus asset-backed finance e.g., margin loans, collars etc. | AF30: 0.64 | AG30: =AF30 -> 0.64 | AH30: 1.31 | AI30: 0.99 | AJ30: 1.43 | AK30: 2.88 | AL30: =AK30 -> 2.88 | AM30: 3.48 | AN30: 2.89 | AO30: 3.62 | AP30: 4.85 | AQ30: =AP30 -> 4.85 | AR30: 5.4 | AS30: 6.11 | AT30: 6.17 | AU30: 7.41 | AV30: =AU30 -> 7.41 | AW30: 8.87 | AX30: 5.54 | AY30: 5.03 | AZ30: 6.46 | BA30: =AZ30 -> 6.46 | BB30: 7.59 | BC30: 8.03 | BD30: 7.54 | BE30: 7.81 | BF30: =BE30 -> 7.81 | BG30: 7.53 | BH30: 6.14 | BI30: 5.33 | BJ30: 3.85 | BK30: =BJ30 -> 3.85 | BL30: 2.75 | BM30: 2.54 | BN30: 5.01
A31: Less: SBG TopCo standalone net interest-bearing debt | AE31: =AE28-AE29-AE30 -> 3.62 | AF31: =AF28-AF29-AF30 -> 4.44 | AG31: =AG28-AG29-AG30 -> 4.44 | AH31: =AH28-AH29-AH30 -> 4.9 | AI31: =AI28-AI29-AI30 -> 4.53 | AJ31: =AJ28-AJ29-AJ30 -> 4.8 | AK31: =AK28-AK29-AK30 -> 3.58 | AL31: =AL28-AL29-AL30 -> 3.58 | ... BN31: =BN28-BN29-BN30 -> 8.04 | BO31: =BO71*BO$79/1000 -> 7.92935 | BP31: =BO31 -> 7.92935 | BQ31: =BQ71*BQ$79/1000 -> 8.6429518 | BR31: =BR71*BR$79/1000 -> 10.356479 | BS31: =BS71*BS$79/1000 -> 12.014067 | BT31: =BT71*BT$79/1000 -> 11.843924 | BU31: =BT31 -> 11.843924
A33: Net asset value = per SBG reporting. | AE33: =AE22-AE31 -> 21.77 | AF33: =AF22-AF31 -> 22.85 | AG33: =AG22-AG31 -> 22.85 | AH33: =AH22-AH31 -> 20.95 | AI33: =AI22-AI31 -> 22.4 | AJ33: =AJ22-AJ31 -> 25.06 | AK33: =AK22-AK31 -> 21.66 | AL33: =AL22-AL31 -> 21.66 | ... BU33: =BU22-BU31 -> 35.031088
A34: of which Telcos assets | AE34: =AE11+SUM(AE18:AE19) -> 7.61 | AF34: =AF11+SUM(AF18:AF19) -> 7.9 | AG34: =AG11+SUM(AG18:AG19) -> 7.9 | AH34: =AH11+SUM(AH18:AH19) -> 7.6 | AI34: =AI11+SUM(AI18:AI19) -> 7.92 | AJ34: =AJ11+SUM(AJ18:AJ19) -> 8.02 | AK34: =AK11+SUM(AK18:AK19) -> 7.65 | AL34: =AL11+SUM(AL18:AL19) -> 7.65 | ... BU34: =BU11+SUM(BU18:BU19) -> 2.8543357
A35: Telcos as % of NAV | AE35: =AE34/AE33 -> 0.34956362 | AF35: =AF34/AF33 -> 0.34573304 | AG35: =AG34/AG33 -> 0.34573304 | AH35: =AH34/AH33 -> 0.3627685 | AI35: =AI34/AI33 -> 0.35357143 | AJ35: =AJ34/AJ33 -> 0.32003192 | AK35: =AK34/AK33 -> 0.3531856 | AL35: =AL34/AL33 -> 0.3531856 | ... BU35: =BU34/BU33 -> 0.081480074
A37: Loan-to-value = only uses net debt effectively held at TopCo i.e., standalone. | AE37: =AE31/AE22 -> 0.14257582 | AF37: =AF31/AF22 -> 0.16269696 | AG37: =AG31/AG22 -> 0.16269696 | AH37: =AH31/AH22 -> 0.18955513 | AI37: =AI31/AI22 -> 0.16821389 | AJ37: =AJ31/AJ22 -> 0.16075017 | AK37: =AK31/AK22 -> 0.14183835 | AL37: =AL31/AL22 -> 0.14183835 | ... BU37: =BU31/BU22 -> 0.25267031 | BY37: =INDEX($AE37:$BK37, MATCH(BY$3, $AE$3:$BK$3, 0)) -> 0.14183835 | BZ37: =INDEX($AE37:$BK37, MATCH(BZ$3, $AE$3:$BK$3, 0)) -> 0.12203947 | CA37: =INDEX($AE37:$BK37, MATCH(CA$3, $AE$3:$BK$3, 0)) -> 0.20362381 | CB37: =INDEX($AE37:$BK37, MATCH(CB$3, $AE$3:$BK$3, 0)) -> 0.11027095 | CC37: =INDEX($AE37:$BK37, MATCH(CC$3, $AE$3:$BK$3, 0)) -> 0.08437706 | CD37: =INDEX($AE37:$BK37, MATCH(CD$3, $AE$3:$BK$3, 0)) -> 0.18074594
A38: = share count reflects Arete est. SoftBank Group share repurchase model.
A39: SoftBank Group share count (millions) | BB39: =BC39 -> 1465.9725 | BC39: =BD39 -> 1465.9725 | BD39: =BE39 -> 1465.9725 | BE39: =BF39 -> 1465.9725 | BF39: =BG39 -> 1465.9725 | BG39: ='TopCo Net debt waterfall'!AR153 -> 1465.9725 | BH39: ='TopCo Net debt waterfall'!AS153 -> 1447.0631 | BI39: ='TopCo Net debt waterfall'!AT153 -> 1441.1233 | BJ39: ='TopCo Net debt waterfall'!AU153 -> 1437.5963 | BK39: =BJ39 -> 1437.5963 | BL39: ='TopCo Net debt waterfall'!AW153 -> 1424.4852 | BM39: ='TopCo Net debt waterfall'!AX153 -> 1424.4852 | BN39: ='TopCo Net debt waterfall'!AY153 -> 1427.962 | BO39: ='TopCo Net debt waterfall'!AZ153 -> 1427.962 | BP39: =BO39 -> 1427.962 | BQ39: =BP39 -> 1427.962 | BR39: =BQ39 -> 1427.962 | BS39: =BR39 -> 1427.962 | BT39: =BS39 -> 1427.962 | BU39: =BT39 -> 1427.962
A41: NAV per share ¥ | BB41: =MROUND(1000000*BB33/BB39, 10) -> 10610 | BC41: =MROUND(1000000*BC33/BC39, 10) -> 11190 | BD41: =MROUND(1000000*BD33/BD39, 10) -> 13120 | BE41: =MROUND(1000000*BE33/BE39, 10) -> 18950 | BF41: =MROUND(1000000*BF33/BF39, 10) -> 18950 | BG41: =MROUND(1000000*BG33/BG39, 10) -> 24060 | BH41: =MROUND(1000000*BH33/BH39, 10) -> 20050 | BI41: =MROUND(1000000*BI33/BI39, 10) -> 20360 | ... BU41: =MROUND(1000000*BU33/BU39, 10) -> 24530
A42: % discount | BB42: =1-FP!$D$5/'Valuation & SBG NAV'!BB41 -> -0.52544769 | BC42: =1-FP!$D$5/'Valuation & SBG NAV'!BC41 -> -0.4463807 | BD42: =1-FP!$D$5/'Valuation & SBG NAV'!BD41 -> -0.2336128 | BE42: =1-FP!$D$5/'Valuation & SBG NAV'!BE41 -> 0.14591029 | BF42: =1-FP!$D$5/'Valuation & SBG NAV'!BF41 -> 0.14591029 | BG42: =1-FP!$D$5/'Valuation & SBG NAV'!BG41 -> 0.32730673 | BH42: =1-FP!$D$5/'Valuation & SBG NAV'!BH41 -> 0.19276808 | BI42: =1-FP!$D$5/'Valuation & SBG NAV'!BI41 -> 0.20505894 | ... BU42: =1-FP!$D$5/'Valuation & SBG NAV'!BU41 -> 0.34019568
A44: SoftBank Group share count (millions) = 4-for-1 share split closed 31 Dec. '25. | BG44: =4*BG39 -> 5863.8899 | BH44: =4*BH39 -> 5788.2524 | BI44: =4*BI39 -> 5764.4932 | BJ44: =4*BJ39 -> 5750.3852 | BK44: =4*BK39 -> 5750.3852 | BL44: =4*BL39 -> 5697.9406 | BM44: =4*BM39 -> 5697.9406 | BN44: =4*BN39 -> 5711.8481 | ... BP44: =4*BP39 -> 5711.8481 | BQ44: =BP44 -> 5711.8481 | BR44: =BQ44 -> 5711.8481 | BS44: =BR44 -> 5711.8481 | BT44: =BS44 -> 5711.8481 | BU44: =BT44 -> 5711.8481
A46: NAV per share ¥ | BG46: =MROUND(1000000*BG33/BG44, 10) -> 6010 | BH46: =MROUND(1000000*BH33/BH44, 10) -> 5010 | BI46: =MROUND(1000000*BI33/BI44, 10) -> 5090 | BJ46: =MROUND(1000000*BJ33/BJ44, 10) -> 4470 | BK46: =MROUND(1000000*BK33/BK44, 10) -> 4470 | BL46: =MROUND(1000000*BL33/BL44, 10) -> 5690 | BM46: =MROUND(1000000*BM33/BM44, 10) -> 5840 | BN46: =MROUND(1000000*BN33/BN44, 10) -> 5420 | ... BU46: =MROUND(1000000*BU33/BU44, 10) -> 6130
A47: % discount | BG47: =1-FP!$D$9/'Valuation & SBG NAV'!BG46 -> 0.32678869 | BH47: =1-FP!$D$9/'Valuation & SBG NAV'!BH46 -> 0.19241517 | BI47: =1-FP!$D$9/'Valuation & SBG NAV'!BI46 -> 0.20510806 | BJ47: =1-FP!$D$9/'Valuation & SBG NAV'!BJ46 -> 0.094854586 | BK47: =1-FP!$D$9/'Valuation & SBG NAV'!BK46 -> 0.094854586 | BL47: =1-FP!$D$9/'Valuation & SBG NAV'!BL46 -> 0.28892794 | BM47: =1-FP!$D$9/'Valuation & SBG NAV'!BM46 -> 0.30719178 | BN47: =1-FP!$D$9/'Valuation & SBG NAV'!BN46 -> 0.25350554 | ... BU47: =1-FP!$D$9/'Valuation & SBG NAV'!BU46 -> 0.33996737
A49: Net asset value & LTV $bn = as reported by SBG.
A51: $bn
A53: SoftBank Group equity value of holdings = as reported by SBG in quarterly Data sheets. | BJ53: = DT formula adjustment for $1bn delta vs. SBG reporting built up in 2Q and 3Q24 -> seems like DT share price now above "short call strike price" of collar.
A54: Alibaba | AE54: =1000*AE10/AE$79 -> 109.0991 | AF54: =1000*AF10/AF$79 -> 117.66826 | AG54: =AF54 -> 117.66826 | AH54: =1000*AH10/AH$79 -> 104.64793 | AI54: =1000*AI10/AI$79 -> 114.89993 | AJ54: =1000*AJ10/AJ$79 -> 135.54217 | AK54: =1000*AK10/AK$79 -> 105.39373 | AL54: =AK54 -> 105.39373 | AM54: =1000*AM10/AM$79 -> 117.22666 | AN54: =1000*AN10/AN$79 -> 175.33081 | AO54: =1000*AO10/AO$79 -> 126.8599 | AP54: =1000*AP10/AP$79 -> 115.16575 | AQ54: =AP54 -> 115.16575 | AR54: =1000*AR10/AR$79 -> 111.95515 | AS54: =1000*AS10/AS$79 -> 64.957112 | AT54: =1000*AT10/AT$79 -> 51.904017 | AU54: =1000*AU10/AU$79 -> 42.732249 | AV54: =AU54 -> 42.732249 | AW54: =1000*AW10/AW$79 -> 32.77729 | AX54: =1000*AX10/AX$79 -> 20.923969 | AY54: =1000*AY10/AY$79 -> 15.44838 | AZ54: =1000*AZ10/AZ$79 -> 5.3171572 | BA54: =AZ54 -> 5.3171572 | BB54: =1000*BB10/BB$79 -> 0.13794055 | BC54: =1000*BC10/BC$79 -> 0.066853857 | BD54: =1000*BD10/BD$79 -> 0.070506945 | BE54: =1000*BE10/BE$79 -> 0.066045836 | BF54: =BE54 -> 0.066045836 | BG54: =1000*BG10/BG$79 -> 0.062084808 | BH54: =1000*BH10/BH$79 -> 0.070062355 | BI54: =1000*BI10/BI$79 -> 0.063219117 | BJ54: =1000*BJ10/BJ$79 -> 0.066880685 | BK54: =BJ54 -> 0.066880685 | BL54: =1000*BL10/BL$79 -> 0.069056004 | BM54: =1000*BM10/BM$79 -> 0 | BN54: =1000*BN10/BN$79 -> 0 | BO54: =BO149-BO96 -> 0 | BP54: =BO54 -> 0 | BQ54: =BQ149-BQ96 -> 0 | BR54: =BR149-BR96 -> 0 | BS54: =BS149-BS96 -> 0 | BT54: =BT149-BT96 -> 0 | BU54: =BT54 -> 0
A55: SoftBank Corp. | AE55: =1000*AE11/AE$79 -> 44.324324 | AF55: =1000*AF11/AF$79 -> 45.769889 | AG55: =AF55 -> 45.769889 | AH55: =1000*AH11/AH$79 -> 43.603303 | AI55: =1000*AI11/AI$79 -> 44.384729 | AJ55: =1000*AJ11/AJ$79 -> 43.720336 | AK55: =1000*AK11/AK$79 -> 41.16512 | AL55: =AK55 -> 41.16512 | AM55: =1000*AM11/AM$79 -> 32.949694 | AN55: =1000*AN11/AN$79 -> 16.635161 | AO55: =1000*AO11/AO$79 -> 19.130435 | AP55: =1000*AP11/AP$79 -> 20.413693 | AQ55: =AP55 -> 20.413693 | AR55: =1000*AR11/AR$79 -> 20.618557 | AS55: =1000*AS11/AS$79 -> 21.443888 | AT55: =1000*AT11/AT$79 -> 19.909581 | AU55: =1000*AU11/AU$79 -> 18.302149 | AV55: =AU55 -> 18.302149 | AW55: =1000*AW11/AW$79 -> 17.486099 | AX55: =1000*AX11/AX$79 -> 15.261377 | AY55: =1000*AY11/AY$79 -> 17.256971 | AZ55: =1000*AZ11/AZ$79 -> 17.74882 | BA55: =AZ55 -> 17.74882 | BB55: =1000*BB11/BB$79 -> 16.483895 | BC55: =1000*BC11/BC$79 -> 17.84998 | BD55: =1000*BD11/BD$79 -> 19.741945 | BE55: =1000*BE11/BE$79 -> 20.870484 | BF55: =BE55 -> 20.870484 | BG55: =1000*BG11/BG$79 -> 19.867139 | BH55: =1000*BH11/BH$79 -> 21.439081 | BI55: =1000*BI11/BI$79 -> 20.925528 | BJ55: =1000*BJ11/BJ$79 -> 21.334938 | BK55: =BJ55 -> 21.334938 | BL55: =1000*BL11/BL$79 -> 23.962434 | BM55: =1000*BM11/BM$79 -> 22.63568 | BN55: =1000*BN11/BN$79 -> 18.650996 | BO55: =BO150-BO97 -> 18.403196 | BP55: =BO55 -> 18.403196 | BQ55: =BQ150-BQ97 -> 18.45078 | BR55: =BR150-BR97 -> 18.498611 | BS55: =BS150-BS97 -> 18.54669 | BT55: =BT150-BT97 -> 18.595021 | BU55: =BT55 -> 18.595021
A56: SVF1 | AM56: =1000*AM12/AM$79 -> 25.431595 | AN56: =1000*AN12/AN$79 -> 26.937618 | AO56: =1000*AO12/AO$79 -> 40.869565 | AP56: =1000*AP12/AP$79 -> 56.002168 | AQ56: =AP56 -> 56.002168 | AR56: =1000*AR12/AR$79 -> 55.977573 | AS56: =1000*AS12/AS$79 -> 45.746962 | AT56: =1000*AT12/AT$79 -> 45.122587 | AU56: =1000*AU12/AU$79 -> 32.600703 | AV56: =AU56 -> 32.600703 | AW56: =1000*AW12/AW$79 -> 24.948785 | AX56: =1000*AX12/AX$79 -> 22.581313 | AY56: =1000*AY12/AY$79 -> 21.024868 | AZ56: =1000*AZ12/AZ$79 -> 20.969071 | BA56: =AZ56 -> 20.969071 | BB56: =1000*BB12/BB$79 -> 20.897993 | BC56: =1000*BC12/BC$79 -> 21.994919 | BD56: =1000*BD12/BD$79 -> 22.914757 | BE56: =1000*BE12/BE$79 -> 22.719768 | BF56: =BE56 -> 22.719768 | BG56: =1000*BG12/BG$79 -> 24.088905 | BH56: =1000*BH12/BH$79 -> 25.57276 | BI56: =1000*BI12/BI$79 -> 24.971551 | BJ56: =1000*BJ12/BJ$79 -> 24.612092 | BK56: =BJ56 -> 24.612092 | BL56: =1000*BL12/BL$79 -> 26.241282 | BM56: =1000*BM12/BM$79 -> 26.598603 | BN56: =1000*BN12/BN$79 -> 24.207971 | BO56: =BO151-BO98 -> 23.15 | BP56: =BO56 -> 23.15 | BQ56: =BQ151-BQ98 -> 21.515 | BR56: =BR151-BR98 -> 19.91 | BS56: =BS151-BS98 -> 18.325 | BT56: =BT151-BT98 -> 16.735 | BU56: =BT56 -> 16.735
A57: OpenAI Global LLC | BG57: =BG152-BG99 -> 0 | BH57: =BH152-BH99 -> 0.5 | BI57: =BI152-BI99 -> 0.5 | BJ57: =BJ152-BJ99 -> 3.2929936 | BK57: =BJ57 -> 3.2929936 | BL57: =BL152-BL99 -> 10.792994 | BM57: =BM152-BM99 -> 24.7 | BN57: =BN152-BN99 -> 54.4 | BO57: =BO152-BO99 -> 54.4 | BP57: =BO57 -> 54.4 | BQ57: =BQ152-BQ99 -> 85.475 | BR57: =BR152-BR99 -> 97.45 | BS57: =BS152-BS99 -> 109.425 | BT57: =BT152-BT99 -> 109.425 | BU57: =BT57 -> 109.425
A58: SVF2 excl. OpenAI | BG58: =BG153-BG100 -> 26.944807 | BH58: =BH153-BH100 -> 27.805192 | BI58: =BI153-BI100 -> 28.075041 | BJ58: =BJ153-BJ100 -> 28.609093 | BK58: =BJ58 -> 28.609093 | BL58: =BL153-BL100 -> 29.673825 | BM58: =BM153-BM100 -> 30.780924 | BN58: =BN153-BN100 -> 29.721104 | BO58: =BO153-BO100 -> 28.99 | BP58: =BO58 -> 28.99 | BQ58: =BQ153-BQ100 -> 26.75 | BR58: =BR153-BR100 -> 24.61 | BS58: =BS153-BS100 -> 22.615 | BT58: =BT153-BT100 -> 20.075 | BU58: =BT58 -> 20.075
A59: SVF2 | AM59: =1000*AM15/AM$79 -> 2.0419528 | AN59: =1000*AN15/AN$79 -> 7.7504726 | AO59: =1000*AO15/AO$79 -> 9.2753623 | AP59: =1000*AP15/AP$79 -> 11.832716 | AQ59: =AP59 -> 11.832716 | AR59: =1000*AR15/AR$79 -> 25.773196 | AS59: =1000*AS15/AS$79 -> 36.097212 | AT59: =1000*AT15/AT$79 -> 41.992697 | AU59: =1000*AU15/AU$79 -> 40.526187 | AV59: =AU59 -> 40.526187 | AW59: =1000*AW15/AW$79 -> 32.923617 | AX59: =1000*AX15/AX$79 -> 28.934466 | AY59: =1000*AY15/AY$79 -> 27.9578 | AZ59: =1000*AZ15/AZ$79 -> 26.361117 | BA59: =AZ59 -> 26.361117 | BB59: =1000*BB15/BB$79 -> 27.863991 | BC59: =1000*BC15/BC$79 -> 26.006151 | BD59: =1000*BD15/BD$79 -> 29.189875 | BE59: =1000*BE15/BE$79 -> 29.192259 | BF59: =BE59 -> 29.192259 | BG59: =1000*BG15/BG$79 -> 26.944807 | BH59: =1000*BH15/BH$79 -> 28.305192 | BI59: =1000*BI15/BI$79 -> 28.575041 | BJ59: =1000*BJ15/BJ$79 -> 31.902087 | BK59: =BJ59 -> 31.902087 | BL59: =1000*BL15/BL$79 -> 40.466819 | BM59: =1000*BM15/BM$79 -> 55.480924 | BN59: =1000*BN15/BN$79 -> 84.121104 | BO59: =BO154-BO101 -> 83.39 | BP59: =BO59 -> 83.39 | BQ59: =BQ154-BQ101 -> 112.225 | BR59: =BR154-BR101 -> 122.06 | BS59: =BS154-BS101 -> 132.04 | BT59: =BT154-BT101 -> 129.5 | BU59: =BT59 -> 129.5
A60: LatAm Funds | AM60: =1000*AM16/AM$79 -> 1.3922406 | AN60: =1000*AN16/AN$79 -> 2.0793951 | AO60: =1000*AO16/AO$79 -> 3.0917874 | AP60: =1000*AP16/AP$79 -> 3.9743474 | AQ60: =AP60 -> 3.9743474 | AR60: =1000*AR16/AR$79 -> 6.9632845 | AS60: =1000*AS16/AS$79 -> 7.5947105 | AT60: =1000*AT16/AT$79 -> 8.1724917 | AU60: =1000*AU16/AU$79 -> 9.2327805 | AV60: =AU60 -> 9.2327805 | AW60: =1000*AW16/AW$79 -> 7.023705 | AX60: =1000*AX16/AX$79 -> 6.8365444 | AY60: =1000*AY16/AY$79 -> 6.4807837 | AZ60: =1000*AZ16/AZ$79 -> 5.9162735 | BA60: =AZ60 -> 5.9162735 | BB60: =1000*BB16/BB$79 -> 6.2762949 | BC60: =1000*BC16/BC$79 -> 6.2842626 | BD60: =1000*BD16/BD$79 -> 6.416132 | BE60: =1000*BE16/BE$79 -> 6.4064461 | BF60: =BE60 -> 6.4064461 | BG60: =1000*BG16/BG$79 -> 6.3326504 | BH60: =1000*BH16/BH$79 -> 6.5858614 | BI60: =1000*BI16/BI$79 -> 6.5115691 | BJ60: =1000*BJ16/BJ$79 -> 6.3536651 | BK60: =BJ60 -> 6.3536651 | BL60: =1000*BL16/BL$79 -> 6.8365444 | BM60: =1000*BM16/BM$79 -> 6.9854917 | BN60: =1000*BN16/BN$79 -> 6.6428206 | BO60: =BO155-BO102 -> 6.773 | BP60: =BO60 -> 6.773 | BQ60: =BQ155-BQ102 -> 6.813 | BR60: =BR155-BR102 -> 6.828 | BS60: =BS155-BS102 -> 6.842 | BT60: =BT155-BT102 -> 6.806 | BU60: =BT60 -> 6.806
A61: SBG's equity in Vision Funds | AE61: =1000*AE17/AE$79 -> 24.324324 | AF61: =1000*AF17/AF$79 -> 28.380935 | AG61: =AF61 -> 28.380935 | AH61: =1000*AH17/AH$79 -> 32.00668 | AI61: =1000*AI17/AI$79 -> 29.37361 | AJ61: =1000*AJ17/AJ$79 -> 28.751369 | AK61: =1000*AK17/AK$79 -> 23.982358 | AL61: =AK61 -> 23.982358 | AM61: =AM56+AM59+AM60 -> 28.865788 | AN61: =AN56+AN59+AN60 -> 36.767486 | AO61: =AO56+AO59+AO60 -> 53.236715 | AP61: =AP56+AP59+AP60 -> 71.809231 | AQ61: =AQ56+AQ59+AQ60 -> 71.809231 | AR61: =AR56+AR59+AR60 -> 88.714053 | AS61: =AS56+AS59+AS60 -> 89.438885 | AT61: =AT56+AT59+AT60 -> 95.287776 | ... BN61: =BN56+BN59+BN60 -> 114.9719 | BO61: =BO156-BO103 -> 113.313 | BP61: =BO61 -> 113.313 | BQ61: =BQ156-BQ103 -> 140.553 | BR61: =BR156-BR103 -> 148.798 | BS61: =BS156-BS103 -> 157.207 | BT61: =BT156-BT103 -> 153.041 | BU61: =BT61 -> 153.041
A62: T-Mobile US | AE62: =1000*AE18/AE$79 -> 24.234234 | AF62: =1000*AF18/AF$79 -> 25.407694 | AG62: =AF62 -> 25.407694 | AH62: =1000*AH18/AH$79 -> 26.904166 | AI62: =1000*AI18/AI$79 -> 29.002965 | AJ62: =1000*AJ18/AJ$79 -> 29.481563 | AK62: =1000*AK18/AK$79 -> 29.127998 | AL62: =AK62 -> 29.127998 | AM62: =1000*AM18/AM$79 -> 12.622981 | AN62: =1000*AN18/AN$79 -> 12.003781 | AO62: =1000*AO18/AO$79 -> 15.169082 | AP62: =1000*AP18/AP$79 -> 13.639238 | AQ62: =AP62 -> 13.639238 | AR62: =1000*AR18/AR$79 -> 17.001266 | AS62: =1000*AS18/AS$79 -> 6.9692638 | AT62: =1000*AT18/AT$79 -> 6.4336637 | AU62: =1000*AU18/AU$79 -> 7.8437781 | AV62: =AU62 -> 7.8437781 | AW62: =1000*AW18/AW$79 -> 7.3163594 | AX62: =1000*AX18/AX$79 -> 7.9414405 | AY62: =1000*AY18/AY$79 -> 8.6661643 | AZ62: =1000*AZ18/AZ$79 -> 9.2114132 | BA62: =AZ62 -> 9.2114132 | BB62: =1000*BB18/BB$79 -> 8.2764329 | BC62: =1000*BC18/BC$79 -> 8.4904399 | BD62: =1000*BD18/BD$79 -> 11.422125 | BE62: =1000*BE18/BE$79 -> 11.624067 | BF62: =BE62 -> 11.624067 | BG62: =1000*BG18/BG$79 -> 15.024523 | BH62: =1000*BH18/BH$79 -> 17.585651 | BI62: =1000*BI18/BI$79 -> 18.839297 | BJ62: =1000*BJ18/BJ$79 -> 22.739433 | BK62: =BJ62 -> 22.739433 | BL62: =1000*BL18/BL$79 -> 15.192321 | BM62: =1000*BM18/BM$79 -> 10.814078 | BN62: =1000*BN18/BN$79 -> 5.8124681 | BO62: =BO157-BO104 -> 3.45776 | BP62: =BO62 -> 3.45776
A63: Deutsche Telekom | AS63: =1000*AS19/AS$79 -> 4.5568263 | AT63: =1000*AT19/AT$79 -> 0.69553121 | AU63: =1000*AU19/AU$79 -> 0.81706022 | AV63: =AU63 -> 0.81706022 | AW63: =1000*AW19/AW$79 -> 1.2437811 | AX63: =1000*AX19/AX$79 -> 0.89772806 | AY63: =1000*AY19/AY$79 -> 1.2057272 | AZ63: =1000*AZ19/AZ$79 -> 2.0969071 | BA63: =AZ63 -> 2.0969071 | BB63: =1000*BB19/BB$79 -> 1.5863163 | BC63: =1000*BC19/BC$79 -> 1.5376387 | BD63: =1000*BD19/BD$79 -> 2.0447014 | BE63: =1000*BE19/BE$79 -> 2.1795126 | BF63: =BE63 -> 2.1795126 | BG63: =1000*BG19/BG$79 -> 2.2971379 | BH63: =1000*BH19/BH$79 -> 2.5923072 | BI63: =1000*BI19/BI$79 -> 2.4023265 | BJ63: =1000*BJ19/BJ$79 -> 2.7421081 | BK63: =BJ63 -> 2.7421081 | BL63: =1000*BL19/BL$79 -> 2.4169602 | BM63: =1000*BM19/BM$79 -> 0.33584095 | BN63: =1000*BN19/BN$79 -> 0 | BO63: ='Investment Business Of HoldCo'!AZ219/1000 -> 0 | BP63: =BO63 -> 0
A64: Arm | AE64: =1000*AE20/AE$79 -> 24.324324 | AF64: =1000*AF20/AF$79 -> 24.416614 | AG64: =AF64 -> 24.416614 | AH64: =1000*AH20/AH$79 -> 24.306522 | AI64: =1000*AI20/AI$79 -> 24.83321 | AJ64: =1000*AJ20/AJ$79 -> 24.644031 | AK64: =1000*AK20/AK$79 -> 24.166131 | AL64: =AK64 -> 24.166131 | AM64: =1000*AM20/AM$79 -> 24.59625 | AN64: =1000*AN20/AN$79 -> 24.574669 | AO64: =1000*AO20/AO$79 -> 24.637681 | AP64: =1000*AP20/AP$79 -> 24.568693 | AQ64: =AP64 -> 24.568693 | AR64: =1000*AR20/AR$79 -> 24.597576 | AS64: =1000*AS20/AS$79 -> 24.571122 | AT64: =1000*AT20/AT$79 -> 24.604417 | AU64: =1000*AU20/AU$79 -> 22.142332 | AV64: =AU64 -> 22.142332 | AW64: =1000*AW20/AW$79 -> 21.656424 | AX64: =1000*AX20/AX$79 -> 21.614529 | AY64: =1000*AY20/AY$79 -> 19.819141 | AZ64: =1000*AZ20/AZ$79 -> 21.493297 | BA64: =AZ64 -> 21.493297 | BB64: =1000*BB20/BB$79 -> 25.24312 | BC64: =1000*BC20/BC$79 -> 28.94772 | BD64: =1000*BD20/BD$79 -> 48.861313 | BE64: =1000*BE20/BE$79 -> 94.84182 | BF64: =BE64 -> 94.84182 | BG64: =1000*BG20/BG$79 -> 130.50227 | BH64: =1000*BH20/BH$79 -> 115.60289 | BI64: =1000*BI20/BI$79 -> 97.483879 | BJ64: =1000*BJ20/BJ$79 -> 86.276083 | BK64: =BJ64 -> 86.276083 | BL64: =1000*BL20/BL$79 -> 136.93806 | BM64: =1000*BM20/BM$79 -> 122.11177 | BN64: =1000*BN20/BN$79 -> 81.055187 | BO64: =BO159-BO106 -> 97.598771 | BP64: =BO64 -> 97.598771 | BQ64: =BQ159-BQ106 -> 97.598771 | BR64: =BR159-BR106 -> 95.098771 | BS64: =BS159-BS106 -> 92.598771 | BT64: =BT159-BT106 -> 92.598771 | BU64: =BT64 -> 92.598771
A65: Others | AE65: =1000*AE21/AE$79 -> 2.4324324 | AF65: =1000*AF21/AF$79 -> 4.2346157 | AG65: =AF65 -> 4.2346157 | AH65: =1000*AH21/AH$79 -> 8.3495686 | AI65: =1000*AI21/AI$79 -> 7.0422535 | AJ65: =1000*AJ21/AJ$79 -> 10.405257 | AK65: =1000*AK21/AK$79 -> 8.0860057 | AL65: =AK65 -> 8.0860057 | AM65: =1000*AM21/AM$79 -> 14.29367 | AN65: =1000*AN21/AN$79 -> 32.703214 | AO65: =1000*AO21/AO$79 -> 32.36715 | AP65: =1000*AP21/AP$79 -> 28.994671 | AQ65: =AP65 -> 28.994671 | AR65: =1000*AR21/AR$79 -> 27.491409 | AS65: =1000*AS21/AS$79 -> 17.691208 | AT65: =1000*AT21/AT$79 -> 15.649452 | AU65: =1000*AU21/AU$79 -> 15.19732 | AV65: =AU65 -> 15.19732 | AW65: =1000*AW21/AW$79 -> 13.096283 | AX65: =1000*AX21/AX$79 -> 10.979905 | AY65: =1000*AY21/AY$79 -> 9.7211756 | AZ65: =1000*AZ21/AZ$79 -> 9.7356399 | BA65: =AZ65 -> 9.7356399 | BB65: =1000*BB21/BB$79 -> 9.7937789 | BC65: =1000*BC21/BC$79 -> 11.565717 | BD65: =1000*BD21/BD$79 -> 12.479729 | BE65: =1000*BE21/BE$79 -> 12.482663 | BF65: =BE65 -> 12.482663 | BG65: =1000*BG21/BG$79 -> 12.416962 | BH65: =1000*BH21/BH$79 -> 14.432845 | BI65: =1000*BI21/BI$79 -> 13.086357 | BJ65: =1000*BJ21/BJ$79 -> 13.777421 | BK65: =BJ65 -> 13.777421 | BL65: =1000*BL21/BL$79 -> 17.471169 | BM65: =1000*BM21/BM$79 -> 22.770016 | BN65: =1000*BN21/BN$79 -> 28.487481 | BO65: =BO160-BO107 -> 30.839879 | BP65: =BO65 -> 30.839879 | BQ65: =BQ160-BQ107 -> 31.339879 | BR65: =BR160-BR107 -> 37.214879 | BS65: =BS160-BS107 -> 40.639879 | BT65: =BT160-BT107 -> 41.139879 | BU65: =BT65 -> 41.139879
A66: SBG total value of equity holdings net of asset-backed finance | AE66: =SUM(AE54:AE55)+AE61+SUM(AE62:AE65) -> 228.73874 | AF66: =SUM(AF54:AF55)+AF61+SUM(AF62:AF65) -> 245.87801 | AG66: =SUM(AG54:AG55)+AG61+SUM(AG62:AG65) -> 245.87801 | AH66: =SUM(AH54:AH55)+AH61+SUM(AH62:AH65) -> 239.81816 | AI66: =SUM(AI54:AI55)+AI61+SUM(AI62:AI65) -> 249.53669 | AJ66: =SUM(AJ54:AJ55)+AJ61+SUM(AJ62:AJ65) -> 272.54472 | AK66: =SUM(AK54:AK55)+AK61+SUM(AK62:AK65) -> 231.92135 | AL66: =SUM(AL54:AL55)+AL61+SUM(AL62:AL65) -> 231.92135 | ... BU66: =SUM(BU54:BU55)+BU61+SUM(BU62:BU65) -> 305.37467
BO67: = model DT on the basis of "net" position due to inconsistent reporting on collar transaction.
A68: Consolidated net interest-bearing debt | AE68: =1000*AE28/AE$79 -> 100.36036 | AF68: =1000*AF28/AF$79 -> 108.65844 | AG68: =AF68 -> 108.65844 | AH68: =1000*AH28/AH$79 -> 135.44856 | AI68: =1000*AI28/AI$79 -> 130.46701 | AJ68: =1000*AJ28/AJ$79 -> 143.30047 | AK68: =1000*AK28/AK$79 -> 101.35073 | AL68: =AK68 -> 101.35073 | AM68: =1000*AM28/AM$79 -> 92.351958 | AN68: =1000*AN28/AN$79 -> 85.727788 | AO68: =1000*AO28/AO$79 -> 119.71014 | AP68: =1000*AP28/AP$79 -> 126.63716 | AQ68: =AP68 -> 126.63716 | AR68: =1000*AR28/AR$79 -> 143.51601 | AS68: =1000*AS28/AS$79 -> 143.5847 | AT68: =1000*AT28/AT$79 -> 145.62685 | AU68: =1000*AU28/AU$79 -> 139.7173 | AV68: =AU68 -> 139.7173 | AW68: =1000*AW28/AW$79 -> 131.10916 | AX68: =1000*AX28/AX$79 -> 97.576134 | AY68: =1000*AY28/AY$79 -> 101.58252 | AZ68: =1000*AZ28/AZ$79 -> 101.77488 | BA68: =AZ68 -> 101.77488 | BB68: =1000*BB28/BB$79 -> 101.3863 | BC68: =1000*BC28/BC$79 -> 98.141463 | BD68: =1000*BD28/BD$79 -> 104.06825 | BE68: =1000*BE28/BE$79 -> 98.34225 | BF68: =BE68 -> 98.34225 | BG68: =1000*BG28/BG$79 -> 96.97647 | BH68: =1000*BH28/BH$79 -> 108.10621 | BI68: =1000*BI28/BI$79 -> 92.489569 | BJ68: =1000*BJ28/BJ$79 -> 96.375067 | BK68: =BJ68 -> 96.375067 | BL68: =1000*BL28/BL$79 -> 101.85761 | BM68: =1000*BM28/BM$79 -> 96.789361 | BN68: =1000*BN28/BN$79 -> 118.5488
A69: Less: net interest-bearing debt at self-financing entities | AE69: =1000*AE29/AE$79 -> 67.747748 | AF69: =1000*AF29/AF$79 -> 62.888549 | AG69: =AF69 -> 62.888549 | AH69: =1000*AH29/AH$79 -> 77.836534 | AI69: =1000*AI29/AI$79 -> 79.318013 | AJ69: =1000*AJ29/AJ$79 -> 86.436656 | AK69: =1000*AK29/AK$79 -> 41.992098 | AL69: =AK69 -> 41.992098 | AM69: =1000*AM29/AM$79 -> 39.910897 | AN69: =1000*AN29/AN$79 -> 24.007561 | AO69: =1000*AO29/AO$79 -> 45.797101 | AP69: =1000*AP29/AP$79 -> 49.318038 | AQ69: =AP69 -> 49.318038 | AR69: =1000*AR29/AR$79 -> 48.471695 | AS69: =1000*AS29/AS$79 -> 46.015011 | AT69: =1000*AT29/AT$79 -> 45.731177 | AU69: =1000*AU29/AU$79 -> 40.607893 | AV69: =AU69 -> 40.607893 | AW69: =1000*AW29/AW$79 -> 43.16652 | AX69: =1000*AX29/AX$79 -> 38.87853 | AY69: =1000*AY29/AY$79 -> 40.467219 | AZ69: =1000*AZ29/AZ$79 -> 40.290571 | BA69: =AZ69 -> 40.290571 | BB69: =1000*BB29/BB$79 -> 39.726878 | BC69: =1000*BC29/BC$79 -> 31.421313 | BD69: =1000*BD29/BD$79 -> 33.420292 | BE69: =1000*BE29/BE$79 -> 29.852718 | BF69: =BE69 -> 29.852718 | BG69: =1000*BG29/BG$79 -> 31.663252 | BH69: =1000*BH29/BH$79 -> 36.152175 | BI69: =1000*BI29/BI$79 -> 31.419901 | BJ69: =1000*BJ29/BJ$79 -> 32.704655 | BK69: =BJ69 -> 32.704655 | BL69: =1000*BL29/BL$79 -> 37.014018 | BM69: =1000*BM29/BM$79 -> 35.666308 | BN69: =1000*BN29/BN$79 -> 35.194175
A70: Other adjustments = 50% equity component of hybrid bonds plus asset-backed finance e.g., margin loans, collars etc. | AE70: =1000*AE30/AE$79 -> 0 | AF70: =1000*AF30/AF$79 -> 5.7662853 | AG70: =AF70 -> 5.7662853 | AH70: =1000*AH30/AH$79 -> 12.153261 | AI70: =1000*AI30/AI$79 -> 9.1734618 | AJ70: =1000*AJ30/AJ$79 -> 13.052209 | AK70: =1000*AK30/AK$79 -> 26.463291 | AL70: =AK70 -> 26.463291 | AM70: =1000*AM30/AM$79 -> 32.299981 | AN70: =1000*AN30/AN$79 -> 27.31569 | AO70: =1000*AO30/AO$79 -> 34.975845 | AP70: =1000*AP30/AP$79 -> 43.808147 | AQ70: =AP70 -> 43.808147 | AR70: =1000*AR30/AR$79 -> 48.833424 | AS70: =1000*AS30/AS$79 -> 54.592566 | AT70: =1000*AT30/AT$79 -> 53.642845 | AU70: =1000*AU30/AU$79 -> 60.544162 | AV70: =AU70 -> 60.544162 | AW70: =1000*AW30/AW$79 -> 64.896108 | AX70: =1000*AX30/AX$79 -> 38.257026 | AY70: =1000*AY30/AY$79 -> 37.905049 | AZ70: =1000*AZ30/AZ$79 -> 48.378642 | BA70: =AZ70 -> 48.378642 | BB70: =1000*BB30/BB$79 -> 52.348438 | BC70: =1000*BC30/BC$79 -> 53.683648 | BD70: =1000*BD30/BD$79 -> 53.162236 | BE70: =1000*BE30/BE$79 -> 51.581798 | BF70: =BE70 -> 51.581798 | BG70: =1000*BG30/BG$79 -> 46.74986 | BH70: =1000*BH30/BH$79 -> 43.018286 | BI70: =1000*BI30/BI$79 -> 33.69579 | BJ70: =1000*BJ30/BJ$79 -> 25.749064 | BK70: =BJ70 -> 25.749064 | BL70: =1000*BL30/BL$79 -> 18.990401 | BM70: =1000*BM30/BM$79 -> 17.06072 | BN70: =1000*BN30/BN$79 -> 32.000511
A71: Less: SBG TopCo standalone net interest-bearing debt | AE71: =AE68-AE69-AE70 -> 32.612613 | AF71: =AF68-AF69-AF70 -> 40.003604 | AG71: =AG68-AG69-AG70 -> 40.003604 | AH71: =AH68-AH69-AH70 -> 45.458762 | AI71: =AI68-AI69-AI70 -> 41.975537 | AJ71: =AJ68-AJ69-AJ70 -> 43.81161 | AK71: =AK68-AK69-AK70 -> 32.895341 | AL71: =AL68-AL69-AL70 -> 32.895341 | ... BN71: =BN68-BN69-BN70 -> 51.354113 | BO71: =BN71+('TopCo Net debt waterfall'!AZ37/1000) -> 51.124113 | BP71: =BO71 -> 51.124113 | BQ71: =BP71+('TopCo Net debt waterfall'!BB37/1000)-50%*1.5 -> 55.869113 | BR71: =BQ71+('TopCo Net debt waterfall'!BC37/1000)-50%*1.5 -> 67.119113 | BS71: =BR71+('TopCo Net debt waterfall'!BD37/1000)-50%*1.5 -> 78.064113 | BT71: =BS71+('TopCo Net debt waterfall'!BE37/1000) -> 77.159113 | BU71: =BT71 -> 77.159113
BQ72: = assumes $4.5bn of "Hybrid" bond issuance carrying 50% equity component in LTV.
A73: Net asset value = per SBG reporting. | AE73: =AE66-AE71 -> 196.12613 | AF73: =AF66-AF71 -> 205.8744 | AG73: =AG66-AG71 -> 205.8744 | AH73: =AH66-AH71 -> 194.3594 | AI73: =AI66-AI71 -> 207.56116 | AJ73: =AJ66-AJ71 -> 228.73311 | AK73: =AK66-AK71 -> 199.026 | AL73: =AL66-AL71 -> 199.026 | ... BU73: =BU66-BU71 -> 228.21556
A74: of which Telcos assets | AE74: =AE55+SUM(AE62:AE63) -> 68.558559 | AF74: =AF55+SUM(AF62:AF63) -> 71.177584 | AG74: =AG55+SUM(AG62:AG63) -> 71.177584 | AH74: =AH55+SUM(AH62:AH63) -> 70.507468 | AI74: =AI55+SUM(AI62:AI63) -> 73.387695 | AJ74: =AJ55+SUM(AJ62:AJ63) -> 73.201899 | AK74: =AK55+SUM(AK62:AK63) -> 70.293118 | AL74: =AL55+SUM(AL62:AL63) -> 70.293118 | ... BU74: =BU55+SUM(BU62:BU63) -> 18.595021
A75: Telcos as % of NAV | AE75: =AE74/AE73 -> 0.34956362 | AF75: =AF74/AF73 -> 0.34573304 | AG75: =AG74/AG73 -> 0.34573304 | AH75: =AH74/AH73 -> 0.3627685 | AI75: =AI74/AI73 -> 0.35357143 | AJ75: =AJ74/AJ73 -> 0.32003192 | AK75: =AK74/AK73 -> 0.3531856 | AL75: =AL74/AL73 -> 0.3531856 | ... BU75: =BU74/BU73 -> 0.081480074
A77: Loan-to-value = only uses net debt effectively held at TopCo i.e., standalone. | AE77: =AE71/AE66 -> 0.14257582 | AF77: =AF71/AF66 -> 0.16269696 | AG77: =AG71/AG66 -> 0.16269696 | AI77: =AI71/AI66 -> 0.16821389 | AJ77: =AJ71/AJ66 -> 0.16075017 | AK77: =AK71/AK66 -> 0.14183835 | AL77: =AL71/AL66 -> 0.14183835 | AM77: =AM71/AM66 -> 0.087359098 | AN77: =AN71/AN66 -> 0.11544561 | AO77: =AO71/AO66 -> 0.14346743 | AP77: =AP71/AP66 -> 0.12203947 | ... BU77: =BU71/BU66 -> 0.25267031
A79: EoP exchange rate | X79: =FX!I6 -> 112 | Y79: =FX!J6 -> 112.73 | Z79: =FX!K6 -> 113 | AA79: =FX!L6 -> 106.24 | AC79: =FX!N6 -> 110.54 | AD79: =FX!O6 -> 113.57 | AE79: =FX!P6 -> 111 | AF79: =FX!Q6 -> 110.99 | AH79: =FX!S6 -> 107.79 | AI79: =FX!T6 -> 107.92 | AJ79: =FX!U6 -> 109.56 | AK79: =FX!V6 -> 108.83 | AM79: =FX!X6 -> 107.74 | AN79: =FX!Y6 -> 105.8 | AO79: =FX!Z6 -> 103.5 | AP79: =FX!AA6 -> 110.71 | AR79: =FX!AC6 -> 110.58 | AS79: =FX!AD6 -> 111.92 | AT79: =FX!AE6 -> 115.02 | AU79: =FX!AF6 -> 122.39 | AW79: =FX!AH6 -> 136.68 | AX79: =FX!AI6 -> 144.81 | AY79: =FX!AJ6 -> 132.7 | AZ79: =FX!AK6 -> 133.53 | BB79: =FX!AM6 -> 144.99 | BC79: =FX!AN6 -> 149.58 | BD79: =FX!AO6 -> 141.83 | BE79: =FX!AP6 -> 151.41 | BG79: =FX!AR6 -> 161.07 | BH79: =FX!AS6 -> 142.73 | BI79: =FX!AT6 -> 158.18 | BJ79: =FX!AU6 -> 149.52 | BL79: =FX!AW6 -> 144.81 | BM79: =FX!AX6 -> 148.88 | BN79: =FX!AY6 -> 156.56 | BO79: =FX!AZ6 -> 155.1 | BQ79: =FX!BB6 -> 154.7 | BR79: =FX!BC6 -> 154.3 | BS79: =FX!BD6 -> 153.9 | BT79: =FX!BE6 -> 153.5
A81: Alternative LTV: = assumes OpenAI debt reported as ABF within SVF2 given intercompany loan from TopCo to SVF2.
A83: SBG total value of equity holdings net of asset-backed finance | BG83: =BG66-'SoftBank Other (13F)'!AR29/1000 -> 237.53647 | BH83: =BH66-'SoftBank Other (13F)'!AS29/1000 -> 232.18665 | BI83: =BI66-'SoftBank Other (13F)'!AT29/1000 -> 212.85877 | BJ83: =BJ66-'SoftBank Other (13F)'!AU29/1000 -> 209.80471 | BK83: =BK66-'SoftBank Other (13F)'!AV29/1000 -> 209.80471 | BL83: =BL66-7.5 -> 262.09464 | BM83: =BM66-7.5 -> 260.2324 | BN83: =BN66-7.5 -> 241.47803 | BO83: =BO66-7.5 -> 256.11261 | BP83: =BP66-'SoftBank Other (13F)'!BA29/1000 -> 217.32324
A84: Less: SBG TopCo standalone net interest-bearing debt | BG84: =BG71-'SoftBank Other (13F)'!AR29/1000 -> 18.563358 | BH84: =BH71-'SoftBank Other (13F)'!AS29/1000 -> 28.935753 | BI84: =BI71-'SoftBank Other (13F)'!AT29/1000 -> 27.373878 | BJ84: =BJ71-'SoftBank Other (13F)'!AU29/1000 -> 37.921348 | BK84: =BK71-'SoftBank Other (13F)'!AV29/1000 -> 37.921348 | BL84: =BL71-7.5 -> 38.353187 | BM84: =BM71-7.5 -> 36.562332 | BN84: =BN71-7.5 -> 43.854113 | BO84: =BO71-7.5 -> 43.624113 | BP84: =BP71-'SoftBank Other (13F)'!BA29/1000 -> 4.8347472
A85: Loan-to-value | BJ85: =BJ84/BJ83 -> 0.18074594 | BK85: =BK84/BK83 -> 0.18074594 | BL85: =BL84/BL83 -> 0.14633335 | BM85: =BM84/BM83 -> 0.14049877 | BN85: =BN84/BN83 -> 0.18160706 | BO85: =BO84/BO83 -> 0.17033177 | BP85: =BP84/BP83 -> 0.022246803
A87: SBG total value of equity holdings net of asset-backed finance post-International telcos sale | BN87: =BN83-SUM(BN62:BN63) -> 235.66556 | BO87: =BO83-SUM(BO62:BO63) -> 252.65485
A88: Less: SBG TopCo standalone net interest-bearing debt | BN88: =BN84-SUM(BN62:BN63) -> 38.041645 | BO88: =BO84-SUM(BO62:BO63) -> 40.166353
A89: Loan-to-value | BM89: =BM85 -> 0.14049877 | BN89: =BN88/BN87 -> 0.16142217 | BO89: =BO88/BO87 -> 0.15897717
A91: LTV with 25% Arm decline | BN91: =BN77 -> 0.20625962 | BO91: =BO71/(BO66-25%*BO159) -> 0.21823542 | BP91: =BP71/(BP66-25%*BP159) -> 0.21823542 | BQ91: =BQ71/(BQ66-25%*BQ159) -> 0.21605194 | BR91: =BR71/(BR66-25%*BR159) -> 0.24835112 | BS91: =BS71/(BS66-25%*BS159) -> 0.27915829 | BT91: =BT71/(BT66-25%*BT159) -> 0.27953834 | BU91: =BU71/(BU66-25%*BU159) -> 0.27953834
A93: Asset-backed financing and other obligations excluding "variable" prepaid forward contracts $bn = as implied by SBG reporting.
AW94: = this analysis excludes "variable" prepaid forward contracts e.g., mainly Alibaba, but some T-Mobile as for these both the "asset" i.e., gross ownership position in the company and the "liability" i.e., variable prepaid forward contracts move in tandem so "net equity" position is the same.
A95: SoftBank Group equity value of holdings = as reported by SBG in quarterly Data sheets. | BJ95: = DT formula adjustment for $1bn delta vs. SBG reporting built up in 2Q and 3Q24 -> seems like DT share price now above "short call strike price" of collar.
A96: Alibaba
A97: SoftBank Corp. | BC97: ='Investment Business Of HoldCo'!AN315/1000 -> 3.3299906 | BD97: ='Investment Business Of HoldCo'!AO315/1000 -> 3.5140661 | BE97: ='Investment Business Of HoldCo'!AP315/1000 -> 3.2943663 | BF97: =BE97 -> 3.2943663 | BG97: ='Investment Business Of HoldCo'!AR315/1000 -> 3.0986528 | BH97: ='Investment Business Of HoldCo'!AS315/1000 -> 3.4996147 | BI97: ='Investment Business Of HoldCo'!AT315/1000 -> 3.1596915 | BJ97: ='Investment Business Of HoldCo'!AU315/1000 -> 5.3237025 | BK97: =BJ97 -> 5.3237025 | BL97: ='Investment Business Of HoldCo'!AW315/1000 -> 5.5003108 | BM97: ='Investment Business Of HoldCo'!AX315/1000 -> 5.3533047 | BN97: ='Investment Business Of HoldCo'!AY315/1000 -> 7.6392437 | BO97: ='Investment Business Of HoldCo'!AZ315/1000 -> 7.7111541 | BP97: =BO97 -> 7.7111541 | BQ97: ='Investment Business Of HoldCo'!BB315/1000 -> 7.7310924 | BR97: ='Investment Business Of HoldCo'!BC315/1000 -> 7.7511342 | BS97: ='Investment Business Of HoldCo'!BD315/1000 -> 7.7712801 | BT97: ='Investment Business Of HoldCo'!BE315/1000 -> 7.7915309 | BU97: =BT97 -> 7.7915309
A98: SVF1
A99: OpenAI Global LLC
A100: SVF2 excl. OpenAI | BG100: =BG101 -> 3.6186379 | BH100: =BH101 -> 3.5597422 | BI100: =BI101 -> 3.4150651 | BJ100: =BJ101 -> 3.3523609 | BK100: =BJ100 -> 3.3523609 | BL100: =BL101 -> 3.1829086 | BM100: =BM101 -> 4.3463595 | BN100: =BN101 -> 5.3315726 | BO100: =BO101 -> 5.33 | BP100: =BO100 -> 5.33 | BQ100: =BQ101 -> 6.83 | BR100: =BR101 -> 8.08 | BS100: =BS101 -> 9.08 | BT100: =BT101 -> 10.58 | BU100: =BT100 -> 10.58
A101: SVF2 | BC101: ='SVF Segment'!AN924/1000 -> 3.6249031 | BD101: ='SVF Segment'!AO924/1000 -> 3.6186773 | BE101: ='SVF Segment'!AP924/1000 -> 3.6186117 | BF101: =BE101 -> 3.6186117 | BG101: ='SVF Segment'!AR924/1000 -> 3.6186379 | BH101: ='SVF Segment'!AS924/1000 -> 3.5597422 | BI101: ='SVF Segment'!AT924/1000 -> 3.4150651 | BJ101: ='SVF Segment'!AU924/1000 -> 3.3523609 | BK101: =BJ101 -> 3.3523609 | BL101: ='SVF Segment'!AW924/1000 -> 3.1829086 | BM101: ='SVF Segment'!AX924/1000 -> 4.3463595 | BN101: ='SVF Segment'!AY924/1000 -> 5.3315726 | BO101: ='SVF Segment'!AZ924/1000 -> 5.33 | BP101: =BO101 -> 5.33 | BQ101: ='SVF Segment'!BB924/1000 -> 6.83 | BR101: ='SVF Segment'!BC924/1000 -> 8.08 | BS101: ='SVF Segment'!BD924/1000 -> 9.08 | BT101: ='SVF Segment'!BE924/1000 -> 10.58 | BU101: =BT101 -> 10.58
A102: LatAm Funds
A103: SBG's equity in Vision Funds | BC103: =BC98+BC101+BC102 -> 3.6249031 | BD103: =BD98+BD101+BD102 -> 3.6186773 | BE103: =BE98+BE101+BE102 -> 3.6186117 | BF103: =BE103 -> 3.6186117 | BG103: =BG98+BG101+BG102 -> 3.6186379 | BH103: =BH98+BH101+BH102 -> 3.5597422 | BI103: =BI98+BI101+BI102 -> 3.4150651 | BJ103: =BJ98+BJ101+BJ102 -> 3.3523609 | BK103: =BJ103 -> 3.3523609 | BL103: =BL98+BL101+BL102 -> 3.1829086 | BM103: =BM98+BM101+BM102 -> 4.3463595 | BN103: =BN98+BN101+BN102 -> 5.3315726 | BO103: =BO98+BO101+BO102 -> 5.33 | BP103: =BO103 -> 5.33 | BQ103: =BQ98+BQ101+BQ102 -> 6.83 | BR103: =BR98+BR101+BR102 -> 8.08 | BS103: =BS98+BS101+BS102 -> 9.08 | BT103: =BT98+BT101+BT102 -> 10.58 | BU103: =BT103 -> 10.58
A104: T-Mobile US | BC104: ='Investment Business Of HoldCo'!AN316/1000 -> 2.8359406 | BD104: ='Investment Business Of HoldCo'!AO316/1000 -> 2.8449552 | BE104: ='Investment Business Of HoldCo'!AP316/1000 -> 2.854501 | BF104: =BE104 -> 2.854501 | BG104: ='Investment Business Of HoldCo'!AR316/1000 -> 0.54013783 | BH104: ='Investment Business Of HoldCo'!AS316/1000 -> 0 | BI104: ='Investment Business Of HoldCo'!AT316/1000 -> 0 | BJ104: ='Investment Business Of HoldCo'!AU316/1000 -> 0 | BK104: =BJ104 -> 0 | BL104: ='Investment Business Of HoldCo'!AW316/1000 -> 0 | BM104: ='Investment Business Of HoldCo'!AX316/1000 -> 0 | BN104: ='Investment Business Of HoldCo'!AY316/1000 -> 0 | BO104: ='Investment Business Of HoldCo'!AZ316/1000 -> 0 | BP104: =BO104 -> 0
A105: Deutsche Telekom | BC105: ='Investment Business Of HoldCo'!AN317/1000 -> 3.2196818 | BD105: ='Investment Business Of HoldCo'!AO317/1000 -> 3.3624762 | BE105: ='Investment Business Of HoldCo'!AP317/1000 -> 3.2818176 | BF105: =BE105 -> 3.2818176 | BG105: ='Investment Business Of HoldCo'!AR317/1000 -> 3.2594524 | BH105: ='Investment Business Of HoldCo'!AS317/1000 -> 3.3931199 | BI105: ='Investment Business Of HoldCo'!AT317/1000 -> 3.1495764 | BJ105: ='Investment Business Of HoldCo'!AU317/1000 -> 2.7380952 | BK105: =BJ105 -> 2.7380952 | BL105: ='Investment Business Of HoldCo'!AW317/1000 -> 2.357572 | BM105: ='Investment Business Of HoldCo'!AX317/1000 -> 0 | BN105: ='Investment Business Of HoldCo'!AY317/1000 -> 0 | BO105: ='Investment Business Of HoldCo'!AZ317/1000 -> 0 | BP105: =BO105 -> 0
A106: Arm | BC106: ='Investment Business Of HoldCo'!AN313/1000+12 -> 20.422249 | BD106: ='Investment Business Of HoldCo'!AO313/1000+12 -> 20.419234 | BE106: ='Investment Business Of HoldCo'!AP313/1000+12 -> 20.420184 | BF106: =BE106 -> 20.420184 | BG106: ='Investment Business Of HoldCo'!AR313/1000+12 -> 20.424908 | BH106: ='Investment Business Of HoldCo'!AS313/1000+12-4.1 -> 16.332705 | BI106: ='Investment Business Of HoldCo'!AT313/1000+12-4.1 -> 16.311936 | BJ106: ='Investment Business Of HoldCo'!AU313/1000+12-4.1-4.1 -> 12.216934 | BK106: =BJ106 -> 12.216934 | BL106: ='Investment Business Of HoldCo'!AW313/1000+12-4.1-4.1 -> 12.226214 | BM106: ='Investment Business Of HoldCo'!AX313/1000 -> 8.4376679 | BN106: ='Investment Business Of HoldCo'!AY313/1000 -> 19.806464 | BO106: ='Investment Business Of HoldCo'!AZ313/1000 -> 19.806464 | BP106: =BO106 -> 19.806464 | BQ106: ='Investment Business Of HoldCo'!BB313/1000 -> 19.806464 | BR106: ='Investment Business Of HoldCo'!BC313/1000 -> 22.306464 | BS106: ='Investment Business Of HoldCo'!BD313/1000 -> 24.806464 | BT106: ='Investment Business Of HoldCo'!BE313/1000 -> 24.806464 | BU106: =BT106 -> 24.806464
A107: Others
A108: SBG total asset-backed finance i.e., collateralised by equity holdings | BC108: =SUM(BC96:BC97)+BC103+SUM(BC104:BC107) -> 33.432765 | BD108: =SUM(BD96:BD97)+BD103+SUM(BD104:BD107) -> 33.759409 | BE108: =SUM(BE96:BE97)+BE103+SUM(BE104:BE107) -> 33.46948 | BF108: =SUM(BF96:BF97)+BF103+SUM(BF104:BF107) -> 33.46948 | BG108: =SUM(BG96:BG97)+BG103+SUM(BG104:BG107) -> 30.941789 | BH108: =SUM(BH96:BH97)+BH103+SUM(BH104:BH107) -> 26.785182 | BI108: =SUM(BI96:BI97)+BI103+SUM(BI104:BI107) -> 26.036269 | BJ108: =SUM(BJ96:BJ97)+BJ103+SUM(BJ104:BJ107) -> 23.631093 | ... BU108: =SUM(BU96:BU97)+BU103+SUM(BU104:BU107) -> 43.177995
BJ109: = Arm asset-backed finance and obligations adjusted for remaining $12bn Arm receivable payment.
A110: Asset-backed financing including proportionate net debt at Telcos assets:
A112: SoftBank Group equity value of holdings = as reported by SBG in quarterly Data sheets.
A113: Alibaba
A114: SoftBank Corp. | BD114: =BD97+$BD$138 -> 13.214066 | BE114: =BE97+$BD$138 -> 12.994366 | BF114: =BF97+$BD$138 -> 12.994366 | BG114: =BG97+$BD$138 -> 12.798653 | BH114: =BH97+$BD$138 -> 13.199615 | BI114: =BI97+$BD$138 -> 12.859691 | BJ114: =BJ97+$BD$138 -> 15.023703 | BK114: =BK97+$BD$138 -> 15.023703
A115: SVF1
A116: SVF2 | BD116: =BD101 -> 3.6186773 | BE116: =BE101 -> 3.6186117 | BF116: =BF101 -> 3.6186117 | BG116: =BG101 -> 3.6186379 | BH116: =BH101 -> 3.5597422 | BI116: =BI101 -> 3.4150651 | BJ116: =BJ101 -> 3.3523609 | BK116: =BK101 -> 3.3523609
A117: LatAm Funds
A118: SBG's equity in Vision Funds | BD118: =SUM(BD115:BD117) -> 3.6186773 | BE118: =SUM(BE115:BE117) -> 3.6186117 | BF118: =SUM(BF115:BF117) -> 3.6186117 | BG118: =SUM(BG115:BG117) -> 3.6186379 | BH118: =SUM(BH115:BH117) -> 3.5597422 | BI118: =SUM(BI115:BI117) -> 3.4150651 | BJ118: =SUM(BJ115:BJ117) -> 3.3523609 | BK118: =SUM(BK115:BK117) -> 3.3523609
A119: T-Mobile US | BD119: =BD104+$BD$139 -> 6.6449552 | BE119: =BE104+$BD$139 -> 6.654501 | BF119: =BF104+$BD$139 -> 6.654501 | BG119: =BG104+$BD$139 -> 4.3401378 | BH119: =BH104+$BD$139 -> 3.8 | BI119: =BI104+$BD$139 -> 3.8 | BJ119: =BJ104+$BD$139 -> 3.8 | BK119: =BK104+$BD$139 -> 3.8
A120: Deutsche Telekom | BD120: =BD105+$BD$140 -> 8.3624762 | BE120: =BE105+$BD$140 -> 8.2818176 | BF120: =BF105+$BD$140 -> 8.2818176 | BG120: =BG105+$BD$140 -> 8.2594524 | BH120: =BH105+$BD$140 -> 8.3931199 | BI120: =BI105+$BD$140 -> 8.1495764 | BJ120: =BJ105+$BD$140 -> 7.7380952 | BK120: =BK105+$BD$140 -> 7.7380952
...

Sheet AI Computing
A1: SoftBank Group Corp. | I1: Jun. '24 | J1: Sep. '24 | K1: Dec. '24 | M1: = year ending 31 March '25. | N1: Jun. '25 | O1: Sep. '25 | P1: Dec. '25 | R1: = year ending 31 March '26. | S1: Jun. '26 | T1: Sep. '26 | U1: Dec. '26 | W1: = year ending 31 March '27. | X1: Jun. '27 | Y1: Sep. '27 | Z1: Dec. '27 | AB1: = year ending 31 March '28. | AC1: Jun. '28 | AD1: Sep. '28 | AE1: Dec. '28 | AG1: = year ending 31 March '29. | AH1: Jun. '29 | AI1: Sep. '29 | AJ1: Dec. '29 | AL1: = year ending 31 March '30. | AM1: Jun. '29 | AN1: Sep. '29 | AO1: Dec. '29 | AQ1: = year ending 31 March '31.
A2: year end March ¥m | I2: 1Q24 | J2: 2Q24 | K2: 3Q24 | L2: 4Q24 | M2: FY24 | N2: 1Q25 | O2: 2Q25 | P2: 3Q25 | Q2: 4Q25 | R2: FY25 | S2: 1Q26 | T2: 2Q26 | U2: 3Q26 | V2: 4Q26 | W2: FY26 | X2: 1Q27 | Y2: 2Q27 | Z2: 3Q27 | AA2: 4Q27 | AB2: FY27 | AC2: 1Q28 | AD2: 2Q28 | AE2: 3Q28 | AF2: 4Q28 | AG2: FY28 | AH2: 1Q29 | AI2: 2Q29 | AJ2: 3Q29 | AK2: 4Q29 | AL2: FY29 | AM2: 1Q30 | AN2: 2Q30 | AO2: 3Q30 | AP2: 4Q30 | AQ2: FY30
A4: Arm quarterly revenues $m = using Arm quarterly reporting.
A6: Total revenues | I6: =[65]Sheet1!P11 -> 939 | J6: =[65]Sheet1!Q11 -> 844 | K6: =[65]Sheet1!R11 -> 983 | N6: =[65]Sheet1!U11 -> 1053 | O6: =[65]Sheet1!V11 -> 1135 | P6: =[65]Sheet1!W11 -> 1242
A7: Less: SoftBank Group licenses | I7: =-[65]Sheet1!P96 -> 0 | J7: =-[65]Sheet1!Q96 -> -43.2 | K7: =-[65]Sheet1!R96 -> -51.1 | N7: =-[65]Sheet1!U96 -> -126.1 | O7: =-[65]Sheet1!V96 -> -177.9 | P7: =-[65]Sheet1!W96 -> -200.2
A8: Total revenues from 3rd parties (incl. Arm China) | I8: =SUM(I6:I7) -> 939 | J8: =SUM(J6:J7) -> 800.8 | K8: =SUM(K6:K7) -> 931.9 | N8: =SUM(N6:N7) -> 926.9 | O8: =SUM(O6:O7) -> 957.1 | P8: =SUM(P6:P7) -> 1041.8
A9: % yoy growth | N9: =N8/I8-1 -> -0.012886049 | O9: =O8/J8-1 -> 0.19517982 | P9: =P8/K8-1 -> 0.11793111
A11: Year-to-date revenues
A12: Total revenues | I12: =I6 -> 939 | J12: =I12+J6 -> 1783 | K12: =J12+K6 -> 2766 | N12: =N6 -> 1053 | O12: =N12+O6 -> 2188 | P12: =O12+P6 -> 3430
A13: Less: SoftBank Group licenses | I13: =I7 -> 0 | J13: =I13+J7 -> -43.2 | K13: =J13+K7 -> -94.3 | N13: =N7 -> -126.1 | O13: =N13+O7 -> -304 | P13: =O13+P7 -> -504.2
A14: Total revenues from 3rd parties (incl. Arm China) | I14: =SUM(I12:I13) -> 939 | J14: =SUM(J12:J13) -> 1739.8 | K14: =SUM(K12:K13) -> 2671.7 | N14: =SUM(N12:N13) -> 926.9 | O14: =SUM(O12:O13) -> 1884 | P14: =SUM(P12:P13) -> 2925.8
A15: % yoy growth | N15: =N14/I14-1 -> -0.012886049 | O15: =O14/J14-1 -> 0.08288309 | P15: =P14/K14-1 -> 0.095107984
A17: AI Computing revenues ¥bn
A19: Year-to-date revenues
A20: Net sales ¥bn | K20: 408.142 | P20: 436.203
A21: FX year-to-date | K21: =AVERAGE(FX!AR5:AT5) -> 152.70333 | P21: =AVERAGE(FX!AW5:AY5) -> 148.91
A22: Net sales $m | K22: =1000*K20/K21 -> 2672.7773 | P22: =1000*P20/P21 -> 2929.3063
A23: Ampere + Graphcore revenues $m | K23: =K22-K14 -> 1.0772806 | P23: =P22-P14 -> 3.5062924

Sheet Investment Business Of HoldCo
A1: SoftBank Group Corp. | I1: Jun. '17 | J1: Sep. '17 | K1: Dec. '17 | M1: = year ending 31 March '18. | N1: Jun. '18 | O1: Sep. '18 | P1: Dec. '18 | R1: = year ending 31 March '19. | S1: Jun. '19 | T1: Sep. '19 | U1: Dec. '19 | W1: = year ending 31 March '20. | X1: Jun. '20 | Y1: Sep. '20 | Z1: Dec. '20 | AB1: = year ending 31 March '21. | AC1: Jun. '21 | AD1: Sep. '21 | AE1: Dec. '21 | AG1: = year ending 31 March '22. | AH1: Jun. '22 | AI1: Sep. '22 | AJ1: Dec. '22 | AL1: = year ending 31 March '23. | AM1: Jun. '23 | AN1: Sep. '23 | AO1: Dec. '23 | AQ1: = year ending 31 March '24. | AR1: Jun. '24 | AS1: Sep. '24 | AT1: Dec. '24 | AV1: = year ending 31 March '25. | AW1: Jun. '25 | AX1: Sep. '25 | AY1: Dec. '25 | BA1: = year ending 31 March '26. | BB1: Jun. '26 | BC1: Sep. '26 | BD1: Dec. '26 | BF1: = year ending 31 March '27. | BG1: Jun. '27 | BH1: Sep. '27 | BI1: Dec. '27 | BK1: = year ending 31 March '28. | BL1: Jun. '28 | BM1: Sep. '28 | BN1: Dec. '28 | BP1: = year ending 31 March '29. | BQ1: Jun. '29 | BR1: Sep. '29 | BS1: Dec. '29 | BU1: = year ending 31 March '30. | BV1: Jun. '29 | BW1: Sep. '29 | BX1: Dec. '29 | BZ1: = year ending 31 March '31.
A2: year end March ¥m | I2: 1Q17 | J2: 2Q17 | K2: 3Q17 | L2: 4Q17 | M2: FY17 | N2: 1Q18 | O2: 2Q18 | P2: 3Q18 | Q2: 4Q18 | R2: FY18 | S2: 1Q19 | T2: 2Q19 | U2: 3Q19 | V2: 4Q19 | W2: FY19 | X2: 1Q20 | Y2: 2Q20 | Z2: 3Q20 | AA2: 4Q20 | AB2: FY20 | AC2: 1Q21 | AD2: 2Q21 | AE2: 3Q21 | AF2: 4Q21 | AG2: FY21 | AH2: 1Q22 | AI2: 2Q22 | AJ2: 3Q22 | AK2: 4Q22 | AL2: FY22 | AM2: 1Q23 | AN2: 2Q23 | AO2: 3Q23 | AP2: 4Q23 | AQ2: FY23 | AR2: 1Q24 | AS2: 2Q24 | AT2: 3Q24 | AU2: 4Q24 | AV2: FY24 | AW2: 1Q25 | AX2: 2Q25 | AY2: 3Q25 | AZ2: 4Q25 | BA2: FY25 | BB2: 1Q26 | BC2: 2Q26 | BD2: 3Q26 | BE2: 4Q26 | BF2: FY26 | BG2: 1Q27 | BH2: 2Q27 | BI2: 3Q27 | BJ2: 4Q27 | BK2: FY27 | BL2: 1Q28 | BM2: 2Q28 | BN2: 3Q28 | BO2: 4Q28 | BP2: FY28 | BQ2: 1Q29 | BR2: 2Q29 | BS2: 3Q29 | BT2: 4Q29 | BU2: FY29 | BV2: 1Q30 | BW2: 2Q30 | BX2: 3Q30 | BY2: 4Q30 | BZ2: FY30 | CB2: FY24 | CC2: FY25 | CD2: FY26 | CE2: FY27 | CF2: FY28 | CG2: FY29 | CH2: FY30
A4: Financial results P&L ¥m | I4: P&L ¥m results taken from Consolidated financial reports. | AY4: = new and simplified "Investment Business of HoldCo" reporting from F3Q.
AP5: = impossible to know how to model moving forwards without any disclosures on holdings.
A6: Gain relating to settlement of prepaid forward contracts using Alibaba shares | AE6: 68050 | AF6: 131922 | AG6: =SUM(AC6:AF6) -> 199972 | AH6: 97263 | AI6: 4740988 | AL6: =SUM(AH6:AK6) -> 4838251
A7: Gain relating to sale of T-Mobile shares | AD7: 3149 | AG7: =SUM(AC7:AF7) -> 3149 | AH7: 24842 | AL7: =SUM(AH7:AK7) -> 24842
A8: Realised gain/(loss) on investments at asset management subsidiaries | AC8: 65416 | AD8: -2465 | AE8: 5364 | AF8: -13462 | AG8: =SUM(AC8:AF8) -> 54853 | AH8: 7176 | AI8: -61402 | AJ8: -15678 | AK8: -4046 | AL8: =SUM(AH8:AK8) -> -73950 | AM8: -59 | AN8: -88283 | AO8: -2343 | AP8: =AQ8-SUM(AM8:AO8) -> 325 | AQ8: -90360 | AR8: 159 | AS8: =355-AR8 -> 196 | AT8: =-41551-AS8-AR8 -> -41906 | AU8: =AV8-SUM(AR8:AT8) -> 2228 | AV8: -39323 | AW8: -48687 | AX8: =-36892-AW8 -> 11795
A9: Unrealised gain/(loss) on valuation of investments at asset management subsidiaries | AC9: 17557 | AD9: -97576 | AE9: -179275 | AF9: -134341 | AG9: =SUM(AC9:AF9) -> -393635 | AH9: -69479 | AI9: 10676 | AJ9: -4013 | AK9: -4238 | AL9: =SUM(AH9:AK9) -> -67054 | AM9: 906 | AN9: 29097 | AO9: 3248 | AP9: =AQ9-SUM(AM9:AO9) -> -20559 | AQ9: 12692 | AR9: -989 | AS9: =7965-AR9 -> 8954 | AT9: =30935-AS9-AR9 -> 22970 | AU9: =AV9-SUM(AR9:AT9) -> -41823 | AV9: -10888 | AW9: 174854 | AX9: =248948-AW9 -> 74094
A10: Derivative gain/(loss) on investments at asset management subsidiaries | AC10: 119511 | AD10: -43326 | AE10: 47541 | AF10: -34250 | AG10: =SUM(AC10:AF10) -> 89476 | AH10: -5246 | AI10: -596 | AJ10: 846 | AK10: -106 | AL10: =SUM(AH10:AK10) -> -5102 | AM10: 18 | AN10: -814 | AO10: 10 | AP10: =AQ10-SUM(AM10:AO10) -> -6 | AQ10: -792 | AR10: 0 | AS10: 0 | AT10: 0 | AU10: =AV10-SUM(AR10:AT10) -> 0 | AV10: 0 | AW10: 0 | AX10: 0
A11: Realised gain/(loss) on investments | AC11: 91789 | AD11: -428456 | AE11: 67224 | AF11: 100 | AG11: =SUM(AC11:AF11) -> -269343 | AH11: -400 | AI11: -147266 | AJ11: -90193 | AK11: 2242 | AL11: =SUM(AH11:AK11) -> -235617 | AM11: 17686 | AN11: -12197 | AO11: -23822 | AP11: =AQ11-SUM(AM11:AO11) -> -20096 | AQ11: -38429 | AR11: 32728 | AS11: =-29617-AR11 -> -62345 | AT11: =-15565-AS11-AR11 -> 14052 | AU11: =AV11-SUM(AR11:AT11) -> 553370 | AV11: 537805 | AW11: 494064 | AX11: =1119243-AW11 -> 625179
A12: Unrealised gain/(loss) on valuation of investments = T-Mobile and Deutsche Telekom positions. | AC12: 288351 | AD12: 173801 | AE12: -200375 | AF12: 26957 | AG12: =SUM(AC12:AF12) -> 288734 | AH12: -27605 | AI12: -1142854 | AJ12: 213163 | AK12: 813098 | AL12: =SUM(AH12:AK12) -> -144198 | AM12: -620356 | AN12: 306585 | AO12: -448793 | AP12: =AQ12-SUM(AM12:AO12) -> 150937 | AQ12: -611627 | AR12: 531085 | AS12: =2113078-AR12 -> 1581993 | AT12: =1995661-AS12-AR12 -> -117417 | AU12: =AV12-SUM(AR12:AT12) -> 1138592 | AV12: 3134253 | AW12: -966075 | AX12: =-1505592-AW12 -> -539517 | AZ12: =AZ40*AZ$245 -> 0 | BA12: =SUM(AW12:AZ12) -> -1505592 | BB12: =BB40*BB$245 -> 0 | BC12: =BC40*BC$245 -> 0 | BD12: =BD40*BD$245 -> 0 | BE12: =BE40*BE$245 -> 0 | BF12: =SUM(BB12:BE12) -> 0 | BG12: =BG40*BG$245 -> 0 | BH12: =BH40*BH$245 -> 0 | BI12: =BI40*BI$245 -> 0 | BJ12: =BJ40*BJ$245 -> 0 | BK12: =SUM(BG12:BJ12) -> 0 | BL12: =BL40*BL$245 -> 0 | BM12: =BM40*BM$245 -> 0 | BN12: =BN40*BN$245 -> 0 | BO12: =BO40*BO$245 -> 0 | BP12: =SUM(BL12:BO12) -> 0 | BQ12: =BQ40*BQ$245 -> 0 | BR12: =BR40*BR$245 -> 0 | BS12: =BS40*BS$245 -> 0 | BT12: =BT40*BT$245 -> 0 | BU12: =SUM(BQ12:BT12) -> 0 | BV12: =BV40*BV$245 -> 0 | BW12: =BW40*BW$245 -> 0 | BX12: =BX40*BX$245 -> 0 | BY12: =BY40*BY$245 -> 0 | BZ12: =SUM(BV12:BY12) -> 0
A13: Change in valuation for the fiscal year | AR13: 502605 | AS13: =1954299-AR13 -> 1451694 | AT13: =1509258-AS13-AR13 -> -445041 | AU13: =AV13-SUM(AR13:AT13) -> 870250 | AV13: 2379508 | AW13: -141149 | AX13: =-64042-AW13 -> 77107
A14: Reclassified to realised gain/(loss) recorded in the past fiscal years | AR14: 28480 | AS14: =158779-AR14 -> 130299 | AT14: =486403-AS14-AR14 -> 327624 | AU14: =AV14-SUM(AR14:AT14) -> 268342 | AV14: 754745 | AW14: -824926 | AX14: =-1569634-AW14 -> -744708
A15: Derivative gain/(loss) on investments | AC15: 147277 | AD15: -78778 | AE15: -72710 | AF15: 105735 | AG15: =SUM(AC15:AF15) -> 101524 | AH15: 73609 | AI15: 12924 | AJ15: 69001 | AK15: 49972 | AL15: =SUM(AH15:AK15) -> 205506 | AM15: -97024 | AN15: 30529 | AO15: 291887 | AP15: =AQ15-SUM(AM15:AO15) -> 658 | AQ15: 226050 | AR15: -12022 | AS15: =-8453-AR15 -> 3569 | AT15: =-24757-AS15-AR15 -> -16304 | AU15: =AV15-SUM(AR15:AT15) -> -272896 | AV15: -297653 | AW15: 31828 | AX15: =446896-AW15 -> 415068
A16: Effect of foreign exchange translation | AD16: 11233 | AE16: -1211 | AG16: =SUM(AC16:AF16) -> 10022 | AN16: 6532 | AQ16: 6532 | AR16: -11066 | AS16: =-11066-AR16 -> 0 | AT16: =-1912-AS16-AR16 -> 9154 | AU16: =AV16-SUM(AR16:AT16) -> -51 | AV16: -1963 | AW16: 33023 | AX16: =47782-AW16 -> 14759
A17: Other | AC17: 11480 | AD17: 726 | AE17: 1551 | AF17: 5626 | AG17: =SUM(AC17:AF17) -> 19383 | AH17: 11073 | AI17: 1005 | AJ17: 1882 | AK17: 3930 | AL17: =SUM(AH17:AK17) -> 17890 | AM17: 9132 | AN17: 4718 | AO17: 9915 | AP17: =AQ17-SUM(AM17:AO17) -> 13124 | AQ17: 36889 | AR17: 28038 | AS17: =44497-AR17 -> 16459 | AT17: =65639-AS17-AR17 -> 21142 | AU17: =AV17-SUM(AR17:AT17) -> 25951 | AV17: 91590 | AW17: 24445 | AX17: =43613-AW17 -> 19168
A18: Gain/(loss) on investments at Investment Business of Holding Companies | AC18: =SUM(AC6:AC12)+SUM(AC15:AC17) -> 741381 | AD18: =SUM(AD6:AD12)+SUM(AD15:AD17) -> -461692 | AE18: =SUM(AE6:AE12)+SUM(AE15:AE17) -> -263841 | AF18: =SUM(AF6:AF12)+SUM(AF15:AF17) -> 88287 | AG18: =SUM(AG6:AG12)+SUM(AG15:AG17) -> 104135 | AH18: =SUM(AH6:AH12)+SUM(AH15:AH17) -> 111233 | AI18: =SUM(AI6:AI12)+SUM(AI15:AI17) -> 3413475 | AJ18: =SUM(AJ6:AJ12)+SUM(AJ15:AJ17) -> 175008 | ... AX18: =SUM(AX6:AX12)+SUM(AX15:AX17) -> 620546 | AY18: =AY19-AX19 -> -200620 | AZ18: =SUM(AZ6:AZ12)+SUM(AZ15:AZ17) -> 0 | BA18: =SUM(BA6:BA12)+SUM(BA15:BA17) -> -1505592 | BB18: =SUM(BB6:BB12)+SUM(BB15:BB17) -> 0 | BC18: =SUM(BC6:BC12)+SUM(BC15:BC17) -> 0 | BD18: =SUM(BD6:BD12)+SUM(BD15:BD17) -> 0 | BE18: =SUM(BE6:BE12)+SUM(BE15:BE17) -> 0 | BF18: =SUM(BF6:BF12)+SUM(BF15:BF17) -> 0 | BG18: =SUM(BG6:BG12)+SUM(BG15:BG17) -> 0 | ... BZ18: =SUM(BZ6:BZ12)+SUM(BZ15:BZ17) -> 0
A19: as reported by SBG | AC19: 741381 | AD19: -461692 | AE19: -263841 | AF19: 88287 | AG19: =SUM(AC19:AF19) -> 104135 | AH19: 111233 | AI19: 3413475 | AJ19: 175008 | AK19: 860852 | AL19: =SUM(AH19:AK19) -> 4560568 | AM19: -689697 | AN19: 276167 | AO19: -169898 | AQ19: -459045 | AR19: 567933 | AS19: 2116759 | AT19: =2008450 -> 2008450 | AV19: 3413821 | AW19: -256548 | AX19: 363998 | AY19: 163378
A20: check | AC20: =AC18-AC19 -> 0 | AD20: =AD18-AD19 -> 0 | AE20: =AE18-AE19 -> 0 | AF20: =AF18-AF19 -> 0 | AH20: =AH18-AH19 -> 0 | AI20: =AI18-AI19 -> 0 | AJ20: =AJ18-AJ19 -> 0 | AK20: =AK18-AK19 -> 0 | AM20: =AM18-AM19 -> 0 | AN20: =AN18-AN19 -> 0 | AO20: =AO18-AO19 -> 0 | AQ20: =AQ18-AQ19 -> 0 | AR20: =AR18-AR19 -> 0 | AS20: =SUM(AR18:AS18)-AS19 -> 0 | AT20: =SUM(AR18:AT18)-AT19 -> 0 | AV20: =AV18-AV19 -> 0 | AW20: =AW18-AW19 -> 0 | AX20: =SUM(AW18:AX18)-AX19 -> 0 | AY20: =SUM(AW18:AY18)-AY19 -> 0
A22: Selling, general and administrative expenses | AC22: -20370 | AD22: -25872 | AE22: -16184 | AF22: -23445 | AG22: =SUM(AC22:AF22) -> -85871 | AH22: -16657 | AI22: -14005 | AJ22: -13537 | AK22: -29597 | AL22: =SUM(AH22:AK22) -> -73796 | AM22: -19633 | AN22: -21862 | AO22: -26544 | AP22: =AQ22-SUM(AM22:AO22) -> -21246 | AQ22: -89285 | AR22: -37171 | AS22: =-60806-AR22 -> -23635 | AT22: =-93743-AS22-AR22 -> -32937 | AU22: =AV22-SUM(AR22:AT22) -> -38113 | AV22: -131856 | AW22: -19140 | AX22: =-47627-AW22 -> -28487 | AY22: =-82174-AX22-AW22 -> -34547 | AZ22: =AZ48*AZ$244 -> -39228.481 | BA22: =SUM(AW22:AZ22) -> -121402.48 | BB22: =BB48*BB$244 -> -20699.582 | BC22: =BC48*BC$244 -> -30247.303 | BD22: =BD48*BD$244 -> -35033.336 | BE22: =BE48*BE$244 -> -39406.16 | BF22: =SUM(BB22:BE22) -> -125386.38 | BG22: =BG48*BG$244 -> -20792.777 | BH22: =BH48*BH$244 -> -30382.662 | BI22: =BI48*BI$244 -> -35189.153 | BJ22: =BJ48*BJ$244 -> -39580.343 | BK22: =SUM(BG22:BJ22) -> -125944.94 | BL22: =BL48*BL$244 -> -20884.111 | BM22: =BM48*BM$244 -> -30515.275 | BN22: =BN48*BN$244 -> -35341.763 | BO22: =BO48*BO$244 -> -39750.885 | BP22: =SUM(BL22:BO22) -> -126492.03 | BQ22: =BQ48*BQ$244 -> -20973.506 | BR22: =BR48*BR$244 -> -30645.03 | BS22: =BS48*BS$244 -> -35491.033 | BT22: =BT48*BT$244 -> -39917.638 | BU22: =SUM(BQ22:BT22) -> -127027.21 | BV22: =BV48*BV$244 -> -21060.884 | BW22: =BW48*BW$244 -> -30771.813 | BX22: =BX48*BX$244 -> -35636.83 | BY22: =BY48*BY$244 -> -40080.449 | BZ22: =SUM(BV22:BY22) -> -127549.98
A23: Finance cost | AC23: -59594 | AD23: -78818 | AE23: -70772 | AF23: -67924 | AG23: =SUM(AC23:AF23) -> -277108 | AH23: -80029 | AI23: -160610 | AJ23: -76563 | AK23: -81339 | AL23: =SUM(AH23:AK23) -> -398541 | AM23: -97256 | AN23: -112386 | AO23: -136361 | AP23: =AQ23-SUM(AM23:AO23) -> -127808 | AQ23: -473811 | AR23: -136075 | AS23: =-270408-AR23 -> -134333 | AT23: =-402887-AS23-AR23 -> -132479 | AU23: =AV23-SUM(AR23:AT23) -> -128365 | AV23: -531252 | AW23: -146581 | AX23: =-296333-AW23 -> -149752 | AY23: =-451597-AX23-AW23 -> -155264 | AZ23: =AZ308 -> -256640 | BA23: =SUM(AW23:AZ23) -> -708237 | BB23: =BB308 -> -255745 | BC23: =BC308 -> -201880 | BD23: =BD308 -> -201770 | BE23: =BE308 -> -201665 | BF23: =SUM(BB23:BE23) -> -861060 | BG23: =BG308 -> -201555 | BH23: =BH308 -> -201445 | BI23: =BI308 -> -201340 | BJ23: =BJ308 -> -201230 | BK23: =SUM(BG23:BJ23) -> -805570 | BL23: =BL308 -> -201120 | BM23: =BM308 -> -201010 | BN23: =BN308 -> -200900 | BO23: =BO308 -> -200795 | BP23: =SUM(BL23:BO23) -> -803825 | BQ23: =BQ308 -> -200685 | BR23: =BR308 -> -200575 | BS23: =BS308 -> -200465 | BT23: =BT308 -> -200350 | BU23: =SUM(BQ23:BT23) -> -802075 | BV23: =BV308 -> -200240 | BW23: =BW308 -> -200130 | BX23: =BX308 -> -200020 | BY23: =BY308 -> -199910 | BZ23: =SUM(BV23:BY23) -> -800300
A24: Foreign exchange gain/(loss) | AC24: -12661 | AD24: -77188 | AE24: -185280 | AF24: -429979 | AG24: =SUM(AC24:AF24) -> -705108 | AH24: -822035 | AI24: -278108 | AJ24: 374787 | AK24: -46697 | AL24: =SUM(AH24:AK24) -> -772053 | AM24: -466107 | AN24: -184024 | AO24: 343456 | AP24: =AQ24-SUM(AM24:AO24) -> -396763 | AQ24: -703438 | AR24: -442568 | AS24: =289539-AR24 -> 732107 | AT24: =-256029-AS24-AR24 -> -545568 | AU24: =AV24-SUM(AR24:AT24) -> 275286 | AV24: 19257 | AW24: 131780 | AX24: =8625-AW24 -> -123155 | AY24: =-107462-AX24-AW24 -> -116087 | AZ24: =AY306-AZ306 -> 51157.623 | BA24: =SUM(AW24:AZ24) -> -56304.377 | BB24: =BA306-BB306 -> 3078119.9 | BC24: =BB306-BC306 -> 6149.5052 | BD24: =BC306-BD306 -> 6161.7598 | BE24: =BD306-BE306 -> 6174.0701 | BF24: =SUM(BB24:BE24) -> 3096605.2 | BG24: =BF306-BG306 -> 6186.4363 | BH24: =BG306-BH306 -> 6198.8589 | BI24: =BH306-BI306 -> 6211.3382 | BJ24: =BI306-BJ306 -> 6223.8747 | BK24: =SUM(BG24:BJ24) -> 24820.508 | BL24: =BK306-BL306 -> 6236.4689 | BM24: =BL306-BM306 -> 6249.121 | BN24: =BM306-BN306 -> 6261.8315 | BO24: =BN306-BO306 -> 6274.601 | BP24: =SUM(BL24:BO24) -> 25022.022 | BQ24: =BP306-BQ306 -> 6287.4297 | BR24: =BQ306-BR306 -> 6300.3181 | BS24: =BR306-BS306 -> 6313.2666 | BT24: =BS306-BT306 -> 6326.2758 | BU24: =SUM(BQ24:BT24) -> 25227.29 | BV24: =BU306-BV306 -> 6339.346 | BW24: =BV306-BW306 -> 6352.4777 | BX24: =BW306-BX306 -> 6365.6713 | BY24: =BX306-BY306 -> 6378.9274 | BZ24: =SUM(BV24:BY24) -> 25436.422
A25: Income/(loss) on equity method investments | AC25: 54670 | AD25: 212319 | AE25: -45309 | AF25: 154753 | AG25: =SUM(AC25:AF25) -> 376433 | AH25: -139782 | AI25: 115903 | AJ25: -829 | AK25: 1872 | AL25: =SUM(AH25:AK25) -> -22836 | AM25: -1581 | AN25: -2481 | AO25: 2859 | AP25: =AQ25-SUM(AM25:AO25) -> 3107 | AQ25: 1904 | AR25: 0 | AS25: 0 | AT25: 0 | AU25: =AV25-SUM(AR25:AT25) -> 0 | AV25: 0 | AW25: 0 | AX25: 0 | AY25: 0
A26: Derivative gain/(loss) = predominantly relates to Alibaba prepaid forward contracts. | AC26: -108211 | AD26: 732200 | AE26: 482668 | AF26: 130029 | AG26: =SUM(AC26:AF26) -> 1236686 | AH26: -244986 | AI26: 1286487 | AJ26: -410386 | AK26: -565383 | AL26: =SUM(AH26:AK26) -> 65732 | AM26: 848775 | AN26: -148389 | AO26: 478445 | AP26: =AQ26-SUM(AM26:AO26) -> 321184 | AQ26: 1500015 | AR26: 58778 | AS26: =-1472334-AR26 -> -1531112 | AT26: =-802486-AS26-AR26 -> 669848 | AU26: =AV26-SUM(AR26:AT26) -> -1239344 | AV26: -2041830 | AW26: 228468 | AX26: =207918-AW26 -> -20550 | AY26: =216825-AX26-AW26 -> 8907 | AZ26: =AZ52*AZ$245 -> -86762.347 | BA26: =SUM(AW26:AZ26) -> 130062.65 | BB26: =BB52*BB$245 -> -88219.735 | BC26: =BC52*BC$245 -> -89701.003 | BD26: =BD52*BD$245 -> -91206.53 | BE26: =BE52*BE$245 -> -92736.698 | BF26: =SUM(BB26:BE26) -> -361863.97 | BG26: =BG52*BG$245 -> -94291.899 | BH26: =BH52*BH$245 -> -95872.525 | BI26: =BI52*BI$245 -> -97478.979 | BJ26: =BJ52*BJ$245 -> -99111.667 | BK26: =SUM(BG26:BJ26) -> -386755.07 | BL26: =BL52*BL$245 -> -100771 | BM26: =BM52*BM$245 -> -102457.4 | BN26: =BN52*BN$245 -> -104171.3 | BO26: =BO52*BO$245 -> -105913.12 | BP26: =SUM(BL26:BO26) -> -413312.82 | BQ26: =BQ52*BQ$245 -> -107683.29 | BR26: =BR52*BR$245 -> -109482.28 | BS26: =BS52*BS$245 -> -111310.52 | BT26: =BT52*BT$245 -> -113168.48 | BU26: =SUM(BQ26:BT26) -> -441644.58 | BV26: =BV52*BV$245 -> -115056.62 | BW26: =BW52*BW$245 -> -116975.41 | BX26: =BX52*BX$245 -> -118925.33 | BY26: =BY52*BY$245 -> -120906.86 | BZ26: =SUM(BV26:BY26) -> -471864.21
A27: Other gain/(loss) | AC27: 30112 | AD27: 89286 | AE27: 56133 | AF27: 140460 | AG27: =SUM(AC27:AF27) -> 315991 | AH27: -5797 | AI27: 97200 | AJ27: -179002 | AK27: 78371 | AL27: =SUM(AH27:AK27) -> -9228 | AM27: 30959 | AN27: 44263 | AO27: 45438 | AP27: =AQ27-SUM(AM27:AO27) -> 5474 | AQ27: 126134 | AR27: 27072 | AS27: =61616-AR27 -> 34544 | AT27: =78681-AS27-AR27 -> 17065 | AU27: =AV27-SUM(AR27:AT27) -> -12570 | AV27: 66111 | AW27: 41083 | AX27: =117828-AW27 -> 76745 | AY27: =171031-AX27-AW27 -> 53203
A28: Segment income (income before income tax) | AC28: =AC18+SUM(AC22:AC27) -> 625327 | AD28: =AD18+SUM(AD22:AD27) -> 390235 | AE28: =AE18+SUM(AE22:AE27) -> -42585 | AF28: =AF18+SUM(AF22:AF27) -> -7819 | AG28: =AG18+SUM(AG22:AG27) -> 965158 | AH28: =AH18+SUM(AH22:AH27) -> -1198053 | AI28: =AI18+SUM(AI22:AI27) -> 4460342 | AJ28: =AJ18+SUM(AJ22:AJ27) -> -130522 | ... BZ28: =BZ18+SUM(BZ22:BZ27) -> -1374277.8
A29: as reported by SBG | AC29: 625327 | AD29: 390235 | AE29: -42585 | AF29: -7819 | AH29: -1198053 | AI29: 4460342 | AJ29: -130522 | AK29: 218079 | AM29: -394540 | AN29: -148712 | AO29: 537395 | AQ29: -97526 | AR29: 37969 | AS29: 664366 | AT29: =531986 -> 531986 | AV29: 794251 | AW29: -20938 | AX29: 354409 | AY29: -89999
A30: check | AH30: =AH28-AH29 -> 0 | AI30: =AI28-AI29 -> 0 | AJ30: =AJ28-AJ29 -> 0 | AK30: =AK28-AK29 -> 0 | AM30: =AM28-AM29 -> 0 | AN30: =AN28-AN29 -> 0 | AO30: =AO28-AO29 -> 0 | AQ30: =AQ28-AQ29 -> 0 | AR30: =AR28-AR29 -> 0 | AS30: =SUM(AR28:AS28)-AS29 -> 0 | AT30: =SUM(AR28:AT28)-AT29 -> 0 | AV30: =AV28-AV29 -> 0 | AW30: =AW28-AW29 -> 0 | AX30: =SUM(AW28:AX28)-AX29 -> 0 | AY30: =SUM(AW28:AY28)-AY29 -> 0
A32: Financial results P&L $m | I32: P&L ¥m results taken from Consolidated financial reports. | AY32: = new and simplified "Investment Business of HoldCo" reporting from F3Q.
AP33: = impossible to know how to model moving forwards without any disclosures on holdings.
A34: Gain relating to settlement of prepaid forward contracts using Alibaba shares | AC34: =AC6/AC$244 -> 0 | AD34: =AD6/AD$244 -> 0 | AE34: =AE6/AE$244 -> 599.03169 | AF34: =AF6/AF$244 -> 1126.5756 | AG34: =SUM(AC34:AF34) -> 1725.6073 | AH34: =AH6/AH$244 -> 753.74303 | AI34: =AI6/AI$244 -> 34186.53 | AJ34: =AJ6/AJ$244 -> 0 | AK34: =AK6/AK$244 -> 0 | AL34: =SUM(AH34:AK34) -> 34940.273 | AM34: =AM6/AM$244 -> 0 | AN34: =AN6/AN$244 -> 0 | AO34: =AO6/AO$244 -> 0 | AP34: =AP6/AP$244 -> 0 | AQ34: =SUM(AM34:AP34) -> 0 | AR34: =AR6/AR$244 -> 0 | AS34: =AS6/AS$244 -> 0 | AT34: =AT6/AT$244 -> 0 | AU34: =AU6/AU$244 -> 0 | AV34: =SUM(AR34:AU34) -> 0 | AW34: =AW6/AW$244 -> 0 | AX34: =AX6/AX$244 -> 0
A35: Gain relating to sale of T-Mobile shares | AC35: =AC7/AC$244 -> 0 | AD35: =AD7/AD$244 -> 28.505477 | AE35: =AE7/AE$244 -> 0 | AF35: =AF7/AF$244 -> 0 | AG35: =SUM(AC35:AF35) -> 28.505477 | AH35: =AH7/AH$244 -> 192.51395 | AI35: =AI7/AI$244 -> 0 | AJ35: =AJ7/AJ$244 -> 0 | AK35: =AK7/AK$244 -> 0 | AL35: =SUM(AH35:AK35) -> 192.51395 | AM35: =AM7/AM$244 -> 0 | AN35: =AN7/AN$244 -> 0 | AO35: =AO7/AO$244 -> 0 | AP35: =AP7/AP$244 -> 0 | AQ35: =SUM(AM35:AP35) -> 0 | AR35: =AR7/AR$244 -> 0 | AS35: =AS7/AS$244 -> 0 | AT35: =AT7/AT$244 -> 0 | AU35: =AU7/AU$244 -> 0 | AV35: =SUM(AR35:AU35) -> 0 | AW35: =AW7/AW$244 -> 0 | AX35: =AX7/AX$244 -> 0
A36: Realised gain/(loss) on investments at asset management subsidiaries | AC36: =AC8/AC$244 -> 594.69091 | AD36: =AD8/AD$244 -> -22.31375 | AE36: =AE8/AE$244 -> 47.21831 | AF36: =AF8/AF$244 -> -114.96157 | AG36: =SUM(AC36:AF36) -> 504.6339 | AH36: =AH8/AH$244 -> 55.610663 | AI36: =AI8/AI$244 -> -442.76031 | AJ36: =AJ8/AJ$244 -> -111.06546 | AK36: =AK8/AK$244 -> -30.361699 | AL36: =SUM(AH36:AK36) -> -528.5768 | AM36: =AM8/AM$244 -> -0.42719571 | AN36: =AN8/AN$244 -> -607.00633 | AO36: =AO8/AO$244 -> -15.938776 | AP36: =AP8/AP$244 -> 2.1978765 | AQ36: =SUM(AM36:AP36) -> -621.17442 | AR36: =AR8/AR$244 -> 1.0157797 | AS36: =AS8/AS$244 -> 1.3044057 | AT36: =AT8/AT$244 -> -276.93629 | AU36: =AU8/AU$244 -> 14.566852 | AV36: =SUM(AR36:AU36) -> -260.04926 | AW36: =AW8/AW$244 -> -335.33301 | AX36: =AX8/AX$244 -> 79.966102
A37: Unrealised gain/(loss) on valuation of investments at asset management subsidiaries | AC37: =AC9/AC$244 -> 159.60909 | AD37: =AD9/AD$244 -> -883.28053 | AE37: =AE9/AE$244 -> -1578.125 | AF37: =AF9/AF$244 -> -1147.2331 | AG37: =SUM(AC37:AF37) -> -3449.0296 | AH37: =AH9/AH$244 -> -538.42994 | AI37: =AI9/AI$244 -> 76.982982 | AJ37: =AJ9/AJ$244 -> -28.428733 | AK37: =AK9/AK$244 -> -31.802491 | AL37: =SUM(AH37:AK37) -> -521.67819 | AM37: =AM9/AM$244 -> 6.5599884 | AN37: =AN9/AN$244 -> 200.06188 | AO37: =AO9/AO$244 -> 22.095238 | AP37: =AP9/AP$244 -> -139.03429 | AQ37: =SUM(AM37:AP37) -> 89.682821 | AR37: =AR9/AR$244 -> -6.3182776 | AS37: =AS9/AS$244 -> 59.590044 | AT37: =AT9/AT$244 -> 151.79752 | AU37: =AU9/AU$244 -> -273.4423 | AV37: =SUM(AR37:AU37) -> -68.37302 | AW37: =AW9/AW$244 -> 1204.3116 | AX37: =AX9/AX$244 -> 502.3322
A38: Derivative gain/(loss) on investments at asset management subsidiaries | AC38: =AC10/AC$244 -> 1086.4636 | AD38: =AD10/AD$244 -> -392.19698 | AE38: =AE10/AE$244 -> 418.49472 | AF38: =AF10/AF$244 -> -292.48506 | AG38: =SUM(AC38:AF38) -> 820.27632 | AH38: =AH10/AH$244 -> -40.654061 | AI38: =AI10/AI$244 -> -4.2976637 | AJ38: =AJ10/AJ$244 -> 5.9931992 | AK38: =AK10/AK$244 -> -0.79543749 | AL38: =SUM(AH38:AK38) -> -39.753963 | AM38: =AM10/AM$244 -> 0.1303309 | AN38: =AN10/AN$244 -> -5.5968097 | AO38: =AO10/AO$244 -> 0.068027211 | AP38: =AP10/AP$244 -> -0.040576182 | AQ38: =SUM(AM38:AP38) -> -5.4390278 | AR38: =AR10/AR$244 -> 0 | AS38: =AS10/AS$244 -> 0 | AT38: =AT10/AT$244 -> 0 | AU38: =AU10/AU$244 -> 0 | AV38: =SUM(AR38:AU38) -> 0 | AW38: =AW10/AW$244 -> 0 | AX38: =AX10/AX$244 -> 0
A39: Realised gain/(loss) on investments | AC39: =AC11/AC$244 -> 834.44545 | AD39: =AD11/AD$244 -> -3878.4828 | AE39: =AE11/AE$244 -> 591.76056 | AF39: =AF11/AF$244 -> 0.85397096 | AG39: =SUM(AC39:AF39) -> -2451.4229 | AH39: =AH11/AH$244 -> -3.099814 | AI39: =AI11/AI$244 -> -1061.9123 | AJ39: =AJ11/AJ$244 -> -638.94163 | AK39: =AK11/AK$244 -> 16.824253 | AL39: =SUM(AH39:AK39) -> -1687.1295 | AM39: =AM11/AM$244 -> 128.05735 | AN39: =AN11/AN$244 -> -83.862761 | AO39: =AO11/AO$244 -> -162.05442 | AP39: =AP11/AP$244 -> -135.90316 | AQ39: =SUM(AM39:AP39) -> -253.763 | AR39: =AR11/AR$244 -> 209.08452 | AS39: =AS11/AS$244 -> -414.91415 | AT39: =AT11/AT$244 -> 92.862807 | AU39: =AU11/AU$244 -> 3617.9797 | AV39: =SUM(AR39:AU39) -> 3505.0129 | AW39: =AW11/AW$244 -> 3402.879 | AX39: =AX11/AX$244 -> 4238.5017
A40: Unrealised gain/(loss) on valuation of investments | AC40: =AC12/AC$244 -> 2621.3727 | AD40: =AD12/AD$244 -> 1573.2869 | AE40: =AE12/AE$244 -> -1763.8644 | AF40: =AF12/AF$244 -> 230.20495 | AG40: =SUM(AC40:AF40) -> 2661.0001 | AH40: =AH12/AH$244 -> -213.92591 | AI40: =AI12/AI$244 -> -8240.9432 | AJ40: =AJ12/AJ$244 -> 1510.0808 | AK40: =AK12/AK$244 -> 6101.5909 | AL40: =SUM(AH40:AK40) -> -843.19746 | AM40: =AM12/AM$244 -> -4491.753 | AN40: =AN12/AN$244 -> 2107.9827 | AO40: =AO12/AO$244 -> -3053.0136 | AP40: =AP12/AP$244 -> 1020.7412 | AQ40: =SUM(AM40:AP40) -> -4416.0427 | AR40: =AR12/AR$244 -> 3392.864 | AS40: =AS12/AS$244 -> 10528.371 | AT40: =AT12/AT$244 -> -775.95163 | AU40: =AU12/AU$244 -> 7444.2105 | AV40: =SUM(AR40:AU40) -> 20589.494 | AW40: =AW12/AW$244 -> -6653.8673 | AX40: =AX12/AX$244 -> -3657.7424 | AZ40: =AZ65 -> 0 | BA40: =SUM(AW40:AZ40) -> -10311.61 | BB40: =BB65 -> 0 | BC40: =BC65 -> 0 | BD40: =BD65 -> 0 | BE40: =BE65 -> 0 | BF40: =SUM(BB40:BE40) -> 0 | BG40: =BG65 -> 0 | BH40: =BH65 -> 0 | BI40: =BI65 -> 0 | BJ40: =BJ65 -> 0 | BK40: =SUM(BG40:BJ40) -> 0 | BL40: =BL65 -> 0 | BM40: =BM65 -> 0 | BN40: =BN65 -> 0 | BO40: =BO65 -> 0 | BP40: =SUM(BL40:BO40) -> 0 | BQ40: =BQ65 -> 0 | BR40: =BR65 -> 0 | BS40: =BS65 -> 0 | BT40: =BT65 -> 0 | BU40: =SUM(BQ40:BT40) -> 0 | BV40: =BV65 -> 0 | BW40: =BW65 -> 0 | BX40: =BX65 -> 0 | BY40: =BY65 -> 0 | BZ40: =SUM(BV40:BY40) -> 0
A41: Change in valuation for the fiscal year | AR41: =AR13/AR$244 -> 3210.918 | AS41: =AS13/AS$244 -> 9661.2139 | AT41: =AT13/AT$244 -> -2941.0587 | AU41: =AU13/AU$244 -> 5689.7679 | AV41: =SUM(AR41:AU41) -> 15620.841 | AW41: =AW13/AW$244 -> -972.1675 | AX41: =AX13/AX$244 -> 522.75932
A42: Reclassified to realised gain/(loss) recorded in the past fiscal years | AR42: =AR14/AR$244 -> 181.94595 | AS42: =AS14/AS$244 -> 867.15693 | AT42: =AT14/AT$244 -> 2165.1071 | AU42: =AU14/AU$244 -> 1754.4426 | AV42: =SUM(AR42:AU42) -> 4968.6526 | AW42: =AW14/AW$244 -> -5681.6998 | AX42: =AX14/AX$244 -> -5048.8678
A43: Derivative gain on investments | AC43: =AC15/AC$244 -> 1338.8818 | AD43: =AD15/AD$244 -> -713.11668 | AE43: =AE15/AE$244 -> -640.05282 | AF43: =AF15/AF$244 -> 902.9462 | AG43: =SUM(AC43:AF43) -> 888.65852 | AH43: =AH15/AH$244 -> 570.43552 | AI43: =AI15/AI$244 -> 93.192962 | AJ43: =AJ15/AJ$244 -> 488.81411 | AK43: =AK15/AK$244 -> 374.99625 | AL43: =SUM(AH43:AK43) -> 1527.4388 | AM43: =AM15/AM$244 -> -702.51249 | AN43: =AN15/AN$244 -> 209.90787 | AO43: =AO15/AO$244 -> 1985.6259 | AP43: =AP15/AP$244 -> 4.4498546 | AQ43: =SUM(AM43:AP43) -> 1497.4711 | AR43: =AR15/AR$244 -> -76.803169 | AS43: =AS15/AS$244 -> 23.752163 | AT43: =AT15/AT$244 -> -107.74518 | AU43: =AU15/AU$244 -> -1784.2171 | AV43: =SUM(AR43:AU43) -> -1945.0132 | AW43: =AW15/AW$244 -> 219.2162 | AX43: =AX15/AX$244 -> 2814.0203
A44: Effect of foreign exchange translation | AC44: =AC16/AC$244 -> 0 | AD44: =AD16/AD$244 -> 101.68372 | AE44: =AE16/AE$244 -> -10.660211 | AF44: =AF16/AF$244 -> 0 | AG44: =SUM(AC44:AF44) -> 91.023504 | AH44: =AH16/AH$244 -> 0 | AI44: =AI16/AI$244 -> 0 | AJ44: =AJ16/AJ$244 -> 0 | AK44: =AK16/AK$244 -> 0 | AL44: =SUM(AH44:AK44) -> 0 | AM44: =AM16/AM$244 -> 0 | AN44: =AN16/AN$244 -> 44.911991 | AO44: =AO16/AO$244 -> 0 | AP44: =AP16/AP$244 -> 0 | AQ44: =SUM(AM44:AP44) -> 44.911991 | AR44: =AR16/AR$244 -> -70.695713 | AS44: =AS16/AS$244 -> 0 | AT44: =AT16/AT$244 -> 60.494317 | AU44: =AU16/AU$244 -> -0.3334423 | AV44: =SUM(AR44:AU44) -> -10.534839 | AW44: =AW16/AW$244 -> 227.44679 | AX44: =AX16/AX$244 -> 100.06102
A45: Other | AC45: =AC17/AC$244 -> 104.36364 | AD45: =AD17/AD$244 -> 6.57192 | AE45: =AE17/AE$244 -> 13.653169 | AF45: =AF17/AF$244 -> 48.044406 | AG45: =SUM(AC45:AF45) -> 172.63313 | AH45: =AH17/AH$244 -> 85.810601 | AI45: =AI17/AI$244 -> 7.2468993 | AJ45: =AJ17/AJ$244 -> 13.332389 | AK45: =AK17/AK$244 -> 29.49122 | AL45: =SUM(AH45:AK45) -> 135.88111 | AM45: =AM17/AM$244 -> 66.121208 | AN45: =AN17/AN$244 -> 32.439494 | AO45: =AO17/AO$244 -> 67.44898 | AP45: =AP17/AP$244 -> 88.753635 | AQ45: =SUM(AM45:AP45) -> 254.76332 | AR45: =AR17/AR$244 -> 179.12221 | AS45: =AS17/AS$244 -> 109.5368 | AT45: =AT17/AT$244 -> 139.71716 | AU45: =AU17/AU$244 -> 169.66983 | AV45: =SUM(AR45:AU45) -> 598.046 | AW45: =AW17/AW$244 -> 168.36559 | AX45: =AX17/AX$244 -> 129.95254
A46: Gain/(loss) on investments at Investment Business of Holding Companies | AC46: =SUM(AC34:AC40)+SUM(AC43:AC45) -> 6739.8273 | AD46: =SUM(AD34:AD40)+SUM(AD43:AD45) -> -4179.3428 | AE46: =SUM(AE34:AE40)+SUM(AE43:AE45) -> -2322.544 | AF46: =SUM(AF34:AF40)+SUM(AF43:AF45) -> 753.94535 | AG46: =SUM(AG34:AG40)+SUM(AG43:AG45) -> 991.8858 | AH46: =SUM(AH34:AH40)+SUM(AH43:AH45) -> 862.00403 | AI46: =SUM(AI34:AI40)+SUM(AI43:AI45) -> 24614.04 | AJ46: =SUM(AJ34:AJ40)+SUM(AJ43:AJ45) -> 1239.7846 | ... AX46: =SUM(AX34:AX40)+SUM(AX43:AX45) -> 4207.0915 | AY46: =AY18/AY$244 -> -1302.389 | AZ46: =SUM(AZ34:AZ40)+SUM(AZ43:AZ45) -> 0 | BA46: =SUM(BA34:BA40)+SUM(BA43:BA45) -> -10311.61 | BB46: =SUM(BB34:BB40)+SUM(BB43:BB45) -> 0 | BC46: =SUM(BC34:BC40)+SUM(BC43:BC45) -> 0 | BD46: =SUM(BD34:BD40)+SUM(BD43:BD45) -> 0 | BE46: =SUM(BE34:BE40)+SUM(BE43:BE45) -> 0 | BF46: =SUM(BF34:BF40)+SUM(BF43:BF45) -> 0 | BG46: =SUM(BG34:BG40)+SUM(BG43:BG45) -> 0 | ... BZ46: =SUM(BZ34:BZ40)+SUM(BZ43:BZ45) -> 0
A48: Selling, general and administrative expenses | AC48: =AC22/AC$244 -> -185.18182 | AD48: =AD22/AD$244 -> -234.19933 | AE48: =AE22/AE$244 -> -142.46479 | AF48: =AF22/AF$244 -> -200.21349 | AG48: =SUM(AC48:AF48) -> -762.05943 | AH48: =AH22/AH$244 -> -129.084 | AI48: =AI22/AI$244 -> -100.98789 | AJ48: =AJ22/AJ$244 -> -95.898271 | AK48: =AK22/AK$244 -> -222.09965 | AL48: =SUM(AH48:AK48) -> -548.06982 | AM48: =AM22/AM$244 -> -142.1548 | AN48: =AN22/AN$244 -> -150.31628 | AO48: =AO22/AO$244 -> -180.57143 | AP48: =AP22/AP$244 -> -143.68026 | AQ48: =SUM(AM48:AP48) -> -616.72277 | AR48: =AR22/AR$244 -> -237.46886 | AS48: =AS22/AS$244 -> -157.29402 | AT48: =AT22/AT$244 -> -217.66455 | AU48: =AU22/AU$244 -> -249.18601 | AV48: =SUM(AR48:AU48) -> -861.61344 | AW48: =AW22/AW$244 -> -131.82726 | AX48: =AX22/AX$244 -> -193.1322 | AY48: =AY22/AY$244 -> -224.27292 | AZ48: =-AZ56 -> -252.9238 | BA48: =SUM(AW48:AZ48) -> -802.15618 | BB48: =-BB56 -> -133.80467 | BC48: =-BC56 -> -196.02919 | BD48: =-BD56 -> -227.63701 | BE48: =-BE56 -> -256.71766 | BF48: =SUM(BB48:BE48) -> -814.18852 | BG48: =-BG56 -> -135.81174 | BH48: =-BH56 -> -198.96962 | BI48: =-BI56 -> -231.05157 | BJ48: =-BJ56 -> -260.56842 | BK48: =SUM(BG48:BJ48) -> -826.40135 | BL48: =-BL56 -> -137.84892 | BM48: =-BM56 -> -201.95417 | BN48: =-BN56 -> -234.51734 | BO48: =-BO56 -> -264.47695 | BP48: =SUM(BL48:BO48) -> -838.79737 | BQ48: =-BQ56 -> -139.91665 | BR48: =-BR56 -> -204.98348 | BS48: =-BS56 -> -238.0351 | BT48: =-BT56 -> -268.4441 | BU48: =SUM(BQ48:BT48) -> -851.37933 | BV48: =-BV56 -> -142.0154 | BW48: =-BW56 -> -208.05823 | BX48: =-BX56 -> -241.60563 | BY48: =-BY56 -> -272.47076 | BZ48: =SUM(BV48:BY48) -> -864.15002
A49: Finance cost | AC49: =AC23/AC$244 -> -541.76364 | AD49: =AD23/AD$244 -> -713.47877 | AE49: =AE23/AE$244 -> -622.99296 | AF49: =AF23/AF$244 -> -580.05124 | AG49: =SUM(AC49:AF49) -> -2458.2866 | AH49: =AH23/AH$244 -> -620.18754 | AI49: =AI23/AI$244 -> -1158.1338 | AJ49: =AJ23/AJ$244 -> -542.38453 | AK49: =AK23/AK$244 -> -610.37821 | AL49: =SUM(AH49:AK49) -> -2931.0841 | AM49: =AM23/AM$244 -> -704.19231 | AN49: =AN23/AN$244 -> -772.73102 | AO49: =AO23/AO$244 -> -927.62585 | AP49: =AP23/AP$244 -> -864.32677 | AQ49: =SUM(AM49:AP49) -> -3268.876 | AR49: =AR23/AR$244 -> -869.32217 | AS49: =AS23/AS$244 -> -894.00373 | AT49: =AT23/AT$244 -> -875.48903 | AU49: =AU23/AU$244 -> -839.2612 | AV49: =SUM(AR49:AU49) -> -3478.0761 | AW49: =AW23/AW$244 -> -1009.5805 | AX49: =AX23/AX$244 -> -1015.2678 | AY49: =AY23/AY$244 -> -1007.946 | AZ49: =AZ23/AZ$244 -> -1654.6744 | BA49: =SUM(AW49:AZ49) -> -4687.4687 | BB49: =BB23/BB$244 -> -1653.1674 | BC49: =BC23/BC$244 -> -1308.3603 | BD49: =BD23/BD$244 -> -1311.0461 | BE49: =BE23/BE$244 -> -1313.7785 | BF49: =SUM(BB49:BE49) -> -5586.3524 | BG49: =BG23/BG$244 -> -1316.4925 | BH49: =BH23/BH$244 -> -1319.2207 | BI49: =BI23/BI$244 -> -1321.9961 | BJ49: =BJ23/BJ$244 -> -1324.7531 | BK49: =SUM(BG49:BJ49) -> -5282.4624 | BL49: =BL23/BL$244 -> -1327.5248 | BM49: =BM23/BM$244 -> -1330.3111 | BN49: =BN23/BN$244 -> -1333.1121 | BO49: =BO23/BO$244 -> -1335.9614 | BP49: =SUM(BL49:BO49) -> -5326.9094 | BQ49: =BQ23/BQ$244 -> -1338.7925 | BR49: =BR23/BR$244 -> -1341.6388 | BS49: =BS23/BS$244 -> -1344.5003 | BT49: =BT23/BT$244 -> -1347.3436 | BU49: =SUM(BQ49:BT49) -> -5372.2753 | BV49: =BV23/BV$244 -> -1350.236 | BW49: =BW23/BW$244 -> -1353.144 | BX49: =BX23/BX$244 -> -1356.0678 | BY49: =BY23/BY$244 -> -1359.0075 | BZ49: =SUM(BV49:BY49) -> -5418.4553
A50: Foreign exchange gain/(loss) | AC50: =AC24/AC$244 -> -115.1 | AD50: =AD24/AD$244 -> -698.72364 | AE50: =AE24/AE$244 -> -1630.9859 | AF50: =AF24/AF$244 -> -3671.8958 | AG50: =SUM(AC50:AF50) -> -6116.7054 | AH50: =AH24/AH$244 -> -6370.389 | AI50: =AI24/AI$244 -> -2005.3937 | AJ50: =AJ24/AJ$244 -> 2655.051 | AK50: =AK24/AK$244 -> -350.42023 | AL50: =SUM(AH50:AK50) -> -6071.152 | AM50: =AM24/AM$244 -> -3374.8968 | AN50: =AN24/AN$244 -> -1265.2915 | AO50: =AO24/AO$244 -> 2336.4354 | AP50: =AP24/AP$244 -> -2683.1879 | AQ50: =SUM(AM50:AP50) -> -4986.9409 | AR50: =AR24/AR$244 -> -2827.3686 | AS50: =AS24/AS$244 -> 4872.2681 | AT50: =AT24/AT$244 -> -3605.3925 | AU50: =AU24/AU$244 -> 1799.8431 | AV50: =SUM(AR50:AU50) -> 239.35005 | AW50: =AW24/AW$244 -> 907.63827 | AX50: =AX24/AX$244 -> -834.94915 | AY50: =AY24/AY$244 -> -753.61594 | AZ50: =AZ24/AZ$244 -> 329.83638 | BA50: =SUM(AW50:AZ50) -> -351.09045 | BB50: =BB24/BB$244 -> 19897.349 | BC50: =BC24/BC$244 -> 39.854214 | BD50: =BD24/BD$244 -> 40.037426 | BE50: =BE24/BE$244 -> 40.221955 | BF50: =SUM(BB50:BE50) -> 20017.462 | BG50: =BG24/BG$244 -> 40.407814 | BH50: =BH24/BH$244 -> 40.595015 | BI50: =BI24/BI$244 -> 40.783573 | BJ50: =BJ24/BJ$244 -> 40.973501 | BK50: =SUM(BG50:BJ50) -> 162.7599 | BL50: =BL24/BL$244 -> 41.164811 | BM50: =BM24/BM$244 -> 41.357518 | BN50: =BN24/BN$244 -> 41.551636 | BO50: =BO24/BO$244 -> 41.747179 | BP50: =SUM(BL50:BO50) -> 165.82114 | BQ50: =BQ24/BQ$244 -> 41.94416 | BR50: =BR24/BR$244 -> 42.142596 | BS50: =BS24/BS$244 -> 42.342499 | BT50: =BT24/BT$244 -> 42.543886 | BU50: =SUM(BQ50:BT50) -> 168.97314 | BV50: =BV24/BV$244 -> 42.74677 | BW50: =BW24/BW$244 -> 42.951168 | BX50: =BX24/BX$244 -> 43.157094 | BY50: =BY24/BY$244 -> 43.364564 | BZ50: =SUM(BV50:BY50) -> 172.2196
A51: Income/(loss) on equity method investments | AC51: =AC25/AC$244 -> 497 | AD51: =AD25/AD$244 -> 1921.9607 | AE51: =AE25/AE$244 -> -398.84683 | AF51: =AF25/AF$244 -> 1321.5457 | AG51: =SUM(AC51:AF51) -> 3341.6596 | AH51: =AH25/AH$244 -> -1083.2455 | AI51: =AI25/AI$244 -> 835.75858 | AJ51: =AJ25/AJ$244 -> -5.8727685 | AK51: =AK25/AK$244 -> 14.047726 | AL51: =SUM(AH51:AK51) -> -239.31197 | AM51: =AM25/AM$244 -> -11.447397 | AN51: =AN25/AN$244 -> -17.058581 | AO51: =AO25/AO$244 -> 19.44898 | AP51: =AP25/AP$244 -> 21.011699 | AQ51: =SUM(AM51:AP51) -> 11.954701 | AR51: =AR25/AR$244 -> 0 | AS51: =AS25/AS$244 -> 0 | AT51: =AT25/AT$244 -> 0 | AU51: =AU25/AU$244 -> 0 | AV51: =SUM(AR51:AU51) -> 0 | AW51: =AW25/AW$244 -> 0 | AX51: =AX25/AX$244 -> 0 | AY51: =AY25/AY$244 -> 0
A52: Derivative gain/(loss) = predominantly relates to Alibaba prepaid forward contracts. | AC52: =AC26/AC$244 -> -983.73636 | AD52: =AD26/AD$244 -> 6628.0438 | AE52: =AE26/AE$244 -> 4248.838 | AF52: =AF26/AF$244 -> 1110.4099 | AG52: =SUM(AC52:AF52) -> 11003.555 | AH52: =AH26/AH$244 -> -1898.5276 | AI52: =AI26/AI$244 -> 9276.6585 | AJ52: =AJ26/AJ$244 -> -2907.24 | AK52: =AK26/AK$244 -> -4242.706 | AL52: =SUM(AH52:AK52) -> 228.18491 | AM52: =AM26/AM$244 -> 6145.6448 | AN52: =AN26/AN$244 -> -1020.2764 | AO52: =AO26/AO$244 -> 3254.7279 | AP52: =AP26/AP$244 -> 2172.0701 | AQ52: =SUM(AM52:AP52) -> 10552.166 | AR52: =AR26/AR$244 -> 375.50629 | AS52: =AS26/AS$244 -> -10189.751 | AT52: =AT26/AT$244 -> 4426.6984 | AU52: =AU26/AU$244 -> -8102.9356 | AV52: =SUM(AR52:AU52) -> -13490.482 | AW52: =AW26/AW$244 -> 1573.5794 | AX52: =AX26/AX$244 -> -139.32203 | AY52: =AY26/AY$244 -> 57.822643 | AZ52: =(AZ82-AY82)+(AZ166-AY166) -> -559.39618 | BA52: =SUM(AW52:AZ52) -> 932.68388 | BB52: =(BB82-BA82)+(BB166-BA166) -> -570.26331 | BC52: =(BC82-BB82)+(BC166-BB166) -> -581.34156 | BD52: =(BD82-BC82)+(BD166-BC166) -> -592.63502 | BE52: =(BE82-BD82)+(BE166-BD166) -> -604.14787 | BF52: =SUM(BB52:BE52) -> -2348.3878 | BG52: =(BG82-BF82)+(BG166-BF166) -> -615.88438 | BH52: =(BH82-BG82)+(BH166-BG166) -> -627.84889 | BI52: =(BI82-BH82)+(BI166-BH166) -> -640.04582 | BJ52: =(BJ82-BI82)+(BJ166-BI166) -> -652.4797 | BK52: =SUM(BG52:BJ52) -> -2536.2588 | BL52: =(BL82-BK82)+(BL166-BK166) -> -665.15513 | BM52: =(BM82-BL82)+(BM166-BL166) -> -678.0768 | BN52: =(BN82-BM82)+(BN166-BM166) -> -691.24949 | BO52: =(BO82-BN82)+(BO166-BN166) -> -704.67808 | BP52: =SUM(BL52:BO52) -> -2739.1595 | BQ52: =(BQ82-BP82)+(BQ166-BP166) -> -718.36754 | BR52: =(BR82-BQ82)+(BR166-BQ166) -> -732.32294 | BS52: =(BS82-BR82)+(BS166-BR166) -> -746.54945 | BT52: =(BT82-BS82)+(BT166-BS166) -> -761.05233 | BU52: =SUM(BQ52:BT52) -> -2958.2923 | BV52: =(BV82-BU82)+(BV166-BU166) -> -775.83694 | BW52: =(BW82-BV82)+(BW166-BV166) -> -790.90878 | BX52: =(BX82-BW82)+(BX166-BW166) -> -806.2734 | BY52: =(BY82-BX82)+(BY166-BX166) -> -821.93651 | BZ52: =SUM(BV52:BY52) -> -3194.9556
A53: Other gain/(loss) | AC53: =AC27/AC$244 -> 273.74545 | AD53: =AD27/AD$244 -> 808.23753 | AE53: =AE27/AE$244 -> 494.12852 | AF53: =AF27/AF$244 -> 1199.4876 | AG53: =SUM(AC53:AF53) -> 2775.5991 | AH53: =AH27/AH$244 -> -44.924055 | AI53: =AI27/AI$244 -> 700.89414 | AJ53: =AJ27/AJ$244 -> -1268.0788 | AK53: =AK27/AK$244 -> 588.10596 | AL53: =SUM(AH53:AK53) -> -24.002727 | AM53: =AM27/AM$244 -> 224.1619 | AN53: =AN27/AN$244 -> 304.33856 | AO53: =AO27/AO$244 -> 309.10204 | AP53: =AP27/AP$244 -> 37.019003 | AQ53: =SUM(AM53:AP53) -> 874.6215 | AR53: =AR27/AR$244 -> 172.95087 | AS53: =AS27/AS$244 -> 229.89485 | AT53: =AT27/AT$244 -> 112.77425 | AU53: =AU27/AU$244 -> -82.18372 | AV53: =SUM(AR53:AU53) -> 433.43625 | AW53: =AW27/AW$244 -> 282.96026 | AX53: =AX27/AX$244 -> 520.30508 | AY53: =AY27/AY$244 -> 345.38432
A54: Segment income (income before income tax) | AC54: =SUM(AC48:AC53) -> -1055.0364 | AD54: =SUM(AD48:AD53) -> 7711.8403 | AE54: =SUM(AE48:AE53) -> 1947.6761 | AF54: =SUM(AF48:AF53) -> -820.71734 | AG54: =SUM(AG48:AG53) -> 7783.7627 | AH54: =SUM(AH48:AH53) -> -10146.358 | AI54: =SUM(AI48:AI53) -> 7548.7958 | AJ54: =SUM(AJ48:AJ53) -> -2164.4233 | ... BZ54: =SUM(BZ48:BZ53) -> -9305.3414
A56: SG&A $m | AC56: =-AC48 -> 185.18182 | AD56: =-AD48 -> 234.19933 | AE56: =-AE48 -> 142.46479 | AF56: =-AF48 -> 200.21349 | AG56: =SUM(AC56:AF56) -> 762.05943 | AH56: =-AH48 -> 129.084 | AI56: =-AI48 -> 100.98789 | AJ56: =-AJ48 -> 95.898271 | AK56: =-AK48 -> 222.09965 | AL56: =SUM(AH56:AK56) -> 548.06982 | AM56: =-AM48 -> 142.1548 | AN56: =-AN48 -> 150.31628 | AO56: =-AO48 -> 180.57143 | AP56: =-AP48 -> 143.68026 | AQ56: =SUM(AM56:AP56) -> 616.72277 | AR56: =-AR48 -> 237.46886 | AS56: =-AS48 -> 157.29402 | AT56: =-AT48 -> 217.66455 | AU56: =-AU48 -> 249.18601 | AV56: =SUM(AR56:AU56) -> 861.61344 | AW56: =-AW48 -> 131.82726 | AX56: =-AX48 -> 193.1322 | AY56: =-AY48 -> 224.27292 | AZ56: =AU56*(1+AZ57) -> 252.9238 | BA56: =SUM(AW56:AZ56) -> 802.15618 | BB56: =AW56*(1+BB57) -> 133.80467 | BC56: =AX56*(1+BC57) -> 196.02919 | BD56: =AY56*(1+BD57) -> 227.63701 | BE56: =AZ56*(1+BE57) -> 256.71766 | BF56: =SUM(BB56:BE56) -> 814.18852 | BG56: =BB56*(1+BG57) -> 135.81174 | BH56: =BC56*(1+BH57) -> 198.96962 | BI56: =BD56*(1+BI57) -> 231.05157 | BJ56: =BE56*(1+BJ57) -> 260.56842 | BK56: =SUM(BG56:BJ56) -> 826.40135 | BL56: =BG56*(1+BL57) -> 137.84892 | BM56: =BH56*(1+BM57) -> 201.95417 | BN56: =BI56*(1+BN57) -> 234.51734 | BO56: =BJ56*(1+BO57) -> 264.47695 | BP56: =SUM(BL56:BO56) -> 838.79737 | BQ56: =BL56*(1+BQ57) -> 139.91665 | BR56: =BM56*(1+BR57) -> 204.98348 | BS56: =BN56*(1+BS57) -> 238.0351 | BT56: =BO56*(1+BT57) -> 268.4441 | BU56: =SUM(BQ56:BT56) -> 851.37933 | BV56: =BQ56*(1+BV57) -> 142.0154 | BW56: =BR56*(1+BW57) -> 208.05823 | BX56: =BS56*(1+BX57) -> 241.60563 | BY56: =BT56*(1+BY57) -> 272.47076 | BZ56: =SUM(BV56:BY56) -> 864.15002
A57: % yoy growth | AH57: =AH56/AC56-1 -> -0.3029337 | AI57: =AI56/AD56-1 -> -0.56879516 | AJ57: =AJ56/AE56-1 -> -0.32686334 | AK57: =AK56/AF56-1 -> 0.10931412 | AL57: =AL56/AG56-1 -> -0.28080436 | AM57: =AM56/AH56-1 -> 0.10125809 | AN57: =AN56/AI56-1 -> 0.48845855 | AO57: =AO56/AJ56-1 -> 0.88294769 | ... AY57: =AY56/AT56-1 -> 0.030360314 | AZ57: 0.015 | BA57: =BA56/AV56-1 -> -0.069006887 | BB57: 0.015 | BC57: 0.015 | BD57: 0.015 | BE57: 0.015 | BF57: =BF56/BA56-1 -> 0.015 | BG57: 0.015 | BH57: 0.015 | BI57: 0.015 | BJ57: 0.015 | BK57: =BK56/BF56-1 -> 0.015 | BL57: 0.015 | BM57: 0.015 | BN57: 0.015 | BO57: 0.015 | BP57: =BP56/BK56-1 -> 0.015 | BQ57: 0.015 | BR57: 0.015 | BS57: 0.015 | BT57: 0.015 | BU57: =BU56/BP56-1 -> 0.015 | BV57: 0.015 | BW57: 0.015 | BX57: 0.015 | BY57: 0.015 | BZ57: =BZ56/BU56-1 -> 0.015
A59: Unrealised gain/(loss) on "gross" EoP T-Mobile/DT positions:
AD60: = manual adjustment for sale of 45.4m T-Mobile shares. | AO60: = need to check with SBG IR about this modelling: doesn't make sense to me!
A61: Unrealised gain/(loss) on "gross" Alibaba position $m | AM61: =AM80-AL80 -> -6569.5081 | AN61: =AN80-AM80 -> 1182.7208 | AO61: =AO80-AN80 -> -3220.2103 | AP61: =AP80-AO80 -> -1796.7587 | AQ61: =SUM(AM61:AP61) -> -10403.756 | AR61: =AR80-AQ80 -> -125.59867 | AS61: =AS80-AR80 -> 1034.6318 | AT61: =AT80-AS80 -> 508.08901 | AU61: =AU80-AT80 -> 517.95942 | AV61: =SUM(AR61:AU61) -> 1935.0816 | AW61: =AW80-AV80 -> 528.02159 | AX61: =AX80-AW80 -> 538.27922
A62: Unrealised gain/(loss) on "gross" T-Mobile position $m | AC62: =AC144-AB144 -> 2076.9383 | AD62: =AD144-(AC144*AD96/AC96) -> -1039.989 | AE62: =AE144-AD144 -> -717.69596 | AF62: =AF144-AE144 -> 753.64168 | AG62: =SUM(AC62:AF62) -> 1072.8951 | AH62: =AH144-(AG144*AH96/AG96) -> 246.1875 | AI62: =AI144-AH144 -> -14.715569 | AJ62: =AJ144-AI144 -> 231.86965 | AK62: =AK144-AJ144 -> 192.49556 | AL62: =SUM(AH62:AK62) -> 655.83713 | AM62: =AM144-(AL144*AM96/AL96) -> -257.42896 | AN62: =AN144-AM144 -> 49.83894 | AO62: =AO144-(AN144*AO96/AN96) -> 1867.5805 | AP62: =AP144-AO144 -> 266.13942 | AQ62: =SUM(AM62:AP62) -> 1926.1299 | AR62: =AR144-AQ144 -> 7.7919674 | AS62: =AS144-AR144 -> 2576.4258 | AT62: =AT144-AS144 -> 1226.6385 | AU62: =AU144-AT144 -> 3924.9018 | AV62: =SUM(AR62:AU62) -> 7735.758 | AW62: =AW144-AV144 -> -7551.1123 | AX62: =AX144-AW144 -> -4395.5613
A63: Unrealised gain/(loss) on "gross" Deutsche Telekom position $m | AE63: =AE204-AD204 -> -383.99545 | AF63: =AF204-AE204 -> 79.545955 | AG63: =SUM(AC63:AF63) -> -304.4495 | AH63: =AH204-AG204 -> 224.19176 | AI63: =AI204-AH204 -> -596.96517 | AJ63: =AJ204-AI204 -> 622.43878 | AK63: =AK204-AJ204 -> 981.93219 | AL63: =SUM(AH63:AK63) -> 1231.5976 | AM63: =AM204-AL204 -> -556.88855 | AN63: =AN204-AM204 -> -175.291 | AO63: =AO204-AN204 -> 677.77412 | AP63: =AP204-AO204 -> 58.991995 | AQ63: =SUM(AM63:AP63) -> 4.5865755 | AR63: =AR204-AQ204 -> 192.31562 | AS63: =AS204-AR204 -> 961.9591 | AT63: =AT204-AS204 -> 121.87877 | AU63: =AU204-AT204 -> 856.34861 | AV63: =SUM(AR63:AU63) -> 2132.5021 | AW63: =AW204-AV204 -> -1544.956 | AX63: =AX204-AW204 -> -5688.1868
A64: delta | AM64: =AM65-SUM(AM61:AM63) -> 2892.0727 | AN64: =AN65-SUM(AN61:AN63) -> 1050.7139 | AO64: =AO65-SUM(AO61:AO63) -> -2378.1579 | AP64: =AP65-SUM(AP61:AP63) -> 2492.3685 | AQ64: =SUM(AM64:AP64) -> 4056.9973 | AR64: =AR65-SUM(AR61:AR63) -> 3318.3551 | AS64: =AS65-SUM(AS61:AS63) -> 5955.3541 | AT64: =AT65-SUM(AT61:AT63) -> -2632.5579 | AU64: =AU65-SUM(AU61:AU63) -> 2145.0007 | AV64: =SUM(AR64:AU64) -> 8786.152 | AW64: =AW65-SUM(AW61:AW63) -> 1914.1794 | AX64: =AX65-SUM(AX61:AX63) -> 5887.7266
A65: Total unrealised gain/(loss) on investments | AM65: =AM40 -> -4491.753 | AN65: =AN40 -> 2107.9827 | AO65: =AO40 -> -3053.0136 | AP65: =AP40 -> 1020.7412 | AQ65: =SUM(AQ61:AQ64) -> -4416.0427 | AR65: =AR40 -> 3392.864 | AS65: =AS40 -> 10528.371 | AT65: =AT40 -> -775.95163 | AU65: =AU40 -> 7444.2105 | AV65: =SUM(AV61:AV64) -> 20589.494 | AW65: =AW40 -> -6653.8673 | AX65: =AX40 -> -3657.7424
AX66: = need to include 13F positions e.g., NVIDIA, Intel, etc.
A67: Alibaba
A69: Ownership:
AM70: Source: latest S&P Capital IQ disclosures.
A71: SBG EoP Alibaba shares | AK71: 348.88519 | AL71: =AK71 -> 348.88519 | AM71: 348.88519 | AN71: 348.88519 | AO71: 348.88519 | AP71: 348.88519 | AQ71: =AP71 -> 348.88519 | AR71: 348.88519 | AS71: 261.67449 | AT71: =AS71 -> 261.67449 | AU71: =AT71 -> 261.67449 | AV71: =AU71 -> 261.67449 | AW71: =AV71 -> 261.67449 | AX71: =AW71 -> 261.67449 | AY71: =AX71 -> 261.67449 | AZ71: =AY71 -> 261.67449 | BA71: =AZ71 -> 261.67449 | ... BZ71: =BY71 -> 261.67449
A72: % ownership | AK72: =AK71/AK74 -> 0.14336029 | AM72: =AM71/AM74 -> 0.14336029 | AN72: =AN71/AN74 -> 0.14336029 | AO72: =AO71/AO74 -> 0.14336029 | AP72: =AP71/AP74 -> 0.14336029 | AR72: =AR71/AR74 -> 0.14336029 | AS72: =AS71/AS74 -> 0.10752457 | AT72: =AT71/AT74 -> 0.10752457 | AU72: =AU71/AU74 -> 0.10752457 | AW72: =AW71/AW74 -> 0.10752457 | AX72: =AX71/AX74 -> 0.10752457 | AY72: =AY71/AY74 -> 0.10752457 | AZ72: =AZ71/AZ74 -> 0.10752457 | BB72: =BB71/BB74 -> 0.10752457 | BC72: =BC71/BC74 -> 0.10752457 | BD72: =BD71/BD74 -> 0.10752457 | BE72: =BE71/BE74 -> 0.10752457 | BG72: =BG71/BG74 -> 0.10752457 | BH72: =BH71/BH74 -> 0.10752457 | BI72: =BI71/BI74 -> 0.10752457 | BJ72: =BJ71/BJ74 -> 0.10752457 | BL72: =BL71/BL74 -> 0.10752457 | BM72: =BM71/BM74 -> 0.10752457 | BN72: =BN71/BN74 -> 0.10752457 | BO72: =BO71/BO74 -> 0.10752457 | BQ72: =BQ71/BQ74 -> 0.10752457 | BR72: =BR71/BR74 -> 0.10752457 | BS72: =BS71/BS74 -> 0.10752457 | BT72: =BT71/BT74 -> 0.10752457 | BV72: =BV71/BV74 -> 0.10752457 | BW72: =BW71/BW74 -> 0.10752457 | BX72: =BX71/BX74 -> 0.10752457 | BY72: =BY71/BY74 -> 0.10752457
AM73: Source: latest S&P Capital IQ disclosures.
A74: Alibaba EoP shares outstanding (millions) | AK74: 2433.625 | AL74: =AK74 -> 2433.625 | AM74: 2433.625 | AN74: 2433.625 | AO74: 2433.625 | AP74: 2433.625 | AQ74: =AP74 -> 2433.625 | AR74: 2433.625 | AS74: =AR74 -> 2433.625 | AT74: =AS74 -> 2433.625 | AU74: =AT74 -> 2433.625 | AV74: =AU74 -> 2433.625 | AW74: =AV74 -> 2433.625 | AX74: =AW74 -> 2433.625 | AY74: =AX74 -> 2433.625 | AZ74: =AY74 -> 2433.625 | ... BZ74: =BY74 -> 2433.625
A76: SBG economic exposure: | AR76: = Alibaba share price CAGR. | AS76: 0.08 | AT76: = quarterly. | AU76: =(1+AS76)^(1/4)-1 -> 0.019426547
A78: Alibaba ADR EoP share price $ | AH78: =VLOOKUP(AH2, 'SBG investee share prices'!$B:$C, 2, FALSE) -> 113.68 | AI78: =VLOOKUP(AI2, 'SBG investee share prices'!$B:$C, 2, FALSE) -> 79.99 | AJ78: =VLOOKUP(AJ2, 'SBG investee share prices'!$B:$C, 2, FALSE) -> 88.09 | AK78: =VLOOKUP(AK2, 'SBG investee share prices'!$B:$C, 2, FALSE) -> 102.18 | AL78: =AK78 -> 102.18 | AM78: =VLOOKUP(AM2, 'SBG investee share prices'!$B:$C, 2, FALSE) -> 83.35 | AN78: =VLOOKUP(AN2, 'SBG investee share prices'!$B:$C, 2, FALSE) -> 86.74 | AO78: =VLOOKUP(AO2, 'SBG investee share prices'!$B:$C, 2, FALSE) -> 77.51 | AP78: =VLOOKUP(AP2, 'SBG investee share prices'!$B:$C, 2, FALSE) -> 72.36 | AQ78: =AP78 -> 72.36 | AR78: =VLOOKUP(AR2, 'SBG investee share prices'!$B:$C, 2, FALSE) -> 72 | AS78: 99.95 | AT78: =AS78*(1+$AU$76) -> 101.89168 | AU78: =AT78*(1+$AU$76) -> 103.87109 | AV78: =AU78 -> 103.87109 | AW78: =AV78*(1+$AU$76) -> 105.88894 | AX78: =AW78*(1+$AU$76) -> 107.946 | AY78: =AX78*(1+$AU$76) -> 110.04302 | AZ78: =AY78*(1+$AU$76) -> 112.18077 | BA78: =AZ78 -> 112.18077 | BB78: =BA78*(1+$AU$76) -> 114.36006 | BC78: =BB78*(1+$AU$76) -> 116.58168 | BD78: =BC78*(1+$AU$76) -> 118.84646 | BE78: =BD78*(1+$AU$76) -> 121.15524 | BF78: =BE78 -> 121.15524 | BG78: =BF78*(1+$AU$76) -> 123.50886 | BH78: =BG78*(1+$AU$76) -> 125.90821 | BI78: =BH78*(1+$AU$76) -> 128.35418 | BJ78: =BI78*(1+$AU$76) -> 130.84765 | BK78: =BJ78 -> 130.84765 | BL78: =BK78*(1+$AU$76) -> 133.38957 | BM78: =BL78*(1+$AU$76) -> 135.98087 | BN78: =BM78*(1+$AU$76) -> 138.62251 | BO78: =BN78*(1+$AU$76) -> 141.31547 | BP78: =BO78 -> 141.31547 | BQ78: =BP78*(1+$AU$76) -> 144.06074 | BR78: =BQ78*(1+$AU$76) -> 146.85934 | BS78: =BR78*(1+$AU$76) -> 149.71231 | BT78: =BS78*(1+$AU$76) -> 152.6207 | BU78: =BT78 -> 152.6207 | BV78: =BU78*(1+$AU$76) -> 155.5856 | BW78: =BV78*(1+$AU$76) -> 158.60809 | BX78: =BW78*(1+$AU$76) -> 161.6893 | BY78: =BX78*(1+$AU$76) -> 164.83036 | BZ78: =BY78 -> 164.83036
A80: SBG EoP gross Alibaba position $m | AK80: =AK71*AK78 -> 35649.089 | AL80: =AL71*AL78 -> 35649.089 | AM80: =AM71*AM78 -> 29079.581 | AN80: =AN71*AN78 -> 30262.301 | AO80: =AO71*AO78 -> 27042.091 | AP80: =AP71*AP78 -> 25245.332 | AQ80: =AQ71*AQ78 -> 25245.332 | AR80: =AR71*AR78 -> 25119.734 | ... BZ80: =BZ71*BZ78 -> 43131.901
A82: Less: SBG asset-backed financing relating to Alibaba shares | AM82: =-AM270/AM$245 -> -32862.266 | AN82: =-AN270/AN$245 -> -33028.48 | AO82: =-AO270/AO$245 -> -31962.208 | AP82: =-AP270/AP$245 -> -30886.996 | AQ82: =AP82 -> -30886.996 | AR82: =-AR270/AR$245 -> -28841.497 | AS82: =AR82+(AR80-AS80) -> -29876.129 | AT82: =AS82+(AS80-AT80) -> -30384.218 | AU82: =AT82+(AT80-AU80) -> -30902.178 | AV82: =AU82 -> -30902.178 | AW82: =AV82+(AV80-AW80) -> -31430.199 | AX82: =AW82+(AW80-AX80) -> -31968.479 | AY82: =AX82+(AX80-AY80) -> -32517.215 | AZ82: =AY82+(AY80-AZ80) -> -33076.611 | BA82: =AZ82 -> -33076.611 | BB82: =BA82+(BA80-BB80) -> -33646.874 | BC82: =BB82+(BB80-BC80) -> -34228.216 | BD82: =BC82+(BC80-BD80) -> -34820.851 | BE82: =BD82+(BD80-BE80) -> -35424.999 | BF82: =BE82 -> -35424.999 | BG82: =BF82+(BF80-BG80) -> -36040.883 | BH82: =BG82+(BG80-BH80) -> -36668.732 | BI82: =BH82+(BH80-BI80) -> -37308.778 | BJ82: =BI82+(BI80-BJ80) -> -37961.257 | BK82: =BJ82 -> -37961.257 | BL82: =BK82+(BK80-BL80) -> -38626.413 | BM82: =BL82+(BL80-BM80) -> -39304.489 | BN82: =BM82+(BM80-BN80) -> -39995.739 | BO82: =BN82+(BN80-BO80) -> -40700.417 | BP82: =BO82 -> -40700.417 | BQ82: =BP82+(BP80-BQ80) -> -41418.784 | BR82: =BQ82+(BQ80-BR80) -> -42151.107 | BS82: =BR82+(BR80-BS80) -> -42897.657 | BT82: =BS82+(BS80-BT80) -> -43658.709 | BU82: =BT82 -> -43658.709 | BV82: =BU82+(BU80-BV80) -> -44434.546 | BW82: =BV82+(BV80-BW80) -> -45225.455 | BX82: =BW82+(BW80-BX80) -> -46031.728 | BY82: =BX82+(BX80-BY80) -> -46853.665 | BZ82: =BY82 -> -46853.665
A83: SBG EoP net Alibaba position $m | AM83: =AM80+AM82 -> -3782.6857 | AN83: =AN80+AN82 -> -2766.1783 | AO83: =AO80+AO82 -> -4920.1171 | AP83: =AP80+AP82 -> -5641.6632 | AQ83: =AQ80+AQ82 -> -5641.6632 | AR83: =AR80+AR82 -> -3721.7637 | AS83: =AS80+AS82 -> -3721.7637 | AT83: =AT80+AT82 -> -3721.7637 | ... BZ83: =BZ80+BZ82 -> -3721.7637
A85: delta | AM85: =AM86-AM83 -> 3920.6262 | AN85: =AN86-AN83 -> 2833.0321 | AO85: =AO86-AO83 -> 4990.6241 | AP85: =AP86-AP83 -> 5707.709 | AQ85: =AP85 -> 5707.709 | AR85: =AR86-AR83 -> 3783.8485 | AS85: =MROUND(AR85, 100) -> 3800 | AT85: =MROUND(AS85, 100) -> 3800 | AU85: =MROUND(AT85, 100) -> 3800 | AV85: =AU85 -> 3800 | AW85: =MROUND(AV85, 100) -> 3800 | AX85: =MROUND(AW85, 100) -> 3800 | AY85: =MROUND(AX85, 100) -> 3800 | AZ85: =MROUND(AY85, 100) -> 3800 | BA85: =AZ85 -> 3800 | BB85: =MROUND(BA85, 100) -> 3800 | BC85: =MROUND(BB85, 100) -> 3800 | BD85: =MROUND(BC85, 100) -> 3800 | BE85: =MROUND(BD85, 100) -> 3800 | BF85: =BE85 -> 3800 | BG85: =MROUND(BF85, 100) -> 3800 | BH85: =MROUND(BG85, 100) -> 3800 | BI85: =MROUND(BH85, 100) -> 3800 | BJ85: =MROUND(BI85, 100) -> 3800 | BK85: =BJ85 -> 3800 | BL85: =MROUND(BK85, 100) -> 3800 | BM85: =MROUND(BL85, 100) -> 3800 | BN85: =MROUND(BM85, 100) -> 3800 | BO85: =MROUND(BN85, 100) -> 3800 | BP85: =BO85 -> 3800 | BQ85: =MROUND(BP85, 100) -> 3800 | BR85: =MROUND(BQ85, 100) -> 3800 | BS85: =MROUND(BR85, 100) -> 3800 | BT85: =MROUND(BS85, 100) -> 3800 | BU85: =BT85 -> 3800 | BV85: =MROUND(BU85, 100) -> 3800 | BW85: =MROUND(BV85, 100) -> 3800 | BX85: =MROUND(BW85, 100) -> 3800 | BY85: =MROUND(BX85, 100) -> 3800 | BZ85: =BY85 -> 3800
A86: SBG reported Alibaba position $m | AM86: ='Valuation & SBG NAV'!BB54*1000 -> 137.94055 | AN86: ='Valuation & SBG NAV'!BC54*1000 -> 66.853857 | AO86: ='Valuation & SBG NAV'!BD54*1000 -> 70.506945 | AP86: ='Valuation & SBG NAV'!BE54*1000 -> 66.045836 | AQ86: =AQ83+AQ85 -> 66.045836 | AR86: ='Valuation & SBG NAV'!BG54*1000 -> 62.084808 | AS86: =AS83+AS85 -> 78.236266 | AT86: =AT83+AT85 -> 78.236266 | AU86: =AU83+AU85 -> 78.236266 | AV86: =AV83+AV85 -> 78.236266 | AW86: =AW83+AW85 -> 78.236266 | AX86: =AX83+AX85 -> 78.236266 | AY86: =AY83+AY85 -> 78.236266 | AZ86: =AZ83+AZ85 -> 78.236266 | ... BZ86: =BZ83+BZ85 -> 78.236266
A88: T-Mobile | AP88: = need to check trailing VWAP call option expiry with IR.
A90: Ownership: | BB90: = we assume a final exit of remaining 16m T-Mobile US shares in F1Q26 to help finance further OpenAI investments.
AD91: = note SBG's intention to sell further 20m of T-Mobile shares to DT post-DT's sale of T-Mobile Netherlands. | AP91: = remaining DT call option is subject to trailing VWAP i.e., still true "economic" exposure to T-Mobile shares. | AX91: = SBG disclosed that it granted a "variable" call option to DT for 10m TMUS shares in Oct. '25.
